Workbook

Sheet Painel Executivo Macro
A1: ="STATUS FUSÃO | PAINEL EXECUTIVO – ATIVIDADES - Frentes acompanhadas:"&COUNTA('Resumo por Frente'!$A$5:$A$17) -> STATUS FUSÃO | PAINEL EXECUTIVO – ATIVIDADES - Frentes acompanhadas:13
A3: Leitura do andamento das atividades Macro | Canceladas incluídas no total e fora do cálculo percentual
A5: Andamento das atividades Macro | K5: ="Total: "&COUNTIF('Atividades Micro'!$G$2:$G$554,"Macro") -> Total: 97
A6: Não iniciado | C6: Em andamento | E6: Testes QA | G6: Bloqueado | I6: Cancelado | K6: Finalizado
A7: =COUNTIFS('Atividades Micro'!$G$2:$G$554,"Macro",'Atividades Micro'!$J$2:$J$554,"Não iniciado") -> 25 | C7: =COUNTIFS('Atividades Micro'!$G$2:$G$554,"Macro",'Atividades Micro'!$J$2:$J$554,"Em andamento")-COUNTIFS('Atividades Micro'!$G$2:$G$554,"Micro",'Atividades Micro'!$E$2:$E$554,"*QA*",'Atividades Micro'!$J$2:$J$554,"Em andamento") -> 18 | E7: =COUNTIFS('Atividades Micro'!$G$2:$G$554,"Micro",'Atividades Micro'!$E$2:$E$554,"*QA*",'Atividades Micro'!$J$2:$J$554,"Em andamento") -> 1 | G7: =COUNTIFS('Atividades Micro'!$G$2:$G$554,"Macro",'Atividades Micro'!$J$2:$J$554,"Bloqueado") -> 12 | I7: =COUNTIFS('Atividades Micro'!$G$2:$G$554,"Macro",'Atividades Micro'!$J$2:$J$554,"Cancelado") -> 11 | K7: =COUNTIFS('Atividades Micro'!$G$2:$G$554,"Macro",'Atividades Micro'!$J$2:$J$554,"Finalizado") -> 30
A8: =IF(COUNTIFS('Atividades Micro'!$G$2:$G$554,"Macro",'Atividades Micro'!$J$2:$J$554,"<>Cancelado")<=0,0,COUNTIFS('Atividades Micro'!$G$2:$G$554,"Macro",'Atividades Micro'!$J$2:$J$554,"Não iniciado")/COUNTIFS('Atividades Micro'!$G$2:$G$554,"Macro",'Atividades Micro'!$J$2:$J$554,"<>Cancelado")) -> 0.29069767 | C8: =IF(COUNTIFS('Atividades Micro'!$G$2:$G$554,"Macro",'Atividades Micro'!$J$2:$J$554,"<>Cancelado")<=0,0,C7/COUNTIFS('Atividades Micro'!$G$2:$G$554,"Macro",'Atividades Micro'!$J$2:$J$554,"<>Cancelado")) -> 0.20930233 | E8: =IF(COUNTIFS('Atividades Micro'!$G$2:$G$554,"Macro",'Atividades Micro'!$J$2:$J$554,"<>Cancelado")<=0,0,E7/COUNTIFS('Atividades Micro'!$G$2:$G$554,"Macro",'Atividades Micro'!$J$2:$J$554,"<>Cancelado")) -> 0.011627907 | G8: =IF(COUNTIFS('Atividades Micro'!$G$2:$G$554,"Macro",'Atividades Micro'!$J$2:$J$554,"<>Cancelado")<=0,0,COUNTIFS('Atividades Micro'!$G$2:$G$554,"Macro",'Atividades Micro'!$J$2:$J$554,"Bloqueado")/COUNTIFS('Atividades Micro'!$G$2:$G$554,"Macro",'Atividades Micro'!$J$2:$J$554,"<>Cancelado")) -> 0.13953488 | I8: Fora do cálculo | K8: =IF(COUNTIFS('Atividades Micro'!$G$2:$G$554,"Macro",'Atividades Micro'!$J$2:$J$554,"<>Cancelado")<=0,0,COUNTIFS('Atividades Micro'!$G$2:$G$554,"Macro",'Atividades Micro'!$J$2:$J$554,"Finalizado")/COUNTIFS('Atividades Micro'!$G$2:$G$554,"Macro",'Atividades Micro'!$J$2:$J$554,"<>Cancelado")) -> 0.34883721
A11: Evolução das atividades Macro
A12: Atividade macro | B12: Frente | C12: Data Planejada | D12: Atividades macro | E12: Não iniciado | F12: Em andamento | G12: Testes QA | H12: Bloqueado | I12: Cancelado | J12: Finalizado | K12: % concluído
A13: ='Atividades Macro'!$B2 -> Infraestrutura - Fusão - Grupo PetzCobasi | B13: ='Atividades Macro'!$C2 -> (Migração ERP) Infraestrutura | C13: =IF('Atividades Macro'!$D2="","",'Atividades Macro'!$D2) -> 46374 | D13: ='Atividades Macro'!$F2 -> 12 | E13: =COUNTIFS('Atividades Micro'!$A$2:$A$554,$B13,'Atividades Micro'!$G$2:$G$554,"Macro",'Atividades Micro'!$J$2:$J$554,E$12) -> 7 | F13: =COUNTIFS('Atividades Micro'!$A$2:$A$554,$B13,'Atividades Micro'!$G$2:$G$554,"Macro",'Atividades Micro'!$J$2:$J$554,"Em andamento")-COUNTIFS('Atividades Micro'!$A$2:$A$554,$B13,'Atividades Micro'!$G$2:$G$554,"Micro",'Atividades Micro'!$E$2:$E$554,"*QA*",'Atividades Micro'!$J$2:$J$554,"Em andamento") -> 0 | G13: =COUNTIFS('Atividades Micro'!$A$2:$A$554,$B13,'Atividades Micro'!$G$2:$G$554,"Micro",'Atividades Micro'!$E$2:$E$554,"*QA*",'Atividades Micro'!$J$2:$J$554,"Em andamento") -> 0 | H13: =COUNTIFS('Atividades Micro'!$A$2:$A$554,$B13,'Atividades Micro'!$G$2:$G$554,"Macro",'Atividades Micro'!$J$2:$J$554,H$12) -> 0 | I13: =COUNTIFS('Atividades Micro'!$A$2:$A$554,$B13,'Atividades Micro'!$G$2:$G$554,"Macro",'Atividades Micro'!$J$2:$J$554,I$12) -> 0 | J13: =COUNTIFS('Atividades Micro'!$A$2:$A$554,$B13,'Atividades Micro'!$G$2:$G$554,"Macro",'Atividades Micro'!$J$2:$J$554,J$12) -> 5 | K13: 0.41666667
A14: ='Atividades Macro'!$B3 -> Migração de Dados/Saldo Inicial | Fusão Petz Cobasi | B14: ='Atividades Macro'!$C3 -> (Migração ERP) Dados Mestres | C14: =IF('Atividades Macro'!$D3="","",'Atividades Macro'!$D3) -> 46346 | D14: ='Atividades Macro'!$F3 -> 14 | E14: =COUNTIFS('Atividades Micro'!$A$2:$A$554,$B14,'Atividades Micro'!$G$2:$G$554,"Macro",'Atividades Micro'!$J$2:$J$554,E$12) -> 10 | F14: =COUNTIFS('Atividades Micro'!$A$2:$A$554,$B14,'Atividades Micro'!$G$2:$G$554,"Macro",'Atividades Micro'!$J$2:$J$554,"Em andamento")-COUNTIFS('Atividades Micro'!$A$2:$A$554,$B14,'Atividades Micro'!$G$2:$G$554,"Micro",'Atividades Micro'!$E$2:$E$554,"*QA*",'Atividades Micro'!$J$2:$J$554,"Em andamento") -> 0 | G14: =COUNTIFS('Atividades Micro'!$A$2:$A$554,$B14,'Atividades Micro'!$G$2:$G$554,"Micro",'Atividades Micro'!$E$2:$E$554,"*QA*",'Atividades Micro'!$J$2:$J$554,"Em andamento") -> 0 | H14: =COUNTIFS('Atividades Micro'!$A$2:$A$554,$B14,'Atividades Micro'!$G$2:$G$554,"Macro",'Atividades Micro'!$J$2:$J$554,H$12) -> 0 | I14: =COUNTIFS('Atividades Micro'!$A$2:$A$554,$B14,'Atividades Micro'!$G$2:$G$554,"Macro",'Atividades Micro'!$J$2:$J$554,I$12) -> 0 | J14: =COUNTIFS('Atividades Micro'!$A$2:$A$554,$B14,'Atividades Micro'!$G$2:$G$554,"Macro",'Atividades Micro'!$J$2:$J$554,J$12) -> 4 | K14: 0.25
A15: ='Atividades Macro'!$B4 -> Revisão de código e configurações | B15: ='Atividades Macro'!$C4 -> (Migração ERP) Refatoração / Fontes | C15: =IF('Atividades Macro'!$D4="","",'Atividades Macro'!$D4) -> 46272 | D15: ='Atividades Macro'!$F4 -> 9 | E15: =COUNTIFS('Atividades Micro'!$A$2:$A$554,$B15,'Atividades Micro'!$G$2:$G$554,"Macro",'Atividades Micro'!$J$2:$J$554,E$12) -> 1 | F15: =COUNTIFS('Atividades Micro'!$A$2:$A$554,$B15,'Atividades Micro'!$G$2:$G$554,"Macro",'Atividades Micro'!$J$2:$J$554,"Em andamento")-COUNTIFS('Atividades Micro'!$A$2:$A$554,$B15,'Atividades Micro'!$G$2:$G$554,"Micro",'Atividades Micro'!$E$2:$E$554,"*QA*",'Atividades Micro'!$J$2:$J$554,"Em andamento") -> 4 | G15: =COUNTIFS('Atividades Micro'!$A$2:$A$554,$B15,'Atividades Micro'!$G$2:$G$554,"Micro",'Atividades Micro'!$E$2:$E$554,"*QA*",'Atividades Micro'!$J$2:$J$554,"Em andamento") -> 0 | H15: =COUNTIFS('Atividades Micro'!$A$2:$A$554,$B15,'Atividades Micro'!$G$2:$G$554,"Macro",'Atividades Micro'!$J$2:$J$554,H$12) -> 0 | I15: =COUNTIFS('Atividades Micro'!$A$2:$A$554,$B15,'Atividades Micro'!$G$2:$G$554,"Macro",'Atividades Micro'!$J$2:$J$554,I$12) -> 1 | J15: =COUNTIFS('Atividades Micro'!$A$2:$A$554,$B15,'Atividades Micro'!$G$2:$G$554,"Macro",'Atividades Micro'!$J$2:$J$554,J$12) -> 3 | K15: 0.22222222
A16: ='Atividades Macro'!$B5 -> Sistemas Satelites | Fusão Petz Cobasi | B16: ='Atividades Macro'!$C5 -> (Migração ERP) Satélites | C16: =IF('Atividades Macro'!$D5="","",'Atividades Macro'!$D5) -> 46248 | D16: ='Atividades Macro'!$F5 -> 2 | E16: =COUNTIFS('Atividades Micro'!$A$2:$A$554,$B16,'Atividades Micro'!$G$2:$G$554,"Macro",'Atividades Micro'!$J$2:$J$554,E$12) -> 0 | F16: =COUNTIFS('Atividades Micro'!$A$2:$A$554,$B16,'Atividades Micro'!$G$2:$G$554,"Macro",'Atividades Micro'!$J$2:$J$554,"Em andamento")-COUNTIFS('Atividades Micro'!$A$2:$A$554,$B16,'Atividades Micro'!$G$2:$G$554,"Micro",'Atividades Micro'!$E$2:$E$554,"*QA*",'Atividades Micro'!$J$2:$J$554,"Em andamento") -> 1 | G16: =COUNTIFS('Atividades Micro'!$A$2:$A$554,$B16,'Atividades Micro'!$G$2:$G$554,"Micro",'Atividades Micro'!$E$2:$E$554,"*QA*",'Atividades Micro'!$J$2:$J$554,"Em andamento") -> 0 | H16: =COUNTIFS('Atividades Micro'!$A$2:$A$554,$B16,'Atividades Micro'!$G$2:$G$554,"Macro",'Atividades Micro'!$J$2:$J$554,H$12) -> 0 | I16: =COUNTIFS('Atividades Micro'!$A$2:$A$554,$B16,'Atividades Micro'!$G$2:$G$554,"Macro",'Atividades Micro'!$J$2:$J$554,I$12) -> 0 | J16: =COUNTIFS('Atividades Micro'!$A$2:$A$554,$B16,'Atividades Micro'!$G$2:$G$554,"Macro",'Atividades Micro'!$J$2:$J$554,J$12) -> 1 | K16: 0.5
A17: ='Atividades Macro'!$B6 -> FINANCEIRO | Fusão - Grupo Petz Cobasi | B17: ='Atividades Macro'!$C6 -> Financeiro | C17: =IF('Atividades Macro'!$D6="","",'Atividades Macro'!$D6) -> 46359 | D17: ='Atividades Macro'!$F6 -> 7 | E17: =COUNTIFS('Atividades Micro'!$A$2:$A$554,$B17,'Atividades Micro'!$G$2:$G$554,"Macro",'Atividades Micro'!$J$2:$J$554,E$12) -> 2 | F17: =COUNTIFS('Atividades Micro'!$A$2:$A$554,$B17,'Atividades Micro'!$G$2:$G$554,"Macro",'Atividades Micro'!$J$2:$J$554,"Em andamento")-COUNTIFS('Atividades Micro'!$A$2:$A$554,$B17,'Atividades Micro'!$G$2:$G$554,"Micro",'Atividades Micro'!$E$2:$E$554,"*QA*",'Atividades Micro'!$J$2:$J$554,"Em andamento") -> 2 | G17: =COUNTIFS('Atividades Micro'!$A$2:$A$554,$B17,'Atividades Micro'!$G$2:$G$554,"Micro",'Atividades Micro'!$E$2:$E$554,"*QA*",'Atividades Micro'!$J$2:$J$554,"Em andamento") -> 0 | H17: =COUNTIFS('Atividades Micro'!$A$2:$A$554,$B17,'Atividades Micro'!$G$2:$G$554,"Macro",'Atividades Micro'!$J$2:$J$554,H$12) -> 0 | I17: =COUNTIFS('Atividades Micro'!$A$2:$A$554,$B17,'Atividades Micro'!$G$2:$G$554,"Macro",'Atividades Micro'!$J$2:$J$554,I$12) -> 1 | J17: =COUNTIFS('Atividades Micro'!$A$2:$A$554,$B17,'Atividades Micro'!$G$2:$G$554,"Macro",'Atividades Micro'!$J$2:$J$554,J$12) -> 2 | K17: 0.1025641
A18: ='Atividades Macro'!$B7 -> (Financeiro) Aderência | B18: ='Atividades Macro'!$C7 -> Financeiro | C18: =IF('Atividades Macro'!$D7="","",'Atividades Macro'!$D7) -> 46238 | D18: ='Atividades Macro'!$F7 -> 3 | E18: =COUNTIFS('Atividades Micro'!$B$2:$B$554,$A18,'Atividades Micro'!$G$2:$G$554,"Macro",'Atividades Micro'!$J$2:$J$554,E$12) -> 0 | F18: =COUNTIFS('Atividades Micro'!$B$2:$B$554,$A18,'Atividades Micro'!$G$2:$G$554,"Macro",'Atividades Micro'!$J$2:$J$554,"Em andamento")-COUNTIFS('Atividades Micro'!$B$2:$B$554,$A18,'Atividades Micro'!$G$2:$G$554,"Micro",'Atividades Micro'!$E$2:$E$554,"*QA*",'Atividades Micro'!$J$2:$J$554,"Em andamento") -> 0 | G18: =COUNTIFS('Atividades Micro'!$B$2:$B$554,$A18,'Atividades Micro'!$G$2:$G$554,"Micro",'Atividades Micro'!$E$2:$E$554,"*QA*",'Atividades Micro'!$J$2:$J$554,"Em andamento") -> 0 | H18: =COUNTIFS('Atividades Micro'!$B$2:$B$554,$A18,'Atividades Micro'!$G$2:$G$554,"Macro",'Atividades Micro'!$J$2:$J$554,H$12) -> 0 | I18: =COUNTIFS('Atividades Micro'!$B$2:$B$554,$A18,'Atividades Micro'!$G$2:$G$554,"Macro",'Atividades Micro'!$J$2:$J$554,I$12) -> 1 | J18: =COUNTIFS('Atividades Micro'!$B$2:$B$554,$A18,'Atividades Micro'!$G$2:$G$554,"Macro",'Atividades Micro'!$J$2:$J$554,J$12) -> 2 | K18: 0.71428571
A19: ='Atividades Macro'!$B8 -> (Financeiro) Satélites | B19: ='Atividades Macro'!$C8 -> Financeiro | C19: =IF('Atividades Macro'!$D8="","",'Atividades Macro'!$D8) -> 46374 | D19: ='Atividades Macro'!$F8 -> 4 | E19: =COUNTIFS('Atividades Micro'!$B$2:$B$554,$A19,'Atividades Micro'!$G$2:$G$554,"Macro",'Atividades Micro'!$J$2:$J$554,E$12) -> 2 | F19: =COUNTIFS('Atividades Micro'!$B$2:$B$554,$A19,'Atividades Micro'!$G$2:$G$554,"Macro",'Atividades Micro'!$J$2:$J$554,"Em andamento")-COUNTIFS('Atividades Micro'!$B$2:$B$554,$A19,'Atividades Micro'!$G$2:$G$554,"Micro",'Atividades Micro'!$E$2:$E$554,"*QA*",'Atividades Micro'!$J$2:$J$554,"Em andamento") -> 2 | G19: =COUNTIFS('Atividades Micro'!$B$2:$B$554,$A19,'Atividades Micro'!$G$2:$G$554,"Micro",'Atividades Micro'!$E$2:$E$554,"*QA*",'Atividades Micro'!$J$2:$J$554,"Em andamento") -> 0 | H19: =COUNTIFS('Atividades Micro'!$B$2:$B$554,$A19,'Atividades Micro'!$G$2:$G$554,"Macro",'Atividades Micro'!$J$2:$J$554,H$12) -> 0 | I19: =COUNTIFS('Atividades Micro'!$B$2:$B$554,$A19,'Atividades Micro'!$G$2:$G$554,"Macro",'Atividades Micro'!$J$2:$J$554,I$12) -> 0 | J19: =COUNTIFS('Atividades Micro'!$B$2:$B$554,$A19,'Atividades Micro'!$G$2:$G$554,"Macro",'Atividades Micro'!$J$2:$J$554,J$12) -> 0 | K19: 0.042253521 | M19: * Gedi, Aptus e Nimbi
A20: ='Atividades Macro'!$B9 -> FISCAL | Fusão - Grupo Petz Cobasi | B20: ='Atividades Macro'!$C9 -> Fiscal | C20: =IF('Atividades Macro'!$D9="","",'Atividades Macro'!$D9) | D20: ='Atividades Macro'!$F9 -> 2 | E20: =COUNTIFS('Atividades Micro'!$A$2:$A$554,$B20,'Atividades Micro'!$G$2:$G$554,"Macro",'Atividades Micro'!$J$2:$J$554,E$12) -> 0 | F20: =COUNTIFS('Atividades Micro'!$A$2:$A$554,$B20,'Atividades Micro'!$G$2:$G$554,"Macro",'Atividades Micro'!$J$2:$J$554,"Em andamento")-COUNTIFS('Atividades Micro'!$A$2:$A$554,$B20,'Atividades Micro'!$G$2:$G$554,"Micro",'Atividades Micro'!$E$2:$E$554,"*QA*",'Atividades Micro'!$J$2:$J$554,"Em andamento") -> 1 | G20: =COUNTIFS('Atividades Micro'!$A$2:$A$554,$B20,'Atividades Micro'!$G$2:$G$554,"Micro",'Atividades Micro'!$E$2:$E$554,"*QA*",'Atividades Micro'!$J$2:$J$554,"Em andamento") -> 0 | H20: =COUNTIFS('Atividades Micro'!$A$2:$A$554,$B20,'Atividades Micro'!$G$2:$G$554,"Macro",'Atividades Micro'!$J$2:$J$554,H$12) -> 0 | I20: =COUNTIFS('Atividades Micro'!$A$2:$A$554,$B20,'Atividades Micro'!$G$2:$G$554,"Macro",'Atividades Micro'!$J$2:$J$554,I$12) -> 1 | J20: =COUNTIFS('Atividades Micro'!$A$2:$A$554,$B20,'Atividades Micro'!$G$2:$G$554,"Macro",'Atividades Micro'!$J$2:$J$554,J$12) -> 0 | K20: ='Atividades Macro'!$O$9 -> 0
A21: ='Atividades Macro'!$B11 -> (Fiscal) Satélites | B21: ='Atividades Macro'!$C11 -> Fiscal | C21: =IF('Atividades Macro'!$D11="","",'Atividades Macro'!$D11) -> 46379 | D21: ='Atividades Macro'!$F11 -> 1 | E21: =COUNTIFS('Atividades Micro'!$B$2:$B$554,$A21,'Atividades Micro'!$G$2:$G$554,"Macro",'Atividades Micro'!$J$2:$J$554,E$12) -> 0 | F21: =COUNTIFS('Atividades Micro'!$B$2:$B$554,$A21,'Atividades Micro'!$G$2:$G$554,"Macro",'Atividades Micro'!$J$2:$J$554,"Em andamento")-COUNTIFS('Atividades Micro'!$B$2:$B$554,$A21,'Atividades Micro'!$G$2:$G$554,"Micro",'Atividades Micro'!$E$2:$E$554,"*QA*",'Atividades Micro'!$J$2:$J$554,"Em andamento") -> 1 | G21: =COUNTIFS('Atividades Micro'!$B$2:$B$554,$A21,'Atividades Micro'!$G$2:$G$554,"Micro",'Atividades Micro'!$E$2:$E$554,"*QA*",'Atividades Micro'!$J$2:$J$554,"Em andamento") -> 0 | H21: =COUNTIFS('Atividades Micro'!$B$2:$B$554,$A21,'Atividades Micro'!$G$2:$G$554,"Macro",'Atividades Micro'!$J$2:$J$554,H$12) -> 0 | I21: =COUNTIFS('Atividades Micro'!$B$2:$B$554,$A21,'Atividades Micro'!$G$2:$G$554,"Macro",'Atividades Micro'!$J$2:$J$554,I$12) -> 0 | J21: =COUNTIFS('Atividades Micro'!$B$2:$B$554,$A21,'Atividades Micro'!$G$2:$G$554,"Macro",'Atividades Micro'!$J$2:$J$554,J$12) -> 0 | K21: 0 | M21: * Turin
A22: ='Atividades Macro'!$B10 -> (Fiscal) Aderência | B22: ='Atividades Macro'!$C10 -> Fiscal | C22: =IF('Atividades Macro'!$D10="","",'Atividades Macro'!$D10) | D22: ='Atividades Macro'!$F10 -> 1 | E22: =COUNTIFS('Atividades Micro'!$B$2:$B$554,$A21,'Atividades Micro'!$G$2:$G$554,"Macro",'Atividades Micro'!$J$2:$J$554,E$12) -> 0 | F22: =COUNTIFS('Atividades Micro'!$B$2:$B$554,$A22,'Atividades Micro'!$G$2:$G$554,"Macro",'Atividades Micro'!$J$2:$J$554,"Em andamento")-COUNTIFS('Atividades Micro'!$B$2:$B$554,$A22,'Atividades Micro'!$G$2:$G$554,"Micro",'Atividades Micro'!$E$2:$E$554,"*QA*",'Atividades Micro'!$J$2:$J$554,"Em andamento") -> 0 | G22: =COUNTIFS('Atividades Micro'!$B$2:$B$554,$A22,'Atividades Micro'!$G$2:$G$554,"Micro",'Atividades Micro'!$E$2:$E$554,"*QA*",'Atividades Micro'!$J$2:$J$554,"Em andamento") -> 0 | H22: =COUNTIFS('Atividades Micro'!$B$2:$B$554,$A22,'Atividades Micro'!$G$2:$G$554,"Macro",'Atividades Micro'!$J$2:$J$554,H$12) -> 0 | I22: =COUNTIFS('Atividades Micro'!$B$2:$B$554,$A22,'Atividades Micro'!$G$2:$G$554,"Macro",'Atividades Micro'!$J$2:$J$554,I$12) -> 1 | J22: =COUNTIFS('Atividades Micro'!$B$2:$B$554,$A22,'Atividades Micro'!$G$2:$G$554,"Macro",'Atividades Micro'!$J$2:$J$554,J$12) -> 0 | K22: 0
A23: ='Atividades Macro'!$B12 -> CONTÁBIL | Fusão - Grupo Petz Cobasi | B23: ='Atividades Macro'!$C12 -> Contábil | C23: =IF('Atividades Macro'!$D12="","",'Atividades Macro'!$D12) -> 46374 | D23: ='Atividades Macro'!$F12 -> 18 | E23: =COUNTIFS('Atividades Micro'!$A$2:$A$554,$B23,'Atividades Micro'!$G$2:$G$554,"Macro",'Atividades Micro'!$J$2:$J$554,E$12) -> 0 | F23: =COUNTIFS('Atividades Micro'!$A$2:$A$554,$B23,'Atividades Micro'!$G$2:$G$554,"Macro",'Atividades Micro'!$J$2:$J$554,"Em andamento")-COUNTIFS('Atividades Micro'!$A$2:$A$554,$B23,'Atividades Micro'!$G$2:$G$554,"Micro",'Atividades Micro'!$E$2:$E$554,"*QA*",'Atividades Micro'!$J$2:$J$554,"Em andamento") -> 2 | G23: =COUNTIFS('Atividades Micro'!$A$2:$A$554,$B23,'Atividades Micro'!$G$2:$G$554,"Micro",'Atividades Micro'!$E$2:$E$554,"*QA*",'Atividades Micro'!$J$2:$J$554,"Em andamento") -> 0 | H23: =COUNTIFS('Atividades Micro'!$A$2:$A$554,$B23,'Atividades Micro'!$G$2:$G$554,"Macro",'Atividades Micro'!$J$2:$J$554,H$12) -> 12 | I23: =COUNTIFS('Atividades Micro'!$A$2:$A$554,$B23,'Atividades Micro'!$G$2:$G$554,"Macro",'Atividades Micro'!$J$2:$J$554,I$12) -> 3 | J23: =COUNTIFS('Atividades Micro'!$A$2:$A$554,$B23,'Atividades Micro'!$G$2:$G$554,"Macro",'Atividades Micro'!$J$2:$J$554,J$12) -> 1 | K23: ='Atividades Macro'!$O$12 -> 0.088888889
A24: ='Atividades Macro'!$B13 -> (Contábil) Aderência | B24: ='Atividades Macro'!$C13 -> Contábil | C24: =IF('Atividades Macro'!$D13="","",'Atividades Macro'!$D13) -> 46339 | D24: ='Atividades Macro'!$F13 -> 15 | E24: =COUNTIFS('Atividades Micro'!$B$2:$B$554,$A24,'Atividades Micro'!$G$2:$G$554,"Macro",'Atividades Micro'!$J$2:$J$554,E$12) -> 0 | F24: =COUNTIFS('Atividades Micro'!$B$2:$B$554,$A24,'Atividades Micro'!$G$2:$G$554,"Macro",'Atividades Micro'!$J$2:$J$554,"Em andamento")-COUNTIFS('Atividades Micro'!$B$2:$B$554,$A24,'Atividades Micro'!$G$2:$G$554,"Micro",'Atividades Micro'!$E$2:$E$554,"*QA*",'Atividades Micro'!$J$2:$J$554,"Em andamento") -> 2 | G24: =COUNTIFS('Atividades Micro'!$B$2:$B$554,$A24,'Atividades Micro'!$G$2:$G$554,"Micro",'Atividades Micro'!$E$2:$E$554,"*QA*",'Atividades Micro'!$J$2:$J$554,"Em andamento") -> 0 | H24: =COUNTIFS('Atividades Micro'!$B$2:$B$554,$A24,'Atividades Micro'!$G$2:$G$554,"Macro",'Atividades Micro'!$J$2:$J$554,H$12) -> 12 | I24: =COUNTIFS('Atividades Micro'!$B$2:$B$554,$A24,'Atividades Micro'!$G$2:$G$554,"Macro",'Atividades Micro'!$J$2:$J$554,I$12) -> 0 | J24: =COUNTIFS('Atividades Micro'!$B$2:$B$554,$A24,'Atividades Micro'!$G$2:$G$554,"Macro",'Atividades Micro'!$J$2:$J$554,J$12) -> 1 | K24: 0.044444444
A25: ='Atividades Macro'!$B14 -> (Contábil) Satélites | B25: ='Atividades Macro'!$C14 -> Contábil | C25: =IF('Atividades Macro'!$D14="","",'Atividades Macro'!$D14) | D25: ='Atividades Macro'!$F14 -> 3 | E25: =COUNTIFS('Atividades Micro'!$B$2:$B$554,$A25,'Atividades Micro'!$G$2:$G$554,"Macro",'Atividades Micro'!$J$2:$J$554,E$12) -> 0 | F25: =COUNTIFS('Atividades Micro'!$B$2:$B$554,$A25,'Atividades Micro'!$G$2:$G$554,"Macro",'Atividades Micro'!$J$2:$J$554,"Em andamento")-COUNTIFS('Atividades Micro'!$B$2:$B$554,$A25,'Atividades Micro'!$G$2:$G$554,"Micro",'Atividades Micro'!$E$2:$E$554,"*QA*",'Atividades Micro'!$J$2:$J$554,"Em andamento") -> 0 | G25: =COUNTIFS('Atividades Micro'!$B$2:$B$554,$A25,'Atividades Micro'!$G$2:$G$554,"Micro",'Atividades Micro'!$E$2:$E$554,"*QA*",'Atividades Micro'!$J$2:$J$554,"Em andamento") -> 0 | H25: =COUNTIFS('Atividades Micro'!$B$2:$B$554,$A25,'Atividades Micro'!$G$2:$G$554,"Macro",'Atividades Micro'!$J$2:$J$554,H$12) -> 0 | I25: =COUNTIFS('Atividades Micro'!$B$2:$B$554,$A25,'Atividades Micro'!$G$2:$G$554,"Macro",'Atividades Micro'!$J$2:$J$554,I$12) -> 3 | J25: =COUNTIFS('Atividades Micro'!$B$2:$B$554,$A25,'Atividades Micro'!$G$2:$G$554,"Macro",'Atividades Micro'!$J$2:$J$554,J$12) -> 0 | K25: 0
A26: ='Atividades Macro'!$B15 -> SUPPLY| Fusão - Petz Cobasi | B26: ='Atividades Macro'!$C15 -> Supply | C26: =IF('Atividades Macro'!$D15="","",'Atividades Macro'!$D15) -> 46290 | D26: ='Atividades Macro'!$F15 -> 6 | E26: =COUNTIFS('Atividades Micro'!$A$2:$A$554,$B26,'Atividades Micro'!$G$2:$G$554,"Macro",'Atividades Micro'!$J$2:$J$554,E$12) -> 0 | F26: =COUNTIFS('Atividades Micro'!$A$2:$A$554,$B26,'Atividades Micro'!$G$2:$G$554,"Macro",'Atividades Micro'!$J$2:$J$554,"Em andamento")-COUNTIFS('Atividades Micro'!$A$2:$A$554,$B26,'Atividades Micro'!$G$2:$G$554,"Micro",'Atividades Micro'!$E$2:$E$554,"*QA*",'Atividades Micro'!$J$2:$J$554,"Em andamento") -> 4 | G26: =COUNTIFS('Atividades Micro'!$A$2:$A$554,$B26,'Atividades Micro'!$G$2:$G$554,"Micro",'Atividades Micro'!$E$2:$E$554,"*QA*",'Atividades Micro'!$J$2:$J$554,"Em andamento") -> 0 | H26: =COUNTIFS('Atividades Micro'!$A$2:$A$554,$B26,'Atividades Micro'!$G$2:$G$554,"Macro",'Atividades Micro'!$J$2:$J$554,H$12) -> 0 | I26: =COUNTIFS('Atividades Micro'!$A$2:$A$554,$B26,'Atividades Micro'!$G$2:$G$554,"Macro",'Atividades Micro'!$J$2:$J$554,I$12) -> 0 | J26: =COUNTIFS('Atividades Micro'!$A$2:$A$554,$B26,'Atividades Micro'!$G$2:$G$554,"Macro",'Atividades Micro'!$J$2:$J$554,J$12) -> 2 | K26: 0.26666667
A27: ='Atividades Macro'!$B16 -> (Supply) Aderência | B27: ='Atividades Macro'!$C16 -> Supply | C27: =IF('Atividades Macro'!$D16="","",'Atividades Macro'!$D16) -> 46276 | D27: ='Atividades Macro'!$F16 -> 2 | E27: =COUNTIFS('Atividades Micro'!$B$2:$B$554,$A27,'Atividades Micro'!$G$2:$G$554,"Macro",'Atividades Micro'!$J$2:$J$554,E$12) -> 0 | F27: =COUNTIFS('Atividades Micro'!$B$2:$B$554,$A27,'Atividades Micro'!$G$2:$G$554,"Macro",'Atividades Micro'!$J$2:$J$554,"Em andamento")-COUNTIFS('Atividades Micro'!$B$2:$B$554,$A27,'Atividades Micro'!$G$2:$G$554,"Micro",'Atividades Micro'!$E$2:$E$554,"*QA*",'Atividades Micro'!$J$2:$J$554,"Em andamento") -> 0 | G27: =COUNTIFS('Atividades Micro'!$B$2:$B$554,$A27,'Atividades Micro'!$G$2:$G$554,"Micro",'Atividades Micro'!$E$2:$E$554,"*QA*",'Atividades Micro'!$J$2:$J$554,"Em andamento") -> 0 | H27: =COUNTIFS('Atividades Micro'!$B$2:$B$554,$A27,'Atividades Micro'!$G$2:$G$554,"Macro",'Atividades Micro'!$J$2:$J$554,H$12) -> 0 | I27: =COUNTIFS('Atividades Micro'!$B$2:$B$554,$A27,'Atividades Micro'!$G$2:$G$554,"Macro",'Atividades Micro'!$J$2:$J$554,I$12) -> 0 | J27: =COUNTIFS('Atividades Micro'!$B$2:$B$554,$A27,'Atividades Micro'!$G$2:$G$554,"Macro",'Atividades Micro'!$J$2:$J$554,J$12) -> 2 | K27: 0.66666667
A28: ='Atividades Macro'!$B17 -> (Supply) Satélites | B28: ='Atividades Macro'!$C17 -> Supply | C28: =IF('Atividades Macro'!$D17="","",'Atividades Macro'!$D17) -> 46374 | D28: ='Atividades Macro'!$F17 -> 4 | E28: =COUNTIFS('Atividades Micro'!$B$2:$B$554,$A28,'Atividades Micro'!$G$2:$G$554,"Macro",'Atividades Micro'!$J$2:$J$554,E$12) -> 0 | F28: =COUNTIFS('Atividades Micro'!$B$2:$B$554,$A28,'Atividades Micro'!$G$2:$G$554,"Macro",'Atividades Micro'!$J$2:$J$554,"Em andamento")-COUNTIFS('Atividades Micro'!$B$2:$B$554,$A28,'Atividades Micro'!$G$2:$G$554,"Micro",'Atividades Micro'!$E$2:$E$554,"*QA*",'Atividades Micro'!$J$2:$J$554,"Em andamento") -> 4 | G28: =COUNTIFS('Atividades Micro'!$B$2:$B$554,$A28,'Atividades Micro'!$G$2:$G$554,"Micro",'Atividades Micro'!$E$2:$E$554,"*QA*",'Atividades Micro'!$J$2:$J$554,"Em andamento") -> 0 | H28: =COUNTIFS('Atividades Micro'!$B$2:$B$554,$A28,'Atividades Micro'!$G$2:$G$554,"Macro",'Atividades Micro'!$J$2:$J$554,H$12) -> 0 | I28: =COUNTIFS('Atividades Micro'!$B$2:$B$554,$A28,'Atividades Micro'!$G$2:$G$554,"Macro",'Atividades Micro'!$J$2:$J$554,I$12) -> 0 | J28: =COUNTIFS('Atividades Micro'!$B$2:$B$554,$A28,'Atividades Micro'!$G$2:$G$554,"Macro",'Atividades Micro'!$J$2:$J$554,J$12) -> 0 | K28: 0 | M28: * Portal do Fornecedor - TOTVS
A29: ='Atividades Macro'!$B18 -> CD | Fusão - Grupo Petz Cobasi | B29: ='Atividades Macro'!$C18 -> CD | C29: =IF('Atividades Macro'!$D18="","",'Atividades Macro'!$D18) -> 46374 | D29: ='Atividades Macro'!$F18 -> 18 | E29: =COUNTIFS('Atividades Micro'!$A$2:$A$554,$B29,'Atividades Micro'!$G$2:$G$554,"Macro",'Atividades Micro'!$J$2:$J$554,E$12) -> 3 | F29: =COUNTIFS('Atividades Micro'!$A$2:$A$554,$B29,'Atividades Micro'!$G$2:$G$554,"Macro",'Atividades Micro'!$J$2:$J$554,"Em andamento")-COUNTIFS('Atividades Micro'!$A$2:$A$554,$B29,'Atividades Micro'!$G$2:$G$554,"Micro",'Atividades Micro'!$E$2:$E$554,"*QA*",'Atividades Micro'!$J$2:$J$554,"Em andamento") -> -1 | G29: =COUNTIFS('Atividades Micro'!$A$2:$A$554,$B29,'Atividades Micro'!$G$2:$G$554,"Micro",'Atividades Micro'!$E$2:$E$554,"*QA*",'Atividades Micro'!$J$2:$J$554,"Em andamento") -> 1 | H29: =COUNTIFS('Atividades Micro'!$A$2:$A$554,$B29,'Atividades Micro'!$G$2:$G$554,"Macro",'Atividades Micro'!$J$2:$J$554,H$12) -> 0 | I29: =COUNTIFS('Atividades Micro'!$A$2:$A$554,$B29,'Atividades Micro'!$G$2:$G$554,"Macro",'Atividades Micro'!$J$2:$J$554,I$12) -> 4 | J29: =COUNTIFS('Atividades Micro'!$A$2:$A$554,$B29,'Atividades Micro'!$G$2:$G$554,"Macro",'Atividades Micro'!$J$2:$J$554,J$12) -> 11 | K29: 0.14285714
A30: ='Atividades Macro'!$B19 -> (CD) Aderência | B30: ='Atividades Macro'!$C19 -> CD | C30: =IF('Atividades Macro'!$D19="","",'Atividades Macro'!$D19) -> 46385 | D30: ='Atividades Macro'!$F19 -> 14 | E30: =COUNTIFS('Atividades Micro'!$B$2:$B$554,$A30,'Atividades Micro'!$G$2:$G$554,"Macro",'Atividades Micro'!$J$2:$J$554,E$12) -> 2 | F30: =COUNTIFS('Atividades Micro'!$B$2:$B$554,$A30,'Atividades Micro'!$G$2:$G$554,"Macro",'Atividades Micro'!$J$2:$J$554,"Em andamento")-COUNTIFS('Atividades Micro'!$B$2:$B$554,$A30,'Atividades Micro'!$G$2:$G$554,"Micro",'Atividades Micro'!$E$2:$E$554,"*QA*",'Atividades Micro'!$J$2:$J$554,"Em andamento") -> -1 | G30: =COUNTIFS('Atividades Micro'!$B$2:$B$554,$A30,'Atividades Micro'!$G$2:$G$554,"Micro",'Atividades Micro'!$E$2:$E$554,"*QA*",'Atividades Micro'!$J$2:$J$554,"Em andamento") -> 1 | H30: =COUNTIFS('Atividades Micro'!$B$2:$B$554,$A30,'Atividades Micro'!$G$2:$G$554,"Macro",'Atividades Micro'!$J$2:$J$554,H$12) -> 0 | I30: =COUNTIFS('Atividades Micro'!$B$2:$B$554,$A30,'Atividades Micro'!$G$2:$G$554,"Macro",'Atividades Micro'!$J$2:$J$554,I$12) -> 1 | J30: =COUNTIFS('Atividades Micro'!$B$2:$B$554,$A30,'Atividades Micro'!$G$2:$G$554,"Macro",'Atividades Micro'!$J$2:$J$554,J$12) -> 11 | K30: 0.15384615
A31: ='Atividades Macro'!$B20 -> (CD) Satélites | B31: ='Atividades Macro'!$C20 -> CD | C31: =IF('Atividades Macro'!$D20="","",'Atividades Macro'!$D20) -> 46279 | D31: ='Atividades Macro'!$F20 -> 4 | E31: =COUNTIFS('Atividades Micro'!$B$2:$B$554,$A31,'Atividades Micro'!$G$2:$G$554,"Macro",'Atividades Micro'!$J$2:$J$554,E$12) -> 1 | F31: =COUNTIFS('Atividades Micro'!$B$2:$B$554,$A31,'Atividades Micro'!$G$2:$G$554,"Macro",'Atividades Micro'!$J$2:$J$554,"Em andamento")-COUNTIFS('Atividades Micro'!$B$2:$B$554,$A31,'Atividades Micro'!$G$2:$G$554,"Micro",'Atividades Micro'!$E$2:$E$554,"*QA*",'Atividades Micro'!$J$2:$J$554,"Em andamento") -> 0 | G31: =COUNTIFS('Atividades Micro'!$B$2:$B$554,$A31,'Atividades Micro'!$G$2:$G$554,"Micro",'Atividades Micro'!$E$2:$E$554,"*QA*",'Atividades Micro'!$J$2:$J$554,"Em andamento") -> 0 | H31: =COUNTIFS('Atividades Micro'!$B$2:$B$554,$A31,'Atividades Micro'!$G$2:$G$554,"Macro",'Atividades Micro'!$J$2:$J$554,H$12) -> 0 | I31: =COUNTIFS('Atividades Micro'!$B$2:$B$554,$A31,'Atividades Micro'!$G$2:$G$554,"Macro",'Atividades Micro'!$J$2:$J$554,I$12) -> 3 | J31: =COUNTIFS('Atividades Micro'!$B$2:$B$554,$A31,'Atividades Micro'!$G$2:$G$554,"Macro",'Atividades Micro'!$J$2:$J$554,J$12) -> 0 | K31: 0.1 | M31: *(VPO) Open Tech, TMS Multi (CTE)
A32: ='Atividades Macro'!$B21 -> COMERCIAL | Fusão - Petz Cobasi | B32: ='Atividades Macro'!$C21 -> Comercial | C32: =IF('Atividades Macro'!$D21="","",'Atividades Macro'!$D21) -> 46304 | D32: ='Atividades Macro'!$F21 -> 4 | E32: =COUNTIFS('Atividades Micro'!$A$2:$A$554,$B32,'Atividades Micro'!$G$2:$G$554,"Macro",'Atividades Micro'!$J$2:$J$554,E$12) -> 2 | F32: =COUNTIFS('Atividades Micro'!$A$2:$A$554,$B32,'Atividades Micro'!$G$2:$G$554,"Macro",'Atividades Micro'!$J$2:$J$554,"Em andamento")-COUNTIFS('Atividades Micro'!$A$2:$A$554,$B32,'Atividades Micro'!$G$2:$G$554,"Micro",'Atividades Micro'!$E$2:$E$554,"*QA*",'Atividades Micro'!$J$2:$J$554,"Em andamento") -> 1 | G32: =COUNTIFS('Atividades Micro'!$A$2:$A$554,$B32,'Atividades Micro'!$G$2:$G$554,"Micro",'Atividades Micro'!$E$2:$E$554,"*QA*",'Atividades Micro'!$J$2:$J$554,"Em andamento") -> 0 | H32: =COUNTIFS('Atividades Micro'!$A$2:$A$554,$B32,'Atividades Micro'!$G$2:$G$554,"Macro",'Atividades Micro'!$J$2:$J$554,H$12) -> 0 | I32: =COUNTIFS('Atividades Micro'!$A$2:$A$554,$B32,'Atividades Micro'!$G$2:$G$554,"Macro",'Atividades Micro'!$J$2:$J$554,I$12) -> 0 | J32: =COUNTIFS('Atividades Micro'!$A$2:$A$554,$B32,'Atividades Micro'!$G$2:$G$554,"Macro",'Atividades Micro'!$J$2:$J$554,J$12) -> 1 | K32: 0.090909091
A33: ='Atividades Macro'!$B22 -> (Comercial) Aderência | B33: ='Atividades Macro'!$C22 -> Comercial | C33: =IF('Atividades Macro'!$D22="","",'Atividades Macro'!$D22) -> 46279 | D33: ='Atividades Macro'!$F22 -> 2 | E33: =COUNTIFS('Atividades Micro'!$B$2:$B$554,$A33,'Atividades Micro'!$G$2:$G$554,"Macro",'Atividades Micro'!$J$2:$J$554,E$12) -> 1 | F33: =COUNTIFS('Atividades Micro'!$B$2:$B$554,$A33,'Atividades Micro'!$G$2:$G$554,"Macro",'Atividades Micro'!$J$2:$J$554,"Em andamento")-COUNTIFS('Atividades Micro'!$B$2:$B$554,$A33,'Atividades Micro'!$G$2:$G$554,"Micro",'Atividades Micro'!$E$2:$E$554,"*QA*",'Atividades Micro'!$J$2:$J$554,"Em andamento") -> 0 | G33: =COUNTIFS('Atividades Micro'!$B$2:$B$554,$A33,'Atividades Micro'!$G$2:$G$554,"Micro",'Atividades Micro'!$E$2:$E$554,"*QA*",'Atividades Micro'!$J$2:$J$554,"Em andamento") -> 0 | H33: =COUNTIFS('Atividades Micro'!$B$2:$B$554,$A33,'Atividades Micro'!$G$2:$G$554,"Macro",'Atividades Micro'!$J$2:$J$554,H$12) -> 0 | I33: =COUNTIFS('Atividades Micro'!$B$2:$B$554,$A33,'Atividades Micro'!$G$2:$G$554,"Macro",'Atividades Micro'!$J$2:$J$554,I$12) -> 0 | J33: =COUNTIFS('Atividades Micro'!$B$2:$B$554,$A33,'Atividades Micro'!$G$2:$G$554,"Macro",'Atividades Micro'!$J$2:$J$554,J$12) -> 1 | K33: 0.16666667
A34: ='Atividades Macro'!$B23 -> (Comercial) Satélites | B34: ='Atividades Macro'!$C23 -> Comercial | C34: =IF('Atividades Macro'!$D23="","",'Atividades Macro'!$D23) -> 46301 | D34: ='Atividades Macro'!$F23 -> 2 | E34: =COUNTIFS('Atividades Micro'!$B$2:$B$554,$A34,'Atividades Micro'!$G$2:$G$554,"Macro",'Atividades Micro'!$J$2:$J$554,E$12) -> 1 | F34: =COUNTIFS('Atividades Micro'!$B$2:$B$554,$A34,'Atividades Micro'!$G$2:$G$554,"Macro",'Atividades Micro'!$J$2:$J$554,"Em andamento")-COUNTIFS('Atividades Micro'!$B$2:$B$554,$A34,'Atividades Micro'!$G$2:$G$554,"Micro",'Atividades Micro'!$E$2:$E$554,"*QA*",'Atividades Micro'!$J$2:$J$554,"Em andamento") -> 1 | G34: =COUNTIFS('Atividades Micro'!$B$2:$B$554,$A34,'Atividades Micro'!$G$2:$G$554,"Micro",'Atividades Micro'!$E$2:$E$554,"*QA*",'Atividades Micro'!$J$2:$J$554,"Em andamento") -> 0 | H34: =COUNTIFS('Atividades Micro'!$B$2:$B$554,$A34,'Atividades Micro'!$G$2:$G$554,"Macro",'Atividades Micro'!$J$2:$J$554,H$12) -> 0 | I34: =COUNTIFS('Atividades Micro'!$B$2:$B$554,$A34,'Atividades Micro'!$G$2:$G$554,"Macro",'Atividades Micro'!$J$2:$J$554,I$12) -> 0 | J34: =COUNTIFS('Atividades Micro'!$B$2:$B$554,$A34,'Atividades Micro'!$G$2:$G$554,"Macro",'Atividades Micro'!$J$2:$J$554,J$12) -> 0 | K34: 0 | M34: *SOLUTIS
A35: ='Atividades Macro'!$B24 -> TOTVS / RM | Fusão Petz Cobasi | B35: ='Atividades Macro'!$C24 -> TOTVS RM | C35: =IF('Atividades Macro'!$D24="","",'Atividades Macro'!$D24) -> 46321 | D35: ='Atividades Macro'!$F24 -> 1 | E35: =COUNTIFS('Atividades Micro'!$A$2:$A$554,$B35,'Atividades Micro'!$G$2:$G$554,"Macro",'Atividades Micro'!$J$2:$J$554,E$12) -> 0 | F35: =COUNTIFS('Atividades Micro'!$A$2:$A$554,$B35,'Atividades Micro'!$G$2:$G$554,"Macro",'Atividades Micro'!$J$2:$J$554,"Em andamento")-COUNTIFS('Atividades Micro'!$A$2:$A$554,$B35,'Atividades Micro'!$G$2:$G$554,"Micro",'Atividades Micro'!$E$2:$E$554,"*QA*",'Atividades Micro'!$J$2:$J$554,"Em andamento") -> 1 | G35: =COUNTIFS('Atividades Micro'!$A$2:$A$554,$B35,'Atividades Micro'!$G$2:$G$554,"Micro",'Atividades Micro'!$E$2:$E$554,"*QA*",'Atividades Micro'!$J$2:$J$554,"Em andamento") -> 0 | H35: =COUNTIFS('Atividades Micro'!$A$2:$A$554,$B35,'Atividades Micro'!$G$2:$G$554,"Macro",'Atividades Micro'!$J$2:$J$554,H$12) -> 0 | I35: =COUNTIFS('Atividades Micro'!$A$2:$A$554,$B35,'Atividades Micro'!$G$2:$G$554,"Macro",'Atividades Micro'!$J$2:$J$554,I$12) -> 0 | J35: =COUNTIFS('Atividades Micro'!$A$2:$A$554,$B35,'Atividades Micro'!$G$2:$G$554,"Macro",'Atividades Micro'!$J$2:$J$554,J$12) -> 0 | K35: 0.1
A36: ='Atividades Macro'!$B25 -> (TOTVS RM) Aderência | B36: ='Atividades Macro'!$C25 -> TOTVS RM | C36: =IF('Atividades Macro'!$D25="","",'Atividades Macro'!$D25) -> 46342 | D36: ='Atividades Macro'!$F25 -> 1 | E36: =COUNTIFS('Atividades Micro'!$B$2:$B$554,$A36,'Atividades Micro'!$G$2:$G$554,"Macro",'Atividades Micro'!$J$2:$J$554,E$12) -> 0 | F36: =COUNTIFS('Atividades Micro'!$B$2:$B$554,$A36,'Atividades Micro'!$G$2:$G$554,"Macro",'Atividades Micro'!$J$2:$J$554,"Em andamento")-COUNTIFS('Atividades Micro'!$B$2:$B$554,$A36,'Atividades Micro'!$G$2:$G$554,"Micro",'Atividades Micro'!$E$2:$E$554,"*QA*",'Atividades Micro'!$J$2:$J$554,"Em andamento") -> 1 | G36: =COUNTIFS('Atividades Micro'!$B$2:$B$554,$A36,'Atividades Micro'!$G$2:$G$554,"Micro",'Atividades Micro'!$E$2:$E$554,"*QA*",'Atividades Micro'!$J$2:$J$554,"Em andamento") -> 0 | H36: =COUNTIFS('Atividades Micro'!$B$2:$B$554,$A36,'Atividades Micro'!$G$2:$G$554,"Macro",'Atividades Micro'!$J$2:$J$554,H$12) -> 0 | I36: =COUNTIFS('Atividades Micro'!$B$2:$B$554,$A36,'Atividades Micro'!$G$2:$G$554,"Macro",'Atividades Micro'!$J$2:$J$554,I$12) -> 0 | J36: =COUNTIFS('Atividades Micro'!$B$2:$B$554,$A36,'Atividades Micro'!$G$2:$G$554,"Macro",'Atividades Micro'!$J$2:$J$554,J$12) -> 0 | K36: 0.1
A37: ='Atividades Macro'!$B26 -> ZANTHUS PDV | Fusão Petz Cobasi | B37: ='Atividades Macro'!$C26 -> Zanthus | C37: =IF('Atividades Macro'!$D26="","",'Atividades Macro'!$D26) -> 46337 | D37: ='Atividades Macro'!$F26 -> 1 | E37: =COUNTIFS('Atividades Micro'!$A$2:$A$554,$B37,'Atividades Micro'!$G$2:$G$554,"Macro",'Atividades Micro'!$J$2:$J$554,E$12) -> 0 | F37: =COUNTIFS('Atividades Micro'!$A$2:$A$554,$B37,'Atividades Micro'!$G$2:$G$554,"Macro",'Atividades Micro'!$J$2:$J$554,"Em andamento")-COUNTIFS('Atividades Micro'!$A$2:$A$554,$B37,'Atividades Micro'!$G$2:$G$554,"Micro",'Atividades Micro'!$E$2:$E$554,"*QA*",'Atividades Micro'!$J$2:$J$554,"Em andamento") -> 1 | G37: =COUNTIFS('Atividades Micro'!$A$2:$A$554,$B37,'Atividades Micro'!$G$2:$G$554,"Micro",'Atividades Micro'!$E$2:$E$554,"*QA*",'Atividades Micro'!$J$2:$J$554,"Em andamento") -> 0 | H37: =COUNTIFS('Atividades Micro'!$A$2:$A$554,$B37,'Atividades Micro'!$G$2:$G$554,"Macro",'Atividades Micro'!$J$2:$J$554,H$12) -> 0 | I37: =COUNTIFS('Atividades Micro'!$A$2:$A$554,$B37,'Atividades Micro'!$G$2:$G$554,"Macro",'Atividades Micro'!$J$2:$J$554,I$12) -> 0 | J37: =COUNTIFS('Atividades Micro'!$A$2:$A$554,$B37,'Atividades Micro'!$G$2:$G$554,"Macro",'Atividades Micro'!$J$2:$J$554,J$12) -> 0 | K37: 0.26666667
A38: ='Atividades Macro'!$B27 -> (Zanthus) Aderência | B38: ='Atividades Macro'!$C27 -> Zanthus | C38: =IF('Atividades Macro'!$D27="","",'Atividades Macro'!$D27) -> 46338 | D38: ='Atividades Macro'!$F27 -> 1 | E38: =COUNTIFS('Atividades Micro'!$B$2:$B$554,$A38,'Atividades Micro'!$G$2:$G$554,"Macro",'Atividades Micro'!$J$2:$J$554,E$12) -> 0 | F38: =COUNTIFS('Atividades Micro'!$B$2:$B$554,$A38,'Atividades Micro'!$G$2:$G$554,"Macro",'Atividades Micro'!$J$2:$J$554,"Em andamento")-COUNTIFS('Atividades Micro'!$B$2:$B$554,$A38,'Atividades Micro'!$G$2:$G$554,"Micro",'Atividades Micro'!$E$2:$E$554,"*QA*",'Atividades Micro'!$J$2:$J$554,"Em andamento") -> 1 | G38: =COUNTIFS('Atividades Micro'!$B$2:$B$554,$A38,'Atividades Micro'!$G$2:$G$554,"Micro",'Atividades Micro'!$E$2:$E$554,"*QA*",'Atividades Micro'!$J$2:$J$554,"Em andamento") -> 0 | H38: =COUNTIFS('Atividades Micro'!$B$2:$B$554,$A38,'Atividades Micro'!$G$2:$G$554,"Macro",'Atividades Micro'!$J$2:$J$554,H$12) -> 0 | I38: =COUNTIFS('Atividades Micro'!$B$2:$B$554,$A38,'Atividades Micro'!$G$2:$G$554,"Macro",'Atividades Micro'!$J$2:$J$554,I$12) -> 0 | J38: =COUNTIFS('Atividades Micro'!$B$2:$B$554,$A38,'Atividades Micro'!$G$2:$G$554,"Macro",'Atividades Micro'!$J$2:$J$554,J$12) -> 0 | K38: 0.26666667
A39: ='Atividades Macro'!$B28 -> OPERAÇÕES | Fusão - Petz Cobasi | B39: ='Atividades Macro'!$C28 -> Operações | C39: =IF('Atividades Macro'!$D28="","",'Atividades Macro'!$D28) -> 46288 | D39: ='Atividades Macro'!$F28 -> 2 | E39: =COUNTIFS('Atividades Micro'!$A$2:$A$554,$B39,'Atividades Micro'!$G$2:$G$554,"Macro",'Atividades Micro'!$J$2:$J$554,E$12) -> 0 | F39: =COUNTIFS('Atividades Micro'!$A$2:$A$554,$B39,'Atividades Micro'!$G$2:$G$554,"Macro",'Atividades Micro'!$J$2:$J$554,"Em andamento")-COUNTIFS('Atividades Micro'!$A$2:$A$554,$B39,'Atividades Micro'!$G$2:$G$554,"Micro",'Atividades Micro'!$E$2:$E$554,"*QA*",'Atividades Micro'!$J$2:$J$554,"Em andamento") -> 1 | G39: =COUNTIFS('Atividades Micro'!$A$2:$A$554,$B39,'Atividades Micro'!$G$2:$G$554,"Micro",'Atividades Micro'!$E$2:$E$554,"*QA*",'Atividades Micro'!$J$2:$J$554,"Em andamento") -> 0 | H39: =COUNTIFS('Atividades Micro'!$A$2:$A$554,$B39,'Atividades Micro'!$G$2:$G$554,"Macro",'Atividades Micro'!$J$2:$J$554,H$12) -> 0 | I39: =COUNTIFS('Atividades Micro'!$A$2:$A$554,$B39,'Atividades Micro'!$G$2:$G$554,"Macro",'Atividades Micro'!$J$2:$J$554,I$12) -> 1 | J39: =COUNTIFS('Atividades Micro'!$A$2:$A$554,$B39,'Atividades Micro'!$G$2:$G$554,"Macro",'Atividades Micro'!$J$2:$J$554,J$12) -> 0 | K39: 0
A40: ='Atividades Macro'!$B29 -> (Operações) Satélites | B40: ='Atividades Macro'!$C29 -> Operações | C40: =IF('Atividades Macro'!$D29="","",'Atividades Macro'!$D29) -> 46352 | D40: ='Atividades Macro'!$F29 -> 2 | E40: =COUNTIFS('Atividades Micro'!$B$2:$B$554,$A40,'Atividades Micro'!$G$2:$G$554,"Macro",'Atividades Micro'!$J$2:$J$554,E$12) -> 0 | F40: =COUNTIFS('Atividades Micro'!$B$2:$B$554,$A40,'Atividades Micro'!$G$2:$G$554,"Macro",'Atividades Micro'!$J$2:$J$554,"Em andamento")-COUNTIFS('Atividades Micro'!$B$2:$B$554,$A40,'Atividades Micro'!$G$2:$G$554,"Micro",'Atividades Micro'!$E$2:$E$554,"*QA*",'Atividades Micro'!$J$2:$J$554,"Em andamento") -> 1 | G40: =COUNTIFS('Atividades Micro'!$B$2:$B$554,$A40,'Atividades Micro'!$G$2:$G$554,"Micro",'Atividades Micro'!$E$2:$E$554,"*QA*",'Atividades Micro'!$J$2:$J$554,"Em andamento") -> 0 | H40: =COUNTIFS('Atividades Micro'!$B$2:$B$554,$A40,'Atividades Micro'!$G$2:$G$554,"Macro",'Atividades Micro'!$J$2:$J$554,H$12) -> 0 | I40: =COUNTIFS('Atividades Micro'!$B$2:$B$554,$A40,'Atividades Micro'!$G$2:$G$554,"Macro",'Atividades Micro'!$J$2:$J$554,I$12) -> 1 | J40: =COUNTIFS('Atividades Micro'!$B$2:$B$554,$A40,'Atividades Micro'!$G$2:$G$554,"Macro",'Atividades Micro'!$J$2:$J$554,J$12) -> 0 | K40: 0 | M40: * Tecsus
A55: A aba apresenta somente o andamento das atividades Macro. Canceladas permanecem na quantidade total e na coluna própria, mas não compõem o denominador da % concluída. Percentuais em vermelho indicam Data Planejada alcançada ou vencida com entrega pendente.

Sheet Painel Executivo Micro
A1: ="STATUS FUSÃO | PAINEL EXECUTIVO – ATIVIDADES - Frentes acompanhadas:"&COUNTA('Resumo por Frente'!$A$5:$A$17) -> STATUS FUSÃO | PAINEL EXECUTIVO – ATIVIDADES - Frentes acompanhadas:13
A3: Leitura do andamento das atividades Micro | Canceladas fora do total ativo e do cálculo percentual
A5: Andamento das atividades Micro | K5: ="Total: "&COUNTIFS('Atividades Micro'!$G$2:$G$554,"Micro",'Atividades Micro'!$J$2:$J$554,"<>Cancelado") -> Total: 215
A6: Não iniciado | C6: Em andamento | E6: Testes QA | G6: Bloqueado | I6: Cancelado | K6: Finalizado
A7: =COUNTIFS('Atividades Micro'!$G$2:$G$554,"Micro",'Atividades Micro'!$J$2:$J$554,"Não iniciado") -> 48 | C7: =COUNTIFS('Atividades Micro'!$G$2:$G$554,"Micro",'Atividades Micro'!$J$2:$J$554,"Em andamento",'Atividades Micro'!$E$2:$E$554,"<>*QA*") -> 24 | E7: =COUNTIFS('Atividades Micro'!$G$2:$G$554,"Micro",'Atividades Micro'!$E$2:$E$554,"*QA*",'Atividades Micro'!$J$2:$J$554,"Em andamento") -> 1 | G7: =COUNTIFS('Atividades Micro'!$G$2:$G$554,"Micro",'Atividades Micro'!$J$2:$J$554,"Bloqueado") -> 25 | I7: =COUNTIFS('Atividades Micro'!$G$2:$G$554,"Micro",'Atividades Micro'!$J$2:$J$554,"Cancelado") -> 31 | K7: =COUNTIFS('Atividades Micro'!$G$2:$G$554,"Micro",'Atividades Micro'!$J$2:$J$554,"Finalizado") -> 117
A8: =IF(COUNTIFS('Atividades Micro'!$G$2:$G$554,"Micro",'Atividades Micro'!$J$2:$J$554,"<>Cancelado")<=0,0,COUNTIFS('Atividades Micro'!$G$2:$G$554,"Micro",'Atividades Micro'!$J$2:$J$554,"Não iniciado")/COUNTIFS('Atividades Micro'!$G$2:$G$554,"Micro",'Atividades Micro'!$J$2:$J$554,"<>Cancelado")) -> 0.22325581 | C8: =IF(COUNTIFS('Atividades Micro'!$G$2:$G$554,"Micro",'Atividades Micro'!$J$2:$J$554,"<>Cancelado")<=0,0,C7/COUNTIFS('Atividades Micro'!$G$2:$G$554,"Micro",'Atividades Micro'!$J$2:$J$554,"<>Cancelado")) -> 0.11162791 | E8: =IF(COUNTIFS('Atividades Micro'!$G$2:$G$554,"Micro",'Atividades Micro'!$J$2:$J$554,"<>Cancelado")<=0,0,E7/COUNTIFS('Atividades Micro'!$G$2:$G$554,"Micro",'Atividades Micro'!$J$2:$J$554,"<>Cancelado")) -> 0.0046511628 | G8: =IF(COUNTIFS('Atividades Micro'!$G$2:$G$554,"Micro",'Atividades Micro'!$J$2:$J$554,"<>Cancelado")<=0,0,COUNTIFS('Atividades Micro'!$G$2:$G$554,"Micro",'Atividades Micro'!$J$2:$J$554,"Bloqueado")/COUNTIFS('Atividades Micro'!$G$2:$G$554,"Micro",'Atividades Micro'!$J$2:$J$554,"<>Cancelado")) -> 0.11627907 | I8: Fora do cálculo | K8: =IF(COUNTIFS('Atividades Micro'!$G$2:$G$554,"Micro",'Atividades Micro'!$J$2:$J$554,"<>Cancelado")<=0,0,COUNTIFS('Atividades Micro'!$G$2:$G$554,"Micro",'Atividades Micro'!$J$2:$J$554,"Finalizado")/COUNTIFS('Atividades Micro'!$G$2:$G$554,"Micro",'Atividades Micro'!$J$2:$J$554,"<>Cancelado")) -> 0.54418605
A11: Evolução das atividades Micro — Aderência e Satélites
A12: Linha de atividade micro | B12: Frente | C12: Data Planejada | D12: Atividades micro | E12: Não iniciado | F12: Em andamento | G12: Testes QA | H12: Bloqueado | I12: Cancelado | J12: Finalizado | K12: % concluído
A13: ='Atividades Macro'!$B7 -> (Financeiro) Aderência | B13: ='Atividades Macro'!$C7 -> Financeiro | C13: =IF('Atividades Macro'!$D7="","",'Atividades Macro'!$D7) -> 46238 | D13: ='Atividades Macro'!$G7 -> 6 | E13: =COUNTIFS('Atividades Micro'!$B$2:$B$554,$A13,'Atividades Micro'!$G$2:$G$554,"Micro",'Atividades Micro'!$J$2:$J$554,E$12) -> 1 | F13: =COUNTIFS('Atividades Micro'!$B$2:$B$554,$A13,'Atividades Micro'!$G$2:$G$554,"Micro",'Atividades Micro'!$J$2:$J$554,"Em andamento",'Atividades Micro'!$E$2:$E$554,"<>*QA*") -> 0 | G13: =COUNTIFS('Atividades Micro'!$B$2:$B$554,$A13,'Atividades Micro'!$G$2:$G$554,"Micro",'Atividades Micro'!$E$2:$E$554,"*QA*",'Atividades Micro'!$J$2:$J$554,"Em andamento") -> 0 | H13: =COUNTIFS('Atividades Micro'!$B$2:$B$554,$A13,'Atividades Micro'!$G$2:$G$554,"Micro",'Atividades Micro'!$J$2:$J$554,H$12) -> 0 | I13: =COUNTIFS('Atividades Micro'!$B$2:$B$554,$A13,'Atividades Micro'!$G$2:$G$554,"Micro",'Atividades Micro'!$J$2:$J$554,I$12) -> 2 | J13: =COUNTIFS('Atividades Micro'!$B$2:$B$554,$A13,'Atividades Micro'!$G$2:$G$554,"Micro",'Atividades Micro'!$J$2:$J$554,J$12) -> 5 | K13: =IF(D13<=0,0,J13/D13) -> 0.83333333
A14: ='Atividades Macro'!$B8 -> (Financeiro) Satélites | B14: ='Atividades Macro'!$C8 -> Financeiro | C14: =IF('Atividades Macro'!$D8="","",'Atividades Macro'!$D8) -> 46374 | D14: ='Atividades Macro'!$G8 -> 69 | E14: =COUNTIFS('Atividades Micro'!$B$2:$B$554,$A14,'Atividades Micro'!$G$2:$G$554,"Micro",'Atividades Micro'!$J$2:$J$554,E$12) -> 20 | F14: =COUNTIFS('Atividades Micro'!$B$2:$B$554,$A14,'Atividades Micro'!$G$2:$G$554,"Micro",'Atividades Micro'!$J$2:$J$554,"Em andamento",'Atividades Micro'!$E$2:$E$554,"<>*QA*") -> 5 | G14: =COUNTIFS('Atividades Micro'!$B$2:$B$554,$A14,'Atividades Micro'!$G$2:$G$554,"Micro",'Atividades Micro'!$E$2:$E$554,"*QA*",'Atividades Micro'!$J$2:$J$554,"Em andamento") -> 0 | H14: =COUNTIFS('Atividades Micro'!$B$2:$B$554,$A14,'Atividades Micro'!$G$2:$G$554,"Micro",'Atividades Micro'!$J$2:$J$554,H$12) -> 0 | I14: =COUNTIFS('Atividades Micro'!$B$2:$B$554,$A14,'Atividades Micro'!$G$2:$G$554,"Micro",'Atividades Micro'!$J$2:$J$554,I$12) -> 12 | J14: =COUNTIFS('Atividades Micro'!$B$2:$B$554,$A14,'Atividades Micro'!$G$2:$G$554,"Micro",'Atividades Micro'!$J$2:$J$554,J$12) -> 44 | K14: =IF(D14<=0,0,J14/D14) -> 0.63768116
A15: ='Atividades Macro'!$B11 -> (Fiscal) Satélites | B15: ='Atividades Macro'!$C11 -> Fiscal | C15: =IF('Atividades Macro'!$D11="","",'Atividades Macro'!$D11) -> 46379 | D15: ='Atividades Macro'!$G11 -> 3 | E15: =COUNTIFS('Atividades Micro'!$B$2:$B$554,$A15,'Atividades Micro'!$G$2:$G$554,"Micro",'Atividades Micro'!$J$2:$J$554,E$12) -> 1 | F15: =COUNTIFS('Atividades Micro'!$B$2:$B$554,$A15,'Atividades Micro'!$G$2:$G$554,"Micro",'Atividades Micro'!$J$2:$J$554,"Em andamento",'Atividades Micro'!$E$2:$E$554,"<>*QA*") -> 2 | G15: =COUNTIFS('Atividades Micro'!$B$2:$B$554,$A15,'Atividades Micro'!$G$2:$G$554,"Micro",'Atividades Micro'!$E$2:$E$554,"*QA*",'Atividades Micro'!$J$2:$J$554,"Em andamento") -> 0 | H15: =COUNTIFS('Atividades Micro'!$B$2:$B$554,$A15,'Atividades Micro'!$G$2:$G$554,"Micro",'Atividades Micro'!$J$2:$J$554,H$12) -> 0 | I15: =COUNTIFS('Atividades Micro'!$B$2:$B$554,$A15,'Atividades Micro'!$G$2:$G$554,"Micro",'Atividades Micro'!$J$2:$J$554,I$12) -> 4 | J15: =COUNTIFS('Atividades Micro'!$B$2:$B$554,$A15,'Atividades Micro'!$G$2:$G$554,"Micro",'Atividades Micro'!$J$2:$J$554,J$12) -> 0 | K15: =IF(D15<=0,0,J15/D15) -> 0
A16: ='Atividades Macro'!$B10 -> (Fiscal) Aderência | B16: ='Atividades Macro'!$C10 -> Fiscal | C16: =IF('Atividades Macro'!$D10="","",'Atividades Macro'!$D10) | D16: ='Atividades Macro'!$G10 -> 0 | E16: =COUNTIFS('Atividades Micro'!$B$2:$B$554,$A16,'Atividades Micro'!$G$2:$G$554,"Micro",'Atividades Micro'!$J$2:$J$554,E$12) -> 0 | F16: =COUNTIFS('Atividades Micro'!$B$2:$B$554,$A16,'Atividades Micro'!$G$2:$G$554,"Micro",'Atividades Micro'!$J$2:$J$554,"Em andamento",'Atividades Micro'!$E$2:$E$554,"<>*QA*") -> 0 | G16: =COUNTIFS('Atividades Micro'!$B$2:$B$554,$A16,'Atividades Micro'!$G$2:$G$554,"Micro",'Atividades Micro'!$E$2:$E$554,"*QA*",'Atividades Micro'!$J$2:$J$554,"Em andamento") -> 0 | H16: =COUNTIFS('Atividades Micro'!$B$2:$B$554,$A16,'Atividades Micro'!$G$2:$G$554,"Micro",'Atividades Micro'!$J$2:$J$554,H$12) -> 0 | I16: =COUNTIFS('Atividades Micro'!$B$2:$B$554,$A16,'Atividades Micro'!$G$2:$G$554,"Micro",'Atividades Micro'!$J$2:$J$554,I$12) -> 1 | J16: =COUNTIFS('Atividades Micro'!$B$2:$B$554,$A16,'Atividades Micro'!$G$2:$G$554,"Micro",'Atividades Micro'!$J$2:$J$554,J$12) -> 0 | K16: =IF(D16<=0,0,J16/D16) -> 0
A17: ='Atividades Macro'!$B13 -> (Contábil) Aderência | B17: ='Atividades Macro'!$C13 -> Contábil | C17: =IF('Atividades Macro'!$D13="","",'Atividades Macro'!$D13) -> 46339 | D17: ='Atividades Macro'!$G13 -> 30 | E17: =COUNTIFS('Atividades Micro'!$B$2:$B$554,$A17,'Atividades Micro'!$G$2:$G$554,"Micro",'Atividades Micro'!$J$2:$J$554,E$12) -> 1 | F17: =COUNTIFS('Atividades Micro'!$B$2:$B$554,$A17,'Atividades Micro'!$G$2:$G$554,"Micro",'Atividades Micro'!$J$2:$J$554,"Em andamento",'Atividades Micro'!$E$2:$E$554,"<>*QA*") -> 1 | G17: =COUNTIFS('Atividades Micro'!$B$2:$B$554,$A17,'Atividades Micro'!$G$2:$G$554,"Micro",'Atividades Micro'!$E$2:$E$554,"*QA*",'Atividades Micro'!$J$2:$J$554,"Em andamento") -> 0 | H17: =COUNTIFS('Atividades Micro'!$B$2:$B$554,$A17,'Atividades Micro'!$G$2:$G$554,"Micro",'Atividades Micro'!$J$2:$J$554,H$12) -> 25 | I17: =COUNTIFS('Atividades Micro'!$B$2:$B$554,$A17,'Atividades Micro'!$G$2:$G$554,"Micro",'Atividades Micro'!$J$2:$J$554,I$12) -> 0 | J17: =COUNTIFS('Atividades Micro'!$B$2:$B$554,$A17,'Atividades Micro'!$G$2:$G$554,"Micro",'Atividades Micro'!$J$2:$J$554,J$12) -> 3 | K17: =IF(D17<=0,0,J17/D17) -> 0.1
A18: ='Atividades Macro'!$B14 -> (Contábil) Satélites | B18: ='Atividades Macro'!$C14 -> Contábil | C18: =IF('Atividades Macro'!$D14="","",'Atividades Macro'!$D14) | D18: ='Atividades Macro'!$G14 -> 0 | E18: =COUNTIFS('Atividades Micro'!$B$2:$B$554,$A18,'Atividades Micro'!$G$2:$G$554,"Micro",'Atividades Micro'!$J$2:$J$554,E$12) -> 0 | F18: =COUNTIFS('Atividades Micro'!$B$2:$B$554,$A18,'Atividades Micro'!$G$2:$G$554,"Micro",'Atividades Micro'!$J$2:$J$554,"Em andamento",'Atividades Micro'!$E$2:$E$554,"<>*QA*") -> 0 | G18: =COUNTIFS('Atividades Micro'!$B$2:$B$554,$A18,'Atividades Micro'!$G$2:$G$554,"Micro",'Atividades Micro'!$E$2:$E$554,"*QA*",'Atividades Micro'!$J$2:$J$554,"Em andamento") -> 0 | H18: =COUNTIFS('Atividades Micro'!$B$2:$B$554,$A18,'Atividades Micro'!$G$2:$G$554,"Micro",'Atividades Micro'!$J$2:$J$554,H$12) -> 0 | I18: =COUNTIFS('Atividades Micro'!$B$2:$B$554,$A18,'Atividades Micro'!$G$2:$G$554,"Micro",'Atividades Micro'!$J$2:$J$554,I$12) -> 0 | J18: =COUNTIFS('Atividades Micro'!$B$2:$B$554,$A18,'Atividades Micro'!$G$2:$G$554,"Micro",'Atividades Micro'!$J$2:$J$554,J$12) -> 0 | K18: =IF(D18<=0,0,J18/D18) -> 0
A19: ='Atividades Macro'!$B16 -> (Supply) Aderência | B19: ='Atividades Macro'!$C16 -> Supply | C19: =IF('Atividades Macro'!$D16="","",'Atividades Macro'!$D16) -> 46276 | D19: ='Atividades Macro'!$G16 -> 4 | E19: =COUNTIFS('Atividades Micro'!$B$2:$B$554,$A19,'Atividades Micro'!$G$2:$G$554,"Micro",'Atividades Micro'!$J$2:$J$554,E$12) -> 0 | F19: =COUNTIFS('Atividades Micro'!$B$2:$B$554,$A19,'Atividades Micro'!$G$2:$G$554,"Micro",'Atividades Micro'!$J$2:$J$554,"Em andamento",'Atividades Micro'!$E$2:$E$554,"<>*QA*") -> 0 | G19: =COUNTIFS('Atividades Micro'!$B$2:$B$554,$A19,'Atividades Micro'!$G$2:$G$554,"Micro",'Atividades Micro'!$E$2:$E$554,"*QA*",'Atividades Micro'!$J$2:$J$554,"Em andamento") -> 0 | H19: =COUNTIFS('Atividades Micro'!$B$2:$B$554,$A19,'Atividades Micro'!$G$2:$G$554,"Micro",'Atividades Micro'!$J$2:$J$554,H$12) -> 0 | I19: =COUNTIFS('Atividades Micro'!$B$2:$B$554,$A19,'Atividades Micro'!$G$2:$G$554,"Micro",'Atividades Micro'!$J$2:$J$554,I$12) -> 0 | J19: =COUNTIFS('Atividades Micro'!$B$2:$B$554,$A19,'Atividades Micro'!$G$2:$G$554,"Micro",'Atividades Micro'!$J$2:$J$554,J$12) -> 4 | K19: =IF(D19<=0,0,J19/D19) -> 1
A20: ='Atividades Macro'!$B17 -> (Supply) Satélites | B20: ='Atividades Macro'!$C17 -> Supply | C20: =IF('Atividades Macro'!$D17="","",'Atividades Macro'!$D17) -> 46374 | D20: ='Atividades Macro'!$G17 -> 14 | E20: =COUNTIFS('Atividades Micro'!$B$2:$B$554,$A20,'Atividades Micro'!$G$2:$G$554,"Micro",'Atividades Micro'!$J$2:$J$554,E$12) -> 6 | F20: =COUNTIFS('Atividades Micro'!$B$2:$B$554,$A20,'Atividades Micro'!$G$2:$G$554,"Micro",'Atividades Micro'!$J$2:$J$554,"Em andamento",'Atividades Micro'!$E$2:$E$554,"<>*QA*") -> 3 | G20: =COUNTIFS('Atividades Micro'!$B$2:$B$554,$A20,'Atividades Micro'!$G$2:$G$554,"Micro",'Atividades Micro'!$E$2:$E$554,"*QA*",'Atividades Micro'!$J$2:$J$554,"Em andamento") -> 0 | H20: =COUNTIFS('Atividades Micro'!$B$2:$B$554,$A20,'Atividades Micro'!$G$2:$G$554,"Micro",'Atividades Micro'!$J$2:$J$554,H$12) -> 0 | I20: =COUNTIFS('Atividades Micro'!$B$2:$B$554,$A20,'Atividades Micro'!$G$2:$G$554,"Micro",'Atividades Micro'!$J$2:$J$554,I$12) -> 3 | J20: =COUNTIFS('Atividades Micro'!$B$2:$B$554,$A20,'Atividades Micro'!$G$2:$G$554,"Micro",'Atividades Micro'!$J$2:$J$554,J$12) -> 5 | K20: =IF(D20<=0,0,J20/D20) -> 0.35714286
A21: ='Atividades Macro'!$B19 -> (CD) Aderência | B21: ='Atividades Macro'!$C19 -> CD | C21: =IF('Atividades Macro'!$D19="","",'Atividades Macro'!$D19) -> 46385 | D21: ='Atividades Macro'!$G19 -> 41 | E21: =COUNTIFS('Atividades Micro'!$B$2:$B$554,$A21,'Atividades Micro'!$G$2:$G$554,"Micro",'Atividades Micro'!$J$2:$J$554,E$12) -> 9 | F21: =COUNTIFS('Atividades Micro'!$B$2:$B$554,$A21,'Atividades Micro'!$G$2:$G$554,"Micro",'Atividades Micro'!$J$2:$J$554,"Em andamento",'Atividades Micro'!$E$2:$E$554,"<>*QA*") -> 5 | G21: =COUNTIFS('Atividades Micro'!$B$2:$B$554,$A21,'Atividades Micro'!$G$2:$G$554,"Micro",'Atividades Micro'!$E$2:$E$554,"*QA*",'Atividades Micro'!$J$2:$J$554,"Em andamento") -> 1 | H21: =COUNTIFS('Atividades Micro'!$B$2:$B$554,$A21,'Atividades Micro'!$G$2:$G$554,"Micro",'Atividades Micro'!$J$2:$J$554,H$12) -> 0 | I21: =COUNTIFS('Atividades Micro'!$B$2:$B$554,$A21,'Atividades Micro'!$G$2:$G$554,"Micro",'Atividades Micro'!$J$2:$J$554,I$12) -> 0 | J21: =COUNTIFS('Atividades Micro'!$B$2:$B$554,$A21,'Atividades Micro'!$G$2:$G$554,"Micro",'Atividades Micro'!$J$2:$J$554,J$12) -> 26 | K21: =IF(D21<=0,0,J21/D21) -> 0.63414634
A22: ='Atividades Macro'!$B20 -> (CD) Satélites | B22: ='Atividades Macro'!$C20 -> CD | C22: =IF('Atividades Macro'!$D20="","",'Atividades Macro'!$D20) -> 46279 | D22: ='Atividades Macro'!$G20 -> 5 | E22: =COUNTIFS('Atividades Micro'!$B$2:$B$554,$A22,'Atividades Micro'!$G$2:$G$554,"Micro",'Atividades Micro'!$J$2:$J$554,E$12) -> 2 | F22: =COUNTIFS('Atividades Micro'!$B$2:$B$554,$A22,'Atividades Micro'!$G$2:$G$554,"Micro",'Atividades Micro'!$J$2:$J$554,"Em andamento",'Atividades Micro'!$E$2:$E$554,"<>*QA*") -> 1 | G22: =COUNTIFS('Atividades Micro'!$B$2:$B$554,$A22,'Atividades Micro'!$G$2:$G$554,"Micro",'Atividades Micro'!$E$2:$E$554,"*QA*",'Atividades Micro'!$J$2:$J$554,"Em andamento") -> 0 | H22: =COUNTIFS('Atividades Micro'!$B$2:$B$554,$A22,'Atividades Micro'!$G$2:$G$554,"Micro",'Atividades Micro'!$J$2:$J$554,H$12) -> 0 | I22: =COUNTIFS('Atividades Micro'!$B$2:$B$554,$A22,'Atividades Micro'!$G$2:$G$554,"Micro",'Atividades Micro'!$J$2:$J$554,I$12) -> 3 | J22: =COUNTIFS('Atividades Micro'!$B$2:$B$554,$A22,'Atividades Micro'!$G$2:$G$554,"Micro",'Atividades Micro'!$J$2:$J$554,J$12) -> 2 | K22: =IF(D22<=0,0,J22/D22) -> 0.4
A23: ='Atividades Macro'!$B22 -> (Comercial) Aderência | B23: ='Atividades Macro'!$C22 -> Comercial | C23: =IF('Atividades Macro'!$D22="","",'Atividades Macro'!$D22) -> 46279 | D23: ='Atividades Macro'!$G22 -> 5 | E23: =COUNTIFS('Atividades Micro'!$B$2:$B$554,$A23,'Atividades Micro'!$G$2:$G$554,"Micro",'Atividades Micro'!$J$2:$J$554,E$12) -> 2 | F23: =COUNTIFS('Atividades Micro'!$B$2:$B$554,$A23,'Atividades Micro'!$G$2:$G$554,"Micro",'Atividades Micro'!$J$2:$J$554,"Em andamento",'Atividades Micro'!$E$2:$E$554,"<>*QA*") -> 0 | G23: =COUNTIFS('Atividades Micro'!$B$2:$B$554,$A23,'Atividades Micro'!$G$2:$G$554,"Micro",'Atividades Micro'!$E$2:$E$554,"*QA*",'Atividades Micro'!$J$2:$J$554,"Em andamento") -> 0 | H23: =COUNTIFS('Atividades Micro'!$B$2:$B$554,$A23,'Atividades Micro'!$G$2:$G$554,"Micro",'Atividades Micro'!$J$2:$J$554,H$12) -> 0 | I23: =COUNTIFS('Atividades Micro'!$B$2:$B$554,$A23,'Atividades Micro'!$G$2:$G$554,"Micro",'Atividades Micro'!$J$2:$J$554,I$12) -> 0 | J23: =COUNTIFS('Atividades Micro'!$B$2:$B$554,$A23,'Atividades Micro'!$G$2:$G$554,"Micro",'Atividades Micro'!$J$2:$J$554,J$12) -> 3 | K23: =IF(D23<=0,0,J23/D23) -> 0.6
A24: ='Atividades Macro'!$B23 -> (Comercial) Satélites | B24: ='Atividades Macro'!$C23 -> Comercial | C24: =IF('Atividades Macro'!$D23="","",'Atividades Macro'!$D23) -> 46301 | D24: ='Atividades Macro'!$G23 -> 9 | E24: =COUNTIFS('Atividades Micro'!$B$2:$B$554,$A24,'Atividades Micro'!$G$2:$G$554,"Micro",'Atividades Micro'!$J$2:$J$554,E$12) -> 3 | F24: =COUNTIFS('Atividades Micro'!$B$2:$B$554,$A24,'Atividades Micro'!$G$2:$G$554,"Micro",'Atividades Micro'!$J$2:$J$554,"Em andamento",'Atividades Micro'!$E$2:$E$554,"<>*QA*") -> 2 | G24: =COUNTIFS('Atividades Micro'!$B$2:$B$554,$A24,'Atividades Micro'!$G$2:$G$554,"Micro",'Atividades Micro'!$E$2:$E$554,"*QA*",'Atividades Micro'!$J$2:$J$554,"Em andamento") -> 0 | H24: =COUNTIFS('Atividades Micro'!$B$2:$B$554,$A24,'Atividades Micro'!$G$2:$G$554,"Micro",'Atividades Micro'!$J$2:$J$554,H$12) -> 0 | I24: =COUNTIFS('Atividades Micro'!$B$2:$B$554,$A24,'Atividades Micro'!$G$2:$G$554,"Micro",'Atividades Micro'!$J$2:$J$554,I$12) -> 4 | J24: =COUNTIFS('Atividades Micro'!$B$2:$B$554,$A24,'Atividades Micro'!$G$2:$G$554,"Micro",'Atividades Micro'!$J$2:$J$554,J$12) -> 4 | K24: =IF(D24<=0,0,J24/D24) -> 0.44444444
A25: ='Atividades Macro'!$B29 -> (Operações) Satélites | B25: ='Atividades Macro'!$C29 -> Operações | C25: =IF('Atividades Macro'!$D29="","",'Atividades Macro'!$D29) -> 46352 | D25: ='Atividades Macro'!$G29 -> 2 | E25: =COUNTIFS('Atividades Micro'!$B$2:$B$554,$A25,'Atividades Micro'!$G$2:$G$554,"Micro",'Atividades Micro'!$J$2:$J$554,E$12) -> 1 | F25: =COUNTIFS('Atividades Micro'!$B$2:$B$554,$A25,'Atividades Micro'!$G$2:$G$554,"Micro",'Atividades Micro'!$J$2:$J$554,"Em andamento",'Atividades Micro'!$E$2:$E$554,"<>*QA*") -> 1 | G25: =COUNTIFS('Atividades Micro'!$B$2:$B$554,$A25,'Atividades Micro'!$G$2:$G$554,"Micro",'Atividades Micro'!$E$2:$E$554,"*QA*",'Atividades Micro'!$J$2:$J$554,"Em andamento") -> 0 | H25: =COUNTIFS('Atividades Micro'!$B$2:$B$554,$A25,'Atividades Micro'!$G$2:$G$554,"Micro",'Atividades Micro'!$J$2:$J$554,H$12) -> 0 | I25: =COUNTIFS('Atividades Micro'!$B$2:$B$554,$A25,'Atividades Micro'!$G$2:$G$554,"Micro",'Atividades Micro'!$J$2:$J$554,I$12) -> 1 | J25: =COUNTIFS('Atividades Micro'!$B$2:$B$554,$A25,'Atividades Micro'!$G$2:$G$554,"Micro",'Atividades Micro'!$J$2:$J$554,J$12) -> 0 | K25: =IF(D25<=0,0,J25/D25) -> 0
A26: (Zanthus) Aderência | B26: Zanthus | C26: =IF('Atividades Macro'!$D27="","",'Atividades Macro'!$D27) -> 46338 | D26: ='Atividades Macro'!$G27 -> 14 | E26: =COUNTIFS('Atividades Micro'!$B$2:$B$554,$A26,'Atividades Micro'!$G$2:$G$554,"Micro",'Atividades Micro'!$J$2:$J$554,E$12) -> 0 | F26: =COUNTIFS('Atividades Micro'!$B$2:$B$554,$A26,'Atividades Micro'!$G$2:$G$554,"Micro",'Atividades Micro'!$J$2:$J$554,"Em andamento",'Atividades Micro'!$E$2:$E$554,"<>*QA*") -> 1 | G26: =COUNTIFS('Atividades Micro'!$B$2:$B$554,$A26,'Atividades Micro'!$G$2:$G$554,"Micro",'Atividades Micro'!$E$2:$E$554,"*QA*",'Atividades Micro'!$J$2:$J$554,"Em andamento") -> 0 | H26: =COUNTIFS('Atividades Micro'!$B$2:$B$554,$A26,'Atividades Micro'!$G$2:$G$554,"Micro",'Atividades Micro'!$J$2:$J$554,H$12) -> 0 | I26: =COUNTIFS('Atividades Micro'!$B$2:$B$554,$A26,'Atividades Micro'!$G$2:$G$554,"Micro",'Atividades Micro'!$J$2:$J$554,I$12) -> 0 | J26: =COUNTIFS('Atividades Micro'!$B$2:$B$554,$A26,'Atividades Micro'!$G$2:$G$554,"Micro",'Atividades Micro'!$J$2:$J$554,J$12) -> 13 | K26: =IF(D26<=0,0,J26/D26) -> 0.92857143
A27: (TOTVS RM) Aderência | B27: TOTVS RM | C27: =IF('Atividades Macro'!$D25="","",'Atividades Macro'!$D25) -> 46342 | D27: ='Atividades Macro'!$G25 -> 10 | E27: =COUNTIFS('Atividades Micro'!$B$2:$B$554,$A27,'Atividades Micro'!$G$2:$G$554,"Micro",'Atividades Micro'!$J$2:$J$554,E$12) -> 2 | F27: =COUNTIFS('Atividades Micro'!$B$2:$B$554,$A27,'Atividades Micro'!$G$2:$G$554,"Micro",'Atividades Micro'!$J$2:$J$554,"Em andamento",'Atividades Micro'!$E$2:$E$554,"<>*QA*") -> 0 | G27: =COUNTIFS('Atividades Micro'!$B$2:$B$554,$A27,'Atividades Micro'!$G$2:$G$554,"Micro",'Atividades Micro'!$E$2:$E$554,"*QA*",'Atividades Micro'!$J$2:$J$554,"Em andamento") -> 0 | H27: =COUNTIFS('Atividades Micro'!$B$2:$B$554,$A27,'Atividades Micro'!$G$2:$G$554,"Micro",'Atividades Micro'!$J$2:$J$554,H$12) -> 0 | I27: =COUNTIFS('Atividades Micro'!$B$2:$B$554,$A27,'Atividades Micro'!$G$2:$G$554,"Micro",'Atividades Micro'!$J$2:$J$554,I$12) -> 1 | J27: =COUNTIFS('Atividades Micro'!$B$2:$B$554,$A27,'Atividades Micro'!$G$2:$G$554,"Micro",'Atividades Micro'!$J$2:$J$554,J$12) -> 8 | K27: =IF(D27<=0,0,J27/D27) -> 0.8
A42: A aba apresenta somente atividades Micro vinculadas às linhas de Aderência e Satélites, sem as linhas principais Macro. Canceladas ficam visíveis, mas não compõem o total ativo nem o denominador da % concluída. Percentuais em vermelho indicam Data Planejada alcançada ou vencida com entrega pendente.

Sheet Resumo por Frente
A1: ATIVIDADES MACRO POR FRENTE
A2: Quantidade Macro inclui atividades canceladas; canceladas permanecem visíveis em coluna própria e ficam fora somente do percentual concluído.
A4: Frente | B4: Atividades macro | C4: Atividades micro | D4: Não iniciado | E4: Em andamento | F4: Testes QA | G4: Bloqueado | H4: Cancelado | I4: Finalizado | J4: % concluído | K4: Data Planejada | L4: Data fim real
A5: (Migração ERP) Infraestrutura | B5: ='Atividades Macro'!$F2 -> 12 | C5: ='Atividades Macro'!$G2 -> 0 | D5: ='Atividades Macro'!$H2 -> 7 | E5: ='Atividades Macro'!$I2 -> 0 | F5: ='Atividades Macro'!$J2 -> 0 | G5: ='Atividades Macro'!$K2 -> 0 | H5: ='Atividades Macro'!$L2 -> 0 | I5: ='Atividades Macro'!$M2 -> 5 | J5: =IF(D5+E5+F5+G5+I5<=0,0,I5/(D5+E5+F5+G5+I5)) -> 0.41666667 | K5: =IF('Atividades Macro'!$D2="","",'Atividades Macro'!$D2) -> 46374 | L5: =IF('Atividades Macro'!$E2="","",'Atividades Macro'!$E2)
A6: (Migração ERP) Dados Mestres | B6: ='Atividades Macro'!$F3 -> 14 | C6: ='Atividades Macro'!$G3 -> 0 | D6: ='Atividades Macro'!$H3 -> 10 | E6: ='Atividades Macro'!$I3 -> 0 | F6: ='Atividades Macro'!$J3 -> 0 | G6: ='Atividades Macro'!$K3 -> 0 | H6: ='Atividades Macro'!$L3 -> 0 | I6: ='Atividades Macro'!$M3 -> 4 | J6: =IF(D6+E6+F6+G6+I6<=0,0,I6/(D6+E6+F6+G6+I6)) -> 0.28571429 | K6: =IF('Atividades Macro'!$D3="","",'Atividades Macro'!$D3) -> 46346 | L6: =IF('Atividades Macro'!$E3="","",'Atividades Macro'!$E3)
A7: (Migração ERP) Refatoração / Fontes | B7: ='Atividades Macro'!$F4 -> 9 | C7: ='Atividades Macro'!$G4 -> 0 | D7: ='Atividades Macro'!$H4 -> 1 | E7: ='Atividades Macro'!$I4 -> 4 | F7: ='Atividades Macro'!$J4 -> 0 | G7: ='Atividades Macro'!$K4 -> 0 | H7: ='Atividades Macro'!$L4 -> 1 | I7: ='Atividades Macro'!$M4 -> 3 | J7: =IF(D7+E7+F7+G7+I7<=0,0,I7/(D7+E7+F7+G7+I7)) -> 0.375 | K7: =IF('Atividades Macro'!$D4="","",'Atividades Macro'!$D4) -> 46272 | L7: =IF('Atividades Macro'!$E4="","",'Atividades Macro'!$E4)
A8: (Migração ERP) Satélites | B8: ='Atividades Macro'!$F5 -> 2 | C8: ='Atividades Macro'!$G5 -> 0 | D8: ='Atividades Macro'!$H5 -> 0 | E8: ='Atividades Macro'!$I5 -> 1 | F8: ='Atividades Macro'!$J5 -> 0 | G8: ='Atividades Macro'!$K5 -> 0 | H8: ='Atividades Macro'!$L5 -> 0 | I8: ='Atividades Macro'!$M5 -> 1 | J8: =IF(D8+E8+F8+G8+I8<=0,0,I8/(D8+E8+F8+G8+I8)) -> 0.5 | K8: =IF('Atividades Macro'!$D5="","",'Atividades Macro'!$D5) -> 46248 | L8: =IF('Atividades Macro'!$E5="","",'Atividades Macro'!$E5)
A9: Financeiro | B9: ='Atividades Macro'!$F6 -> 7 | C9: ='Atividades Macro'!$G6 -> 73 | D9: ='Atividades Macro'!$H6 -> 21 | E9: ='Atividades Macro'!$I6 -> 7 | F9: ='Atividades Macro'!$J6 -> 0 | G9: ='Atividades Macro'!$K6 -> 0 | H9: ='Atividades Macro'!$L6 -> 15 | I9: ='Atividades Macro'!$M6 -> 51 | J9: =IF(D9+E9+F9+G9+I9<=0,0,I9/(D9+E9+F9+G9+I9)) -> 0.64556962 | K9: =IF('Atividades Macro'!$D6="","",'Atividades Macro'!$D6) -> 46359 | L9: =IF('Atividades Macro'!$E6="","",'Atividades Macro'!$E6)
A10: Fiscal | B10: ='Atividades Macro'!$F9 -> 2 | C10: ='Atividades Macro'!$G9 -> 3 | D10: ='Atividades Macro'!$H9 -> 1 | E10: ='Atividades Macro'!$I9 -> 3 | F10: ='Atividades Macro'!$J9 -> 0 | G10: ='Atividades Macro'!$K9 -> 0 | H10: ='Atividades Macro'!$L9 -> 6 | I10: ='Atividades Macro'!$M9 -> 0 | J10: =IF(D10+E10+F10+G10+I10<=0,0,I10/(D10+E10+F10+G10+I10)) -> 0 | K10: =IF('Atividades Macro'!$D9="","",'Atividades Macro'!$D9) | L10: =IF('Atividades Macro'!$E9="","",'Atividades Macro'!$E9)
A11: Contábil | B11: ='Atividades Macro'!$F12 -> 18 | C11: ='Atividades Macro'!$G12 -> 30 | D11: ='Atividades Macro'!$H12 -> 1 | E11: ='Atividades Macro'!$I12 -> 3 | F11: ='Atividades Macro'!$J12 -> 0 | G11: ='Atividades Macro'!$K12 -> 37 | H11: ='Atividades Macro'!$L12 -> 3 | I11: ='Atividades Macro'!$M12 -> 4 | J11: =IF(D11+E11+F11+G11+I11<=0,0,I11/(D11+E11+F11+G11+I11)) -> 0.088888889 | K11: =IF('Atividades Macro'!$D12="","",'Atividades Macro'!$D12) -> 46374 | L11: =IF('Atividades Macro'!$E12="","",'Atividades Macro'!$E12)
A12: Supply | B12: ='Atividades Macro'!$F15 -> 6 | C12: ='Atividades Macro'!$G15 -> 18 | D12: ='Atividades Macro'!$H15 -> 6 | E12: ='Atividades Macro'!$I15 -> 7 | F12: ='Atividades Macro'!$J15 -> 0 | G12: ='Atividades Macro'!$K15 -> 0 | H12: ='Atividades Macro'!$L15 -> 3 | I12: ='Atividades Macro'!$M15 -> 11 | J12: =IF(D12+E12+F12+G12+I12<=0,0,I12/(D12+E12+F12+G12+I12)) -> 0.45833333 | K12: =IF('Atividades Macro'!$D15="","",'Atividades Macro'!$D15) -> 46290 | L12: =IF('Atividades Macro'!$E15="","",'Atividades Macro'!$E15)
A13: CD | B13: ='Atividades Macro'!$F18 -> 18 | C13: ='Atividades Macro'!$G18 -> 46 | D13: ='Atividades Macro'!$H18 -> 14 | E13: ='Atividades Macro'!$I18 -> 7 | F13: ='Atividades Macro'!$J18 -> 0 | G13: ='Atividades Macro'!$K18 -> 0 | H13: ='Atividades Macro'!$L18 -> 7 | I13: ='Atividades Macro'!$M18 -> 39 | J13: =IF(D13+E13+F13+G13+I13<=0,0,I13/(D13+E13+F13+G13+I13)) -> 0.65 | K13: =IF('Atividades Macro'!$D18="","",'Atividades Macro'!$D18) -> 46374 | L13: =IF('Atividades Macro'!$E18="","",'Atividades Macro'!$E18)
A14: Comercial | B14: ='Atividades Macro'!$F21 -> 4 | C14: ='Atividades Macro'!$G21 -> 13 | D14: ='Atividades Macro'!$H21 -> 6 | E14: ='Atividades Macro'!$I21 -> 3 | F14: ='Atividades Macro'!$J21 -> 0 | G14: ='Atividades Macro'!$K21 -> 0 | H14: ='Atividades Macro'!$L21 -> 4 | I14: ='Atividades Macro'!$M21 -> 8 | J14: =IF(D14+E14+F14+G14+I14<=0,0,I14/(D14+E14+F14+G14+I14)) -> 0.47058824 | K14: =IF('Atividades Macro'!$D21="","",'Atividades Macro'!$D21) -> 46304 | L14: =IF('Atividades Macro'!$E21="","",'Atividades Macro'!$E21)
A15: TOTVS RM | B15: ='Atividades Macro'!$F24 -> 1 | C15: ='Atividades Macro'!$G24 -> 10 | D15: ='Atividades Macro'!$H24 -> 2 | E15: ='Atividades Macro'!$I24 -> 1 | F15: ='Atividades Macro'!$J24 -> 0 | G15: ='Atividades Macro'!$K24 -> 0 | H15: ='Atividades Macro'!$L24 -> 1 | I15: ='Atividades Macro'!$M24 -> 8 | J15: =IF(D15+E15+F15+G15+I15<=0,0,I15/(D15+E15+F15+G15+I15)) -> 0.72727273 | K15: =IF('Atividades Macro'!$D24="","",'Atividades Macro'!$D24) -> 46321 | L15: =IF('Atividades Macro'!$E24="","",'Atividades Macro'!$E24)
A16: Zanthus | B16: ='Atividades Macro'!$F26 -> 1 | C16: ='Atividades Macro'!$G26 -> 14 | D16: ='Atividades Macro'!$H26 -> 0 | E16: ='Atividades Macro'!$I26 -> 2 | F16: ='Atividades Macro'!$J26 -> 0 | G16: ='Atividades Macro'!$K26 -> 0 | H16: ='Atividades Macro'!$L26 -> 0 | I16: ='Atividades Macro'!$M26 -> 13 | J16: =IF(D16+E16+F16+G16+I16<=0,0,I16/(D16+E16+F16+G16+I16)) -> 0.86666667 | K16: =IF('Atividades Macro'!$D26="","",'Atividades Macro'!$D26) -> 46337 | L16: =IF('Atividades Macro'!$E26="","",'Atividades Macro'!$E26)
A17: Operações | B17: ='Atividades Macro'!$F28 -> 2 | C17: ='Atividades Macro'!$G28 -> 2 | D17: ='Atividades Macro'!$H28 -> 1 | E17: ='Atividades Macro'!$I28 -> 2 | F17: ='Atividades Macro'!$J28 -> 0 | G17: ='Atividades Macro'!$K28 -> 0 | H17: ='Atividades Macro'!$L28 -> 2 | I17: ='Atividades Macro'!$M28 -> 0 | J17: =IF(D17+E17+F17+G17+I17<=0,0,I17/(D17+E17+F17+G17+I17)) -> 0 | K17: =IF('Atividades Macro'!$D28="","",'Atividades Macro'!$D28) -> 46288 | L17: =IF('Atividades Macro'!$E28="","",'Atividades Macro'!$E28)
A18: TOTAL | B18: =SUM(B5:B17) -> 96 | C18: =SUM(C5:C17) -> 209 | D18: =SUM(D5:D17) -> 70 | E18: =SUM(E5:E17) -> 40 | F18: =SUM(F5:F17) -> 0 | G18: =SUM(G5:G17) -> 37 | H18: =SUM(H5:H17) -> 42 | I18: =SUM(I5:I17) -> 147 | J18: =IF(D18+E18+F18+G18+I18<=0,0,I18/(D18+E18+F18+G18+I18)) -> 0.5 | K18: =IF(COUNT(K5:K17)=0,"",MIN(K5:K17)) -> 46248 | L18: =IF(COUNT(L5:L17)=0,"",MAX(L5:L17))

Sheet Atividades Macro
A1: Ticket | B1: Atividade macro | C1: Frente | D1: Data Planejada | E1: Data fim real | F1: Atividades macro | G1: Atividades micro | H1: Não iniciado | I1: Em andamento | J1: Testes QA | K1: Bloqueado | L1: Cancelado | M1: Finalizado | N1: Status da macro | O1: % concluído
A2: MERP-7406 | B2: Infraestrutura - Fusão - Grupo PetzCobasi | C2: (Migração ERP) Infraestrutura | D2: 46374 | E2: =IF(N2="Finalizado",IF(COUNT('Cálculos (apoio)'!$B$4:$B$502)=0,"",MAX('Cálculos (apoio)'!$B$4:$B$502)),"") | F2: =COUNTIFS('Atividades Micro'!$A$2:$A$554,$C2,'Atividades Micro'!$G$2:$G$554,"Macro") -> 12 | G2: =COUNTIFS('Atividades Micro'!$A$2:$A$554,$C2,'Atividades Micro'!$G$2:$G$554,"Micro",'Atividades Micro'!$J$2:$J$554,"<>Cancelado") -> 0 | H2: =COUNTIFS('Atividades Micro'!$A$2:$A$554,$C2,'Atividades Micro'!$J$2:$J$554,H$1) -> 7 | I2: =COUNTIFS('Atividades Micro'!$A$2:$A$554,$C2,'Atividades Micro'!$J$2:$J$554,I$1) -> 0 | J2: =COUNTIFS('Atividades Micro'!$A$2:$A$554,$C2,'Atividades Micro'!$J$2:$J$554,J$1) -> 0 | K2: =COUNTIFS('Atividades Micro'!$A$2:$A$554,$C2,'Atividades Micro'!$J$2:$J$554,K$1) -> 0 | L2: =COUNTIFS('Atividades Micro'!$A$2:$A$554,$C2,'Atividades Micro'!$J$2:$J$554,L$1) -> 0 | M2: =COUNTIFS('Atividades Micro'!$A$2:$A$554,$C2,'Atividades Micro'!$J$2:$J$554,M$1) -> 5 | N2: =IF(H2+I2+J2+K2+M2=0,IF(L2>0,"Cancelado","Não iniciado"),IF(M2=H2+I2+J2+K2+M2,"Finalizado",IF(K2>0,"Bloqueado",IF(J2>0,"Testes QA",IF(OR(I2>0,M2>0),"Em andamento","Não iniciado"))))) -> Em andamento | O2: =IF(H2+I2+J2+K2+M2<=0,0,M2/(H2+I2+J2+K2+M2)) -> 0.41666667
A3: MERP-7384 | B3: Migração de Dados/Saldo Inicial | Fusão Petz Cobasi | C3: (Migração ERP) Dados Mestres | D3: 46346 | E3: =IF(N3="Finalizado",IF(COUNT('Cálculos (apoio)'!$D$4:$D$502)=0,"",MAX('Cálculos (apoio)'!$D$4:$D$502)),"") | F3: =COUNTIFS('Atividades Micro'!$A$2:$A$554,$C3,'Atividades Micro'!$G$2:$G$554,"Macro") -> 14 | G3: =COUNTIFS('Atividades Micro'!$A$2:$A$554,$C3,'Atividades Micro'!$G$2:$G$554,"Micro",'Atividades Micro'!$J$2:$J$554,"<>Cancelado") -> 0 | H3: =COUNTIFS('Atividades Micro'!$A$2:$A$554,$C3,'Atividades Micro'!$J$2:$J$554,H$1) -> 10 | I3: =COUNTIFS('Atividades Micro'!$A$2:$A$554,$C3,'Atividades Micro'!$J$2:$J$554,I$1) -> 0 | J3: =COUNTIFS('Atividades Micro'!$A$2:$A$554,$C3,'Atividades Micro'!$J$2:$J$554,J$1) -> 0 | K3: =COUNTIFS('Atividades Micro'!$A$2:$A$554,$C3,'Atividades Micro'!$J$2:$J$554,K$1) -> 0 | L3: =COUNTIFS('Atividades Micro'!$A$2:$A$554,$C3,'Atividades Micro'!$J$2:$J$554,L$1) -> 0 | M3: =COUNTIFS('Atividades Micro'!$A$2:$A$554,$C3,'Atividades Micro'!$J$2:$J$554,M$1) -> 4 | N3: =IF(H3+I3+J3+K3+M3=0,IF(L3>0,"Cancelado","Não iniciado"),IF(M3=H3+I3+J3+K3+M3,"Finalizado",IF(K3>0,"Bloqueado",IF(J3>0,"Testes QA",IF(OR(I3>0,M3>0),"Em andamento","Não iniciado"))))) -> Em andamento | O3: =IF(H3+I3+J3+K3+M3<=0,0,M3/(H3+I3+J3+K3+M3)) -> 0.28571429
A4: MERP-7402 | B4: Revisão de código e configurações | C4: (Migração ERP) Refatoração / Fontes | D4: 46272 | E4: =IF(N4="Finalizado",IF(COUNT('Cálculos (apoio)'!$F$4:$F$502)=0,"",MAX('Cálculos (apoio)'!$F$4:$F$502)),"") | F4: =COUNTIFS('Atividades Micro'!$A$2:$A$554,$C4,'Atividades Micro'!$G$2:$G$554,"Macro") -> 9 | G4: =COUNTIFS('Atividades Micro'!$A$2:$A$554,$C4,'Atividades Micro'!$G$2:$G$554,"Micro",'Atividades Micro'!$J$2:$J$554,"<>Cancelado") -> 0 | H4: =COUNTIFS('Atividades Micro'!$A$2:$A$554,$C4,'Atividades Micro'!$J$2:$J$554,H$1) -> 1 | I4: =COUNTIFS('Atividades Micro'!$A$2:$A$554,$C4,'Atividades Micro'!$J$2:$J$554,I$1) -> 4 | J4: =COUNTIFS('Atividades Micro'!$A$2:$A$554,$C4,'Atividades Micro'!$J$2:$J$554,J$1) -> 0 | K4: =COUNTIFS('Atividades Micro'!$A$2:$A$554,$C4,'Atividades Micro'!$J$2:$J$554,K$1) -> 0 | L4: =COUNTIFS('Atividades Micro'!$A$2:$A$554,$C4,'Atividades Micro'!$J$2:$J$554,L$1) -> 1 | M4: =COUNTIFS('Atividades Micro'!$A$2:$A$554,$C4,'Atividades Micro'!$J$2:$J$554,M$1) -> 3 | N4: =IF(H4+I4+J4+K4+M4=0,IF(L4>0,"Cancelado","Não iniciado"),IF(M4=H4+I4+J4+K4+M4,"Finalizado",IF(K4>0,"Bloqueado",IF(J4>0,"Testes QA",IF(OR(I4>0,M4>0),"Em andamento","Não iniciado"))))) -> Em andamento | O4: =IF(H4+I4+J4+K4+M4<=0,0,M4/(H4+I4+J4+K4+M4)) -> 0.375
A5: MERP-7394 | B5: Sistemas Satelites | Fusão Petz Cobasi | C5: (Migração ERP) Satélites | D5: 46248 | E5: =IF(N5="Finalizado",IF(COUNT('Cálculos (apoio)'!$H$4:$H$502)=0,"",MAX('Cálculos (apoio)'!$H$4:$H$502)),"") | F5: =COUNTIFS('Atividades Micro'!$A$2:$A$554,$C5,'Atividades Micro'!$G$2:$G$554,"Macro") -> 2 | G5: =COUNTIFS('Atividades Micro'!$A$2:$A$554,$C5,'Atividades Micro'!$G$2:$G$554,"Micro",'Atividades Micro'!$J$2:$J$554,"<>Cancelado") -> 0 | H5: =COUNTIFS('Atividades Micro'!$A$2:$A$554,$C5,'Atividades Micro'!$J$2:$J$554,H$1) -> 0 | I5: =COUNTIFS('Atividades Micro'!$A$2:$A$554,$C5,'Atividades Micro'!$J$2:$J$554,I$1) -> 1 | J5: =COUNTIFS('Atividades Micro'!$A$2:$A$554,$C5,'Atividades Micro'!$J$2:$J$554,J$1) -> 0 | K5: =COUNTIFS('Atividades Micro'!$A$2:$A$554,$C5,'Atividades Micro'!$J$2:$J$554,K$1) -> 0 | L5: =COUNTIFS('Atividades Micro'!$A$2:$A$554,$C5,'Atividades Micro'!$J$2:$J$554,L$1) -> 0 | M5: =COUNTIFS('Atividades Micro'!$A$2:$A$554,$C5,'Atividades Micro'!$J$2:$J$554,M$1) -> 1 | N5: =IF(H5+I5+J5+K5+M5=0,IF(L5>0,"Cancelado","Não iniciado"),IF(M5=H5+I5+J5+K5+M5,"Finalizado",IF(K5>0,"Bloqueado",IF(J5>0,"Testes QA",IF(OR(I5>0,M5>0),"Em andamento","Não iniciado"))))) -> Em andamento | O5: =IF(H5+I5+J5+K5+M5<=0,0,M5/(H5+I5+J5+K5+M5)) -> 0.5
A6: SPR-626 | B6: FINANCEIRO | Fusão - Grupo Petz Cobasi | C6: Financeiro | D6: 46359 | E6: =IF(N6="Finalizado",IF(COUNT('Cálculos (apoio)'!$J$4:$J$502)=0,"",MAX('Cálculos (apoio)'!$J$4:$J$502)),"") | F6: =COUNTIFS('Atividades Micro'!$A$2:$A$554,$C6,'Atividades Micro'!$G$2:$G$554,"Macro") -> 7 | G6: =COUNTIFS('Atividades Micro'!$A$2:$A$554,$C6,'Atividades Micro'!$G$2:$G$554,"Micro",'Atividades Micro'!$J$2:$J$554,"<>Cancelado") -> 73 | H6: =COUNTIFS('Atividades Micro'!$A$2:$A$554,$C6,'Atividades Micro'!$J$2:$J$554,H$1) -> 21 | I6: =COUNTIFS('Atividades Micro'!$A$2:$A$554,$C6,'Atividades Micro'!$J$2:$J$554,I$1) -> 7 | J6: =COUNTIFS('Atividades Micro'!$A$2:$A$554,$C6,'Atividades Micro'!$J$2:$J$554,J$1) -> 0 | K6: =COUNTIFS('Atividades Micro'!$A$2:$A$554,$C6,'Atividades Micro'!$J$2:$J$554,K$1) -> 0 | L6: =COUNTIFS('Atividades Micro'!$A$2:$A$554,$C6,'Atividades Micro'!$J$2:$J$554,L$1) -> 15 | M6: =COUNTIFS('Atividades Micro'!$A$2:$A$554,$C6,'Atividades Micro'!$J$2:$J$554,M$1) -> 51 | N6: =IF(H6+I6+J6+K6+M6=0,IF(L6>0,"Cancelado","Não iniciado"),IF(M6=H6+I6+J6+K6+M6,"Finalizado",IF(K6>0,"Bloqueado",IF(J6>0,"Testes QA",IF(OR(I6>0,M6>0),"Em andamento","Não iniciado"))))) -> Em andamento | O6: =IF(H6+I6+J6+K6+M6<=0,0,M6/(H6+I6+J6+K6+M6)) -> 0.64556962
A7: SPR-626 | B7: (Financeiro) Aderência | C7: Financeiro | D7: =IF(COUNT('Cálculos (apoio)'!$K$4:$K$502)=0,"",MAX('Cálculos (apoio)'!$K$4:$K$502)) -> 46238 | E7: =IF(N7="Finalizado",IF(COUNT('Cálculos (apoio)'!$L$4:$L$502)=0,"",MAX('Cálculos (apoio)'!$L$4:$L$502)),"") | F7: =COUNTIFS('Atividades Micro'!$B$2:$B$554,$B7,'Atividades Micro'!$G$2:$G$554,"Macro") -> 3 | G7: =COUNTIFS('Atividades Micro'!$B$2:$B$554,$B7,'Atividades Micro'!$G$2:$G$554,"Micro",'Atividades Micro'!$J$2:$J$554,"<>Cancelado") -> 6 | H7: =COUNTIFS('Atividades Micro'!$B$2:$B$554,$B7,'Atividades Micro'!$J$2:$J$554,H$1) -> 1 | I7: =COUNTIFS('Atividades Micro'!$B$2:$B$554,$B7,'Atividades Micro'!$J$2:$J$554,I$1) -> 0 | J7: =COUNTIFS('Atividades Micro'!$B$2:$B$554,$B7,'Atividades Micro'!$J$2:$J$554,J$1) -> 0 | K7: =COUNTIFS('Atividades Micro'!$B$2:$B$554,$B7,'Atividades Micro'!$J$2:$J$554,K$1) -> 0 | L7: =COUNTIFS('Atividades Micro'!$B$2:$B$554,$B7,'Atividades Micro'!$J$2:$J$554,L$1) -> 3 | M7: =COUNTIFS('Atividades Micro'!$B$2:$B$554,$B7,'Atividades Micro'!$J$2:$J$554,M$1) -> 7 | N7: =IF(H7+I7+J7+K7+M7=0,IF(L7>0,"Cancelado","Não iniciado"),IF(M7=H7+I7+J7+K7+M7,"Finalizado",IF(K7>0,"Bloqueado",IF(J7>0,"Testes QA",IF(OR(I7>0,M7>0),"Em andamento","Não iniciado"))))) -> Em andamento | O7: =IF(H7+I7+J7+K7+M7<=0,0,M7/(H7+I7+J7+K7+M7)) -> 0.875
A8: SPR-626 | B8: (Financeiro) Satélites | C8: Financeiro | D8: =IF(COUNT('Cálculos (apoio)'!$M$4:$M$502)=0,"",MAX('Cálculos (apoio)'!$M$4:$M$502)) -> 46374 | E8: =IF(N8="Finalizado",IF(COUNT('Cálculos (apoio)'!$N$4:$N$502)=0,"",MAX('Cálculos (apoio)'!$N$4:$N$502)),"") | F8: =COUNTIFS('Atividades Micro'!$B$2:$B$554,$B8,'Atividades Micro'!$G$2:$G$554,"Macro") -> 4 | G8: =COUNTIFS('Atividades Micro'!$B$2:$B$554,$B8,'Atividades Micro'!$G$2:$G$554,"Micro",'Atividades Micro'!$J$2:$J$554,"<>Cancelado") -> 69 | H8: =COUNTIFS('Atividades Micro'!$B$2:$B$554,$B8,'Atividades Micro'!$J$2:$J$554,H$1) -> 22 | I8: =COUNTIFS('Atividades Micro'!$B$2:$B$554,$B8,'Atividades Micro'!$J$2:$J$554,I$1) -> 7 | J8: =COUNTIFS('Atividades Micro'!$B$2:$B$554,$B8,'Atividades Micro'!$J$2:$J$554,J$1) -> 0 | K8: =COUNTIFS('Atividades Micro'!$B$2:$B$554,$B8,'Atividades Micro'!$J$2:$J$554,K$1) -> 0 | L8: =COUNTIFS('Atividades Micro'!$B$2:$B$554,$B8,'Atividades Micro'!$J$2:$J$554,L$1) -> 12 | M8: =COUNTIFS('Atividades Micro'!$B$2:$B$554,$B8,'Atividades Micro'!$J$2:$J$554,M$1) -> 44 | N8: =IF(H8+I8+J8+K8+M8=0,IF(L8>0,"Cancelado","Não iniciado"),IF(M8=H8+I8+J8+K8+M8,"Finalizado",IF(K8>0,"Bloqueado",IF(J8>0,"Testes QA",IF(OR(I8>0,M8>0),"Em andamento","Não iniciado"))))) -> Em andamento | O8: =IF(H8+I8+J8+K8+M8<=0,0,M8/(H8+I8+J8+K8+M8)) -> 0.60273973
A9: SPR-628 | B9: FISCAL | Fusão - Grupo Petz Cobasi | C9: Fiscal | E9: =IF(N9="Finalizado",IF(COUNT('Cálculos (apoio)'!$P$4:$P$502)=0,"",MAX('Cálculos (apoio)'!$P$4:$P$502)),"") | F9: =COUNTIFS('Atividades Micro'!$A$2:$A$554,$C9,'Atividades Micro'!$G$2:$G$554,"Macro") -> 2 | G9: =COUNTIFS('Atividades Micro'!$A$2:$A$554,$C9,'Atividades Micro'!$G$2:$G$554,"Micro",'Atividades Micro'!$J$2:$J$554,"<>Cancelado") -> 3 | H9: =COUNTIFS('Atividades Micro'!$A$2:$A$554,$C9,'Atividades Micro'!$J$2:$J$554,H$1) -> 1 | I9: =COUNTIFS('Atividades Micro'!$A$2:$A$554,$C9,'Atividades Micro'!$J$2:$J$554,I$1) -> 3 | J9: =COUNTIFS('Atividades Micro'!$A$2:$A$554,$C9,'Atividades Micro'!$J$2:$J$554,J$1) -> 0 | K9: =COUNTIFS('Atividades Micro'!$A$2:$A$554,$C9,'Atividades Micro'!$J$2:$J$554,K$1) -> 0 | L9: =COUNTIFS('Atividades Micro'!$A$2:$A$554,$C9,'Atividades Micro'!$J$2:$J$554,L$1) -> 6 | M9: =COUNTIFS('Atividades Micro'!$A$2:$A$554,$C9,'Atividades Micro'!$J$2:$J$554,M$1) -> 0 | N9: =IF(H9+I9+J9+K9+M9=0,IF(L9>0,"Cancelado","Não iniciado"),IF(M9=H9+I9+J9+K9+M9,"Finalizado",IF(K9>0,"Bloqueado",IF(J9>0,"Testes QA",IF(OR(I9>0,M9>0),"Em andamento","Não iniciado"))))) -> Em andamento | O9: =IF(H9+I9+J9+K9+M9<=0,0,M9/(H9+I9+J9+K9+M9)) -> 0
A10: SPR-628 | B10: (Fiscal) Aderência | C10: Fiscal | F10: =COUNTIFS('Atividades Micro'!$B$2:$B$554,$B11,'Atividades Micro'!$G$2:$G$554,"Macro") -> 1 | O10: =IF(H10+I10+J10+K10+M10<=0,0,M10/(H10+I10+J10+K10+M10)) -> 0
A11: SPR-628 | B11: (Fiscal) Satélites | C11: Fiscal | D11: =IF(COUNT('Cálculos (apoio)'!$Q$4:$Q$502)=0,"",MAX('Cálculos (apoio)'!$Q$4:$Q$502)) -> 46379 | E11: =IF(N11="Finalizado",IF(COUNT('Cálculos (apoio)'!$R$4:$R$502)=0,"",MAX('Cálculos (apoio)'!$R$4:$R$502)),"") | F11: =COUNTIFS('Atividades Micro'!$B$2:$B$554,$B11,'Atividades Micro'!$G$2:$G$554,"Macro") -> 1 | G11: =COUNTIFS('Atividades Micro'!$B$2:$B$554,$B11,'Atividades Micro'!$G$2:$G$554,"Micro",'Atividades Micro'!$J$2:$J$554,"<>Cancelado") -> 3 | H11: =COUNTIFS('Atividades Micro'!$B$2:$B$554,$B11,'Atividades Micro'!$J$2:$J$554,H$1) -> 1 | I11: =COUNTIFS('Atividades Micro'!$B$2:$B$554,$B11,'Atividades Micro'!$J$2:$J$554,I$1) -> 3 | J11: =COUNTIFS('Atividades Micro'!$B$2:$B$554,$B11,'Atividades Micro'!$J$2:$J$554,J$1) -> 0 | K11: =COUNTIFS('Atividades Micro'!$B$2:$B$554,$B11,'Atividades Micro'!$J$2:$J$554,K$1) -> 0 | L11: =COUNTIFS('Atividades Micro'!$B$2:$B$554,$B11,'Atividades Micro'!$J$2:$J$554,L$1) -> 4 | M11: =COUNTIFS('Atividades Micro'!$B$2:$B$554,$B11,'Atividades Micro'!$J$2:$J$554,M$1) -> 0 | N11: =IF(H11+I11+J11+K11+M11=0,IF(L11>0,"Cancelado","Não iniciado"),IF(M11=H11+I11+J11+K11+M11,"Finalizado",IF(K11>0,"Bloqueado",IF(J11>0,"Testes QA",IF(OR(I11>0,M11>0),"Em andamento","Não iniciado"))))) -> Em andamento | O11: =IF(H11+I11+J11+K11+M11<=0,0,M11/(H11+I11+J11+K11+M11)) -> 0
A12: SPR-629 | B12: CONTÁBIL | Fusão - Grupo Petz Cobasi | C12: Contábil | D12: 46374 | E12: =IF(N12="Finalizado",IF(COUNT('Cálculos (apoio)'!$T$4:$T$502)=0,"",MAX('Cálculos (apoio)'!$T$4:$T$502)),"") | F12: =COUNTIFS('Atividades Micro'!$A$2:$A$554,$C12,'Atividades Micro'!$G$2:$G$554,"Macro") -> 18 | G12: =COUNTIFS('Atividades Micro'!$A$2:$A$554,$C12,'Atividades Micro'!$G$2:$G$554,"Micro",'Atividades Micro'!$J$2:$J$554,"<>Cancelado") -> 30 | H12: =COUNTIFS('Atividades Micro'!$A$2:$A$554,$C12,'Atividades Micro'!$J$2:$J$554,H$1) -> 1 | I12: =COUNTIFS('Atividades Micro'!$A$2:$A$554,$C12,'Atividades Micro'!$J$2:$J$554,I$1) -> 3 | J12: =COUNTIFS('Atividades Micro'!$A$2:$A$554,$C12,'Atividades Micro'!$J$2:$J$554,J$1) -> 0 | K12: =COUNTIFS('Atividades Micro'!$A$2:$A$554,$C12,'Atividades Micro'!$J$2:$J$554,K$1) -> 37 | L12: =COUNTIFS('Atividades Micro'!$A$2:$A$554,$C12,'Atividades Micro'!$J$2:$J$554,L$1) -> 3 | M12: =COUNTIFS('Atividades Micro'!$A$2:$A$554,$C12,'Atividades Micro'!$J$2:$J$554,M$1) -> 4 | N12: =IF(H12+I12+J12+K12+M12=0,IF(L12>0,"Cancelado","Não iniciado"),IF(M12=H12+I12+J12+K12+M12,"Finalizado",IF(K12>0,"Bloqueado",IF(J12>0,"Testes QA",IF(OR(I12>0,M12>0),"Em andamento","Não iniciado"))))) -> Bloqueado | O12: =IF(H12+I12+J12+K12+M12<=0,0,M12/(H12+I12+J12+K12+M12)) -> 0.088888889
A13: SPR-629 | B13: (Contábil) Aderência | C13: Contábil | D13: =IF(COUNT('Cálculos (apoio)'!$U$4:$U$502)=0,"",MAX('Cálculos (apoio)'!$U$4:$U$502)) -> 46339 | E13: =IF(N13="Finalizado",IF(COUNT('Cálculos (apoio)'!$V$4:$V$502)=0,"",MAX('Cálculos (apoio)'!$V$4:$V$502)),"") | F13: =COUNTIFS('Atividades Micro'!$B$2:$B$554,$B13,'Atividades Micro'!$G$2:$G$554,"Macro") -> 15 | G13: =COUNTIFS('Atividades Micro'!$B$2:$B$554,$B13,'Atividades Micro'!$G$2:$G$554,"Micro",'Atividades Micro'!$J$2:$J$554,"<>Cancelado") -> 30 | H13: =COUNTIFS('Atividades Micro'!$B$2:$B$554,$B13,'Atividades Micro'!$J$2:$J$554,H$1) -> 1 | I13: =COUNTIFS('Atividades Micro'!$B$2:$B$554,$B13,'Atividades Micro'!$J$2:$J$554,I$1) -> 3 | J13: =COUNTIFS('Atividades Micro'!$B$2:$B$554,$B13,'Atividades Micro'!$J$2:$J$554,J$1) -> 0 | K13: =COUNTIFS('Atividades Micro'!$B$2:$B$554,$B13,'Atividades Micro'!$J$2:$J$554,K$1) -> 37 | L13: =COUNTIFS('Atividades Micro'!$B$2:$B$554,$B13,'Atividades Micro'!$J$2:$J$554,L$1) -> 0 | M13: =COUNTIFS('Atividades Micro'!$B$2:$B$554,$B13,'Atividades Micro'!$J$2:$J$554,M$1) -> 4 | N13: =IF(H13+I13+J13+K13+M13=0,IF(L13>0,"Cancelado","Não iniciado"),IF(M13=H13+I13+J13+K13+M13,"Finalizado",IF(K13>0,"Bloqueado",IF(J13>0,"Testes QA",IF(OR(I13>0,M13>0),"Em andamento","Não iniciado"))))) -> Bloqueado | O13: =IF(H13+I13+J13+K13+M13<=0,0,M13/(H13+I13+J13+K13+M13)) -> 0.088888889
A14: SPR-629 | B14: (Contábil) Satélites | C14: Contábil | D14: =IF(COUNT('Cálculos (apoio)'!$W$4:$W$502)=0,"",MAX('Cálculos (apoio)'!$W$4:$W$502)) | E14: =IF(N14="Finalizado",IF(COUNT('Cálculos (apoio)'!$X$4:$X$502)=0,"",MAX('Cálculos (apoio)'!$X$4:$X$502)),"") | F14: =COUNTIFS('Atividades Micro'!$B$2:$B$554,$B14,'Atividades Micro'!$G$2:$G$554,"Macro") -> 3 | G14: =COUNTIFS('Atividades Micro'!$B$2:$B$554,$B14,'Atividades Micro'!$G$2:$G$554,"Micro",'Atividades Micro'!$J$2:$J$554,"<>Cancelado") -> 0 | H14: =COUNTIFS('Atividades Micro'!$B$2:$B$554,$B14,'Atividades Micro'!$J$2:$J$554,H$1) -> 0 | I14: =COUNTIFS('Atividades Micro'!$B$2:$B$554,$B14,'Atividades Micro'!$J$2:$J$554,I$1) -> 0 | J14: =COUNTIFS('Atividades Micro'!$B$2:$B$554,$B14,'Atividades Micro'!$J$2:$J$554,J$1) -> 0 | K14: =COUNTIFS('Atividades Micro'!$B$2:$B$554,$B14,'Atividades Micro'!$J$2:$J$554,K$1) -> 0 | L14: =COUNTIFS('Atividades Micro'!$B$2:$B$554,$B14,'Atividades Micro'!$J$2:$J$554,L$1) -> 3 | M14: =COUNTIFS('Atividades Micro'!$B$2:$B$554,$B14,'Atividades Micro'!$J$2:$J$554,M$1) -> 0 | N14: =IF(H14+I14+J14+K14+M14=0,IF(L14>0,"Cancelado","Não iniciado"),IF(M14=H14+I14+J14+K14+M14,"Finalizado",IF(K14>0,"Bloqueado",IF(J14>0,"Testes QA",IF(OR(I14>0,M14>0),"Em andamento","Não iniciado"))))) -> Cancelado | O14: =IF(H14+I14+J14+K14+M14<=0,0,M14/(H14+I14+J14+K14+M14)) -> 0
A15: SPS-1048 | B15: SUPPLY| Fusão - Petz Cobasi | C15: Supply | D15: 46290 | E15: =IF(N15="Finalizado",IF(COUNT('Cálculos (apoio)'!$Z$4:$Z$502)=0,"",MAX('Cálculos (apoio)'!$Z$4:$Z$502)),"") | F15: =COUNTIFS('Atividades Micro'!$A$2:$A$554,$C15,'Atividades Micro'!$G$2:$G$554,"Macro") -> 6 | G15: =COUNTIFS('Atividades Micro'!$A$2:$A$554,$C15,'Atividades Micro'!$G$2:$G$554,"Micro",'Atividades Micro'!$J$2:$J$554,"<>Cancelado") -> 18 | H15: =COUNTIFS('Atividades Micro'!$A$2:$A$554,$C15,'Atividades Micro'!$J$2:$J$554,H$1) -> 6 | I15: =COUNTIFS('Atividades Micro'!$A$2:$A$554,$C15,'Atividades Micro'!$J$2:$J$554,I$1) -> 7 | J15: =COUNTIFS('Atividades Micro'!$A$2:$A$554,$C15,'Atividades Micro'!$J$2:$J$554,J$1) -> 0 | K15: =COUNTIFS('Atividades Micro'!$A$2:$A$554,$C15,'Atividades Micro'!$J$2:$J$554,K$1) -> 0 | L15: =COUNTIFS('Atividades Micro'!$A$2:$A$554,$C15,'Atividades Micro'!$J$2:$J$554,L$1) -> 3 | M15: =COUNTIFS('Atividades Micro'!$A$2:$A$554,$C15,'Atividades Micro'!$J$2:$J$554,M$1) -> 11 | N15: =IF(H15+I15+J15+K15+M15=0,IF(L15>0,"Cancelado","Não iniciado"),IF(M15=H15+I15+J15+K15+M15,"Finalizado",IF(K15>0,"Bloqueado",IF(J15>0,"Testes QA",IF(OR(I15>0,M15>0),"Em andamento","Não iniciado"))))) -> Em andamento | O15: =IF(H15+I15+J15+K15+M15<=0,0,M15/(H15+I15+J15+K15+M15)) -> 0.45833333
A16: SPS-1048 | B16: (Supply) Aderência | C16: Supply | D16: =IF(COUNT('Cálculos (apoio)'!$AA$4:$AA$502)=0,"",MAX('Cálculos (apoio)'!$AA$4:$AA$502)) -> 46276 | E16: =IF(N16="Finalizado",IF(COUNT('Cálculos (apoio)'!$AB$4:$AB$502)=0,"",MAX('Cálculos (apoio)'!$AB$4:$AB$502)),"") -> 46269 | F16: =COUNTIFS('Atividades Micro'!$B$2:$B$554,$B16,'Atividades Micro'!$G$2:$G$554,"Macro") -> 2 | G16: =COUNTIFS('Atividades Micro'!$B$2:$B$554,$B16,'Atividades Micro'!$G$2:$G$554,"Micro",'Atividades Micro'!$J$2:$J$554,"<>Cancelado") -> 4 | H16: =COUNTIFS('Atividades Micro'!$B$2:$B$554,$B16,'Atividades Micro'!$J$2:$J$554,H$1) -> 0 | I16: =COUNTIFS('Atividades Micro'!$B$2:$B$554,$B16,'Atividades Micro'!$J$2:$J$554,I$1) -> 0 | J16: =COUNTIFS('Atividades Micro'!$B$2:$B$554,$B16,'Atividades Micro'!$J$2:$J$554,J$1) -> 0 | K16: =COUNTIFS('Atividades Micro'!$B$2:$B$554,$B16,'Atividades Micro'!$J$2:$J$554,K$1) -> 0 | L16: =COUNTIFS('Atividades Micro'!$B$2:$B$554,$B16,'Atividades Micro'!$J$2:$J$554,L$1) -> 0 | M16: =COUNTIFS('Atividades Micro'!$B$2:$B$554,$B16,'Atividades Micro'!$J$2:$J$554,M$1) -> 6 | N16: =IF(H16+I16+J16+K16+M16=0,IF(L16>0,"Cancelado","Não iniciado"),IF(M16=H16+I16+J16+K16+M16,"Finalizado",IF(K16>0,"Bloqueado",IF(J16>0,"Testes QA",IF(OR(I16>0,M16>0),"Em andamento","Não iniciado"))))) -> Finalizado | O16: =IF(H16+I16+J16+K16+M16<=0,0,M16/(H16+I16+J16+K16+M16)) -> 1
A17: SPS-1048 | B17: (Supply) Satélites | C17: Supply | D17: =IF(COUNT('Cálculos (apoio)'!$AC$4:$AC$502)=0,"",MAX('Cálculos (apoio)'!$AC$4:$AC$502)) -> 46374 | E17: =IF(N17="Finalizado",IF(COUNT('Cálculos (apoio)'!$AD$4:$AD$502)=0,"",MAX('Cálculos (apoio)'!$AD$4:$AD$502)),"") | F17: =COUNTIFS('Atividades Micro'!$B$2:$B$554,$B17,'Atividades Micro'!$G$2:$G$554,"Macro") -> 4 | G17: =COUNTIFS('Atividades Micro'!$B$2:$B$554,$B17,'Atividades Micro'!$G$2:$G$554,"Micro",'Atividades Micro'!$J$2:$J$554,"<>Cancelado") -> 14 | H17: =COUNTIFS('Atividades Micro'!$B$2:$B$554,$B17,'Atividades Micro'!$J$2:$J$554,H$1) -> 6 | I17: =COUNTIFS('Atividades Micro'!$B$2:$B$554,$B17,'Atividades Micro'!$J$2:$J$554,I$1) -> 7 | J17: =COUNTIFS('Atividades Micro'!$B$2:$B$554,$B17,'Atividades Micro'!$J$2:$J$554,J$1) -> 0 | K17: =COUNTIFS('Atividades Micro'!$B$2:$B$554,$B17,'Atividades Micro'!$J$2:$J$554,K$1) -> 0 | L17: =COUNTIFS('Atividades Micro'!$B$2:$B$554,$B17,'Atividades Micro'!$J$2:$J$554,L$1) -> 3 | M17: =COUNTIFS('Atividades Micro'!$B$2:$B$554,$B17,'Atividades Micro'!$J$2:$J$554,M$1) -> 5 | N17: =IF(H17+I17+J17+K17+M17=0,IF(L17>0,"Cancelado","Não iniciado"),IF(M17=H17+I17+J17+K17+M17,"Finalizado",IF(K17>0,"Bloqueado",IF(J17>0,"Testes QA",IF(OR(I17>0,M17>0),"Em andamento","Não iniciado"))))) -> Em andamento | O17: =IF(H17+I17+J17+K17+M17<=0,0,M17/(H17+I17+J17+K17+M17)) -> 0.27777778
A18: SPCD-2330 | B18: CD | Fusão - Grupo Petz Cobasi | C18: CD | D18: 46374 | E18: =IF(N18="Finalizado",IF(COUNT('Cálculos (apoio)'!$AF$4:$AF$502)=0,"",MAX('Cálculos (apoio)'!$AF$4:$AF$502)),"") | F18: =COUNTIFS('Atividades Micro'!$A$2:$A$554,$C18,'Atividades Micro'!$G$2:$G$554,"Macro") -> 18 | G18: =COUNTIFS('Atividades Micro'!$A$2:$A$554,$C18,'Atividades Micro'!$G$2:$G$554,"Micro",'Atividades Micro'!$J$2:$J$554,"<>Cancelado") -> 46 | H18: =COUNTIFS('Atividades Micro'!$A$2:$A$554,$C18,'Atividades Micro'!$J$2:$J$554,H$1) -> 14 | I18: =COUNTIFS('Atividades Micro'!$A$2:$A$554,$C18,'Atividades Micro'!$J$2:$J$554,I$1) -> 7 | J18: =COUNTIFS('Atividades Micro'!$A$2:$A$554,$C18,'Atividades Micro'!$J$2:$J$554,J$1) -> 0 | K18: =COUNTIFS('Atividades Micro'!$A$2:$A$554,$C18,'Atividades Micro'!$J$2:$J$554,K$1) -> 0 | L18: =COUNTIFS('Atividades Micro'!$A$2:$A$554,$C18,'Atividades Micro'!$J$2:$J$554,L$1) -> 7 | M18: =COUNTIFS('Atividades Micro'!$A$2:$A$554,$C18,'Atividades Micro'!$J$2:$J$554,M$1) -> 39 | N18: =IF(H18+I18+J18+K18+M18=0,IF(L18>0,"Cancelado","Não iniciado"),IF(M18=H18+I18+J18+K18+M18,"Finalizado",IF(K18>0,"Bloqueado",IF(J18>0,"Testes QA",IF(OR(I18>0,M18>0),"Em andamento","Não iniciado"))))) -> Em andamento | O18: =IF(H18+I18+J18+K18+M18<=0,0,M18/(H18+I18+J18+K18+M18)) -> 0.65
A19: SPCD-2330 | B19: (CD) Aderência | C19: CD | D19: =IF(COUNT('Cálculos (apoio)'!$AG$4:$AG$502)=0,"",MAX('Cálculos (apoio)'!$AG$4:$AG$502)) -> 46385 | E19: =IF(N19="Finalizado",IF(COUNT('Cálculos (apoio)'!$AH$4:$AH$502)=0,"",MAX('Cálculos (apoio)'!$AH$4:$AH$502)),"") | F19: =COUNTIFS('Atividades Micro'!$B$2:$B$554,$B19,'Atividades Micro'!$G$2:$G$554,"Macro") -> 14 | G19: =COUNTIFS('Atividades Micro'!$B$2:$B$554,$B19,'Atividades Micro'!$G$2:$G$554,"Micro",'Atividades Micro'!$J$2:$J$554,"<>Cancelado") -> 41 | H19: =COUNTIFS('Atividades Micro'!$B$2:$B$554,$B19,'Atividades Micro'!$J$2:$J$554,H$1) -> 11 | I19: =COUNTIFS('Atividades Micro'!$B$2:$B$554,$B19,'Atividades Micro'!$J$2:$J$554,I$1) -> 6 | J19: =COUNTIFS('Atividades Micro'!$B$2:$B$554,$B19,'Atividades Micro'!$J$2:$J$554,J$1) -> 0 | K19: =COUNTIFS('Atividades Micro'!$B$2:$B$554,$B19,'Atividades Micro'!$J$2:$J$554,K$1) -> 0 | L19: =COUNTIFS('Atividades Micro'!$B$2:$B$554,$B19,'Atividades Micro'!$J$2:$J$554,L$1) -> 1 | M19: =COUNTIFS('Atividades Micro'!$B$2:$B$554,$B19,'Atividades Micro'!$J$2:$J$554,M$1) -> 37 | N19: =IF(H19+I19+J19+K19+M19=0,IF(L19>0,"Cancelado","Não iniciado"),IF(M19=H19+I19+J19+K19+M19,"Finalizado",IF(K19>0,"Bloqueado",IF(J19>0,"Testes QA",IF(OR(I19>0,M19>0),"Em andamento","Não iniciado"))))) -> Em andamento | O19: =IF(H19+I19+J19+K19+M19<=0,0,M19/(H19+I19+J19+K19+M19)) -> 0.68518519
A20: SPCD-2330 | B20: (CD) Satélites | C20: CD | D20: =IF(COUNT('Cálculos (apoio)'!$AI$4:$AI$502)=0,"",MAX('Cálculos (apoio)'!$AI$4:$AI$502)) -> 46279 | E20: =IF(N20="Finalizado",IF(COUNT('Cálculos (apoio)'!$AJ$4:$AJ$502)=0,"",MAX('Cálculos (apoio)'!$AJ$4:$AJ$502)),"") | F20: =COUNTIFS('Atividades Micro'!$B$2:$B$554,$B20,'Atividades Micro'!$G$2:$G$554,"Macro") -> 4 | G20: =COUNTIFS('Atividades Micro'!$B$2:$B$554,$B20,'Atividades Micro'!$G$2:$G$554,"Micro",'Atividades Micro'!$J$2:$J$554,"<>Cancelado") -> 5 | H20: =COUNTIFS('Atividades Micro'!$B$2:$B$554,$B20,'Atividades Micro'!$J$2:$J$554,H$1) -> 3 | I20: =COUNTIFS('Atividades Micro'!$B$2:$B$554,$B20,'Atividades Micro'!$J$2:$J$554,I$1) -> 1 | J20: =COUNTIFS('Atividades Micro'!$B$2:$B$554,$B20,'Atividades Micro'!$J$2:$J$554,J$1) -> 0 | K20: =COUNTIFS('Atividades Micro'!$B$2:$B$554,$B20,'Atividades Micro'!$J$2:$J$554,K$1) -> 0 | L20: =COUNTIFS('Atividades Micro'!$B$2:$B$554,$B20,'Atividades Micro'!$J$2:$J$554,L$1) -> 6 | M20: =COUNTIFS('Atividades Micro'!$B$2:$B$554,$B20,'Atividades Micro'!$J$2:$J$554,M$1) -> 2 | N20: =IF(H20+I20+J20+K20+M20=0,IF(L20>0,"Cancelado","Não iniciado"),IF(M20=H20+I20+J20+K20+M20,"Finalizado",IF(K20>0,"Bloqueado",IF(J20>0,"Testes QA",IF(OR(I20>0,M20>0),"Em andamento","Não iniciado"))))) -> Em andamento | O20: =IF(H20+I20+J20+K20+M20<=0,0,M20/(H20+I20+J20+K20+M20)) -> 0.33333333
A21: SPR-1239 | B21: COMERCIAL | Fusão - Petz Cobasi | C21: Comercial | D21: 46304 | E21: =IF(N21="Finalizado",IF(COUNT('Cálculos (apoio)'!$AL$4:$AL$502)=0,"",MAX('Cálculos (apoio)'!$AL$4:$AL$502)),"") | F21: =COUNTIFS('Atividades Micro'!$A$2:$A$554,$C21,'Atividades Micro'!$G$2:$G$554,"Macro") -> 4 | G21: =COUNTIFS('Atividades Micro'!$A$2:$A$554,$C21,'Atividades Micro'!$G$2:$G$554,"Micro",'Atividades Micro'!$J$2:$J$554,"<>Cancelado") -> 13 | H21: =COUNTIFS('Atividades Micro'!$A$2:$A$554,$C21,'Atividades Micro'!$J$2:$J$554,H$1) -> 6 | I21: =COUNTIFS('Atividades Micro'!$A$2:$A$554,$C21,'Atividades Micro'!$J$2:$J$554,I$1) -> 3 | J21: =COUNTIFS('Atividades Micro'!$A$2:$A$554,$C21,'Atividades Micro'!$J$2:$J$554,J$1) -> 0 | K21: =COUNTIFS('Atividades Micro'!$A$2:$A$554,$C21,'Atividades Micro'!$J$2:$J$554,K$1) -> 0 | L21: =COUNTIFS('Atividades Micro'!$A$2:$A$554,$C21,'Atividades Micro'!$J$2:$J$554,L$1) -> 4 | M21: =COUNTIFS('Atividades Micro'!$A$2:$A$554,$C21,'Atividades Micro'!$J$2:$J$554,M$1) -> 8 | N21: =IF(H21+I21+J21+K21+M21=0,IF(L21>0,"Cancelado","Não iniciado"),IF(M21=H21+I21+J21+K21+M21,"Finalizado",IF(K21>0,"Bloqueado",IF(J21>0,"Testes QA",IF(OR(I21>0,M21>0),"Em andamento","Não iniciado"))))) -> Em andamento | O21: =IF(H21+I21+J21+K21+M21<=0,0,M21/(H21+I21+J21+K21+M21)) -> 0.47058824
A22: SPR-1239 | B22: (Comercial) Aderência | C22: Comercial | D22: =IF(COUNT('Cálculos (apoio)'!$AM$4:$AM$502)=0,"",MAX('Cálculos (apoio)'!$AM$4:$AM$502)) -> 46279 | E22: =IF(N22="Finalizado",IF(COUNT('Cálculos (apoio)'!$AN$4:$AN$502)=0,"",MAX('Cálculos (apoio)'!$AN$4:$AN$502)),"") | F22: =COUNTIFS('Atividades Micro'!$B$2:$B$554,$B22,'Atividades Micro'!$G$2:$G$554,"Macro") -> 2 | G22: =COUNTIFS('Atividades Micro'!$B$2:$B$554,$B22,'Atividades Micro'!$G$2:$G$554,"Micro",'Atividades Micro'!$J$2:$J$554,"<>Cancelado") -> 5 | H22: =COUNTIFS('Atividades Micro'!$B$2:$B$554,$B22,'Atividades Micro'!$J$2:$J$554,H$1) -> 3 | I22: =COUNTIFS('Atividades Micro'!$B$2:$B$554,$B22,'Atividades Micro'!$J$2:$J$554,I$1) -> 0 | J22: =COUNTIFS('Atividades Micro'!$B$2:$B$554,$B22,'Atividades Micro'!$J$2:$J$554,J$1) -> 0 | K22: =COUNTIFS('Atividades Micro'!$B$2:$B$554,$B22,'Atividades Micro'!$J$2:$J$554,K$1) -> 0 | L22: =COUNTIFS('Atividades Micro'!$B$2:$B$554,$B22,'Atividades Micro'!$J$2:$J$554,L$1) -> 0 | M22: =COUNTIFS('Atividades Micro'!$B$2:$B$554,$B22,'Atividades Micro'!$J$2:$J$554,M$1) -> 4 | N22: =IF(H22+I22+J22+K22+M22=0,IF(L22>0,"Cancelado","Não iniciado"),IF(M22=H22+I22+J22+K22+M22,"Finalizado",IF(K22>0,"Bloqueado",IF(J22>0,"Testes QA",IF(OR(I22>0,M22>0),"Em andamento","Não iniciado"))))) -> Em andamento | O22: =IF(H22+I22+J22+K22+M22<=0,0,M22/(H22+I22+J22+K22+M22)) -> 0.57142857
A23: SPR-1239 | B23: (Comercial) Satélites | C23: Comercial | D23: =IF(COUNT('Cálculos (apoio)'!$AO$4:$AO$502)=0,"",MAX('Cálculos (apoio)'!$AO$4:$AO$502)) -> 46301 | E23: =IF(N23="Finalizado",IF(COUNT('Cálculos (apoio)'!$AP$4:$AP$502)=0,"",MAX('Cálculos (apoio)'!$AP$4:$AP$502)),"") | F23: =COUNTIFS('Atividades Micro'!$B$2:$B$554,$B23,'Atividades Micro'!$G$2:$G$554,"Macro") -> 2 | G23: =COUNTIFS('Atividades Micro'!$B$2:$B$554,$B23,'Atividades Micro'!$G$2:$G$554,"Micro",'Atividades Micro'!$J$2:$J$554,"<>Cancelado") -> 9 | H23: =COUNTIFS('Atividades Micro'!$B$2:$B$554,$B23,'Atividades Micro'!$J$2:$J$554,H$1) -> 4 | I23: =COUNTIFS('Atividades Micro'!$B$2:$B$554,$B23,'Atividades Micro'!$J$2:$J$554,I$1) -> 3 | J23: =COUNTIFS('Atividades Micro'!$B$2:$B$554,$B23,'Atividades Micro'!$J$2:$J$554,J$1) -> 0 | K23: =COUNTIFS('Atividades Micro'!$B$2:$B$554,$B23,'Atividades Micro'!$J$2:$J$554,K$1) -> 0 | L23: =COUNTIFS('Atividades Micro'!$B$2:$B$554,$B23,'Atividades Micro'!$J$2:$J$554,L$1) -> 4 | M23: =COUNTIFS('Atividades Micro'!$B$2:$B$554,$B23,'Atividades Micro'!$J$2:$J$554,M$1) -> 4 | N23: =IF(H23+I23+J23+K23+M23=0,IF(L23>0,"Cancelado","Não iniciado"),IF(M23=H23+I23+J23+K23+M23,"Finalizado",IF(K23>0,"Bloqueado",IF(J23>0,"Testes QA",IF(OR(I23>0,M23>0),"Em andamento","Não iniciado"))))) -> Em andamento | O23: =IF(H23+I23+J23+K23+M23<=0,0,M23/(H23+I23+J23+K23+M23)) -> 0.36363636
A24: SRM-37 | B24: TOTVS / RM | Fusão Petz Cobasi | C24: TOTVS RM | D24: 46321 | E24: =IF(N24="Finalizado",IF(COUNT('Cálculos (apoio)'!$AR$4:$AR$502)=0,"",MAX('Cálculos (apoio)'!$AR$4:$AR$502)),"") | F24: =COUNTIFS('Atividades Micro'!$A$2:$A$554,$C24,'Atividades Micro'!$G$2:$G$554,"Macro") -> 1 | G24: =COUNTIFS('Atividades Micro'!$A$2:$A$554,$C24,'Atividades Micro'!$G$2:$G$554,"Micro",'Atividades Micro'!$J$2:$J$554,"<>Cancelado") -> 10 | H24: =COUNTIFS('Atividades Micro'!$A$2:$A$554,$C24,'Atividades Micro'!$J$2:$J$554,H$1) -> 2 | I24: =COUNTIFS('Atividades Micro'!$A$2:$A$554,$C24,'Atividades Micro'!$J$2:$J$554,I$1) -> 1 | J24: =COUNTIFS('Atividades Micro'!$A$2:$A$554,$C24,'Atividades Micro'!$J$2:$J$554,J$1) -> 0 | K24: =COUNTIFS('Atividades Micro'!$A$2:$A$554,$C24,'Atividades Micro'!$J$2:$J$554,K$1) -> 0 | L24: =COUNTIFS('Atividades Micro'!$A$2:$A$554,$C24,'Atividades Micro'!$J$2:$J$554,L$1) -> 1 | M24: =COUNTIFS('Atividades Micro'!$A$2:$A$554,$C24,'Atividades Micro'!$J$2:$J$554,M$1) -> 8 | N24: =IF(H24+I24+J24+K24+M24=0,IF(L24>0,"Cancelado","Não iniciado"),IF(M24=H24+I24+J24+K24+M24,"Finalizado",IF(K24>0,"Bloqueado",IF(J24>0,"Testes QA",IF(OR(I24>0,M24>0),"Em andamento","Não iniciado"))))) -> Em andamento | O24: =IF(H24+I24+J24+K24+M24<=0,0,M24/(H24+I24+J24+K24+M24)) -> 0.72727273
A25: SRM-37 | B25: (TOTVS RM) Aderência | C25: TOTVS RM | D25: =IF(COUNT('Cálculos (apoio)'!$AS$4:$AS$502)=0,"",MAX('Cálculos (apoio)'!$AS$4:$AS$502)) -> 46342 | E25: =IF(N25="Finalizado",IF(COUNT('Cálculos (apoio)'!$AT$4:$AT$502)=0,"",MAX('Cálculos (apoio)'!$AT$4:$AT$502)),"") | F25: =COUNTIFS('Atividades Micro'!$B$2:$B$554,$B25,'Atividades Micro'!$G$2:$G$554,"Macro") -> 1 | G25: =COUNTIFS('Atividades Micro'!$B$2:$B$554,$B25,'Atividades Micro'!$G$2:$G$554,"Micro",'Atividades Micro'!$J$2:$J$554,"<>Cancelado") -> 10 | H25: =COUNTIFS('Atividades Micro'!$B$2:$B$554,$B25,'Atividades Micro'!$J$2:$J$554,H$1) -> 2 | I25: =COUNTIFS('Atividades Micro'!$B$2:$B$554,$B25,'Atividades Micro'!$J$2:$J$554,I$1) -> 1 | J25: =COUNTIFS('Atividades Micro'!$B$2:$B$554,$B25,'Atividades Micro'!$J$2:$J$554,J$1) -> 0 | K25: =COUNTIFS('Atividades Micro'!$B$2:$B$554,$B25,'Atividades Micro'!$J$2:$J$554,K$1) -> 0 | L25: =COUNTIFS('Atividades Micro'!$B$2:$B$554,$B25,'Atividades Micro'!$J$2:$J$554,L$1) -> 1 | M25: =COUNTIFS('Atividades Micro'!$B$2:$B$554,$B25,'Atividades Micro'!$J$2:$J$554,M$1) -> 8 | N25: =IF(H25+I25+J25+K25+M25=0,IF(L25>0,"Cancelado","Não iniciado"),IF(M25=H25+I25+J25+K25+M25,"Finalizado",IF(K25>0,"Bloqueado",IF(J25>0,"Testes QA",IF(OR(I25>0,M25>0),"Em andamento","Não iniciado"))))) -> Em andamento | O25: =IF(H25+I25+J25+K25+M25<=0,0,M25/(H25+I25+J25+K25+M25)) -> 0.72727273
A26: PTZO-551 | B26: ZANTHUS PDV | Fusão Petz Cobasi | C26: Zanthus | D26: 46337 | E26: =IF(N26="Finalizado",IF(COUNT('Cálculos (apoio)'!$AV$4:$AV$502)=0,"",MAX('Cálculos (apoio)'!$AV$4:$AV$502)),"") | F26: =COUNTIFS('Atividades Micro'!$A$2:$A$554,$C26,'Atividades Micro'!$G$2:$G$554,"Macro") -> 1 | G26: =COUNTIFS('Atividades Micro'!$A$2:$A$554,$C26,'Atividades Micro'!$G$2:$G$554,"Micro",'Atividades Micro'!$J$2:$J$554,"<>Cancelado") -> 14 | H26: =COUNTIFS('Atividades Micro'!$A$2:$A$554,$C26,'Atividades Micro'!$J$2:$J$554,H$1) -> 0 | I26: =COUNTIFS('Atividades Micro'!$A$2:$A$554,$C26,'Atividades Micro'!$J$2:$J$554,I$1) -> 2 | J26: =COUNTIFS('Atividades Micro'!$A$2:$A$554,$C26,'Atividades Micro'!$J$2:$J$554,J$1) -> 0 | K26: =COUNTIFS('Atividades Micro'!$A$2:$A$554,$C26,'Atividades Micro'!$J$2:$J$554,K$1) -> 0 | L26: =COUNTIFS('Atividades Micro'!$A$2:$A$554,$C26,'Atividades Micro'!$J$2:$J$554,L$1) -> 0 | M26: =COUNTIFS('Atividades Micro'!$A$2:$A$554,$C26,'Atividades Micro'!$J$2:$J$554,M$1) -> 13 | N26: =IF(H26+I26+J26+K26+M26=0,IF(L26>0,"Cancelado","Não iniciado"),IF(M26=H26+I26+J26+K26+M26,"Finalizado",IF(K26>0,"Bloqueado",IF(J26>0,"Testes QA",IF(OR(I26>0,M26>0),"Em andamento","Não iniciado"))))) -> Em andamento | O26: =IF(H26+I26+J26+K26+M26<=0,0,M26/(H26+I26+J26+K26+M26)) -> 0.86666667
A27: PTZO-551 | B27: (Zanthus) Aderência | C27: Zanthus | D27: =IF(COUNT('Cálculos (apoio)'!$AW$4:$AW$502)=0,"",MAX('Cálculos (apoio)'!$AW$4:$AW$502)) -> 46338 | E27: =IF(N27="Finalizado",IF(COUNT('Cálculos (apoio)'!$AX$4:$AX$502)=0,"",MAX('Cálculos (apoio)'!$AX$4:$AX$502)),"") | F27: =COUNTIFS('Atividades Micro'!$B$2:$B$554,$B27,'Atividades Micro'!$G$2:$G$554,"Macro") -> 1 | G27: =COUNTIFS('Atividades Micro'!$B$2:$B$554,$B27,'Atividades Micro'!$G$2:$G$554,"Micro",'Atividades Micro'!$J$2:$J$554,"<>Cancelado") -> 14 | H27: =COUNTIFS('Atividades Micro'!$B$2:$B$554,$B27,'Atividades Micro'!$J$2:$J$554,H$1) -> 0 | I27: =COUNTIFS('Atividades Micro'!$B$2:$B$554,$B27,'Atividades Micro'!$J$2:$J$554,I$1) -> 2 | J27: =COUNTIFS('Atividades Micro'!$B$2:$B$554,$B27,'Atividades Micro'!$J$2:$J$554,J$1) -> 0 | K27: =COUNTIFS('Atividades Micro'!$B$2:$B$554,$B27,'Atividades Micro'!$J$2:$J$554,K$1) -> 0 | L27: =COUNTIFS('Atividades Micro'!$B$2:$B$554,$B27,'Atividades Micro'!$J$2:$J$554,L$1) -> 0 | M27: =COUNTIFS('Atividades Micro'!$B$2:$B$554,$B27,'Atividades Micro'!$J$2:$J$554,M$1) -> 13 | N27: =IF(H27+I27+J27+K27+M27=0,IF(L27>0,"Cancelado","Não iniciado"),IF(M27=H27+I27+J27+K27+M27,"Finalizado",IF(K27>0,"Bloqueado",IF(J27>0,"Testes QA",IF(OR(I27>0,M27>0),"Em andamento","Não iniciado"))))) -> Em andamento | O27: =IF(H27+I27+J27+K27+M27<=0,0,M27/(H27+I27+J27+K27+M27)) -> 0.86666667
A28: MERP- | B28: OPERAÇÕES | Fusão - Petz Cobasi | C28: Operações | D28: 46288 | E28: =IF(N28="Finalizado",IF(COUNT('Cálculos (apoio)'!$AZ$4:$AZ$502)=0,"",MAX('Cálculos (apoio)'!$AZ$4:$AZ$502)),"") | F28: =COUNTIFS('Atividades Micro'!$A$2:$A$554,$C28,'Atividades Micro'!$G$2:$G$554,"Macro") -> 2 | G28: =COUNTIFS('Atividades Micro'!$A$2:$A$554,$C28,'Atividades Micro'!$G$2:$G$554,"Micro",'Atividades Micro'!$J$2:$J$554,"<>Cancelado") -> 2 | H28: =COUNTIFS('Atividades Micro'!$A$2:$A$554,$C28,'Atividades Micro'!$J$2:$J$554,H$1) -> 1 | I28: =COUNTIFS('Atividades Micro'!$A$2:$A$554,$C28,'Atividades Micro'!$J$2:$J$554,I$1) -> 2 | J28: =COUNTIFS('Atividades Micro'!$A$2:$A$554,$C28,'Atividades Micro'!$J$2:$J$554,J$1) -> 0 | K28: =COUNTIFS('Atividades Micro'!$A$2:$A$554,$C28,'Atividades Micro'!$J$2:$J$554,K$1) -> 0 | L28: =COUNTIFS('Atividades Micro'!$A$2:$A$554,$C28,'Atividades Micro'!$J$2:$J$554,L$1) -> 2 | M28: =COUNTIFS('Atividades Micro'!$A$2:$A$554,$C28,'Atividades Micro'!$J$2:$J$554,M$1) -> 0 | N28: =IF(H28+I28+J28+K28+M28=0,IF(L28>0,"Cancelado","Não iniciado"),IF(M28=H28+I28+J28+K28+M28,"Finalizado",IF(K28>0,"Bloqueado",IF(J28>0,"Testes QA",IF(OR(I28>0,M28>0),"Em andamento","Não iniciado"))))) -> Em andamento | O28: =IF(H28+I28+J28+K28+M28<=0,0,M28/(H28+I28+J28+K28+M28)) -> 0
A29: MERP- | B29: (Operações) Satélites | C29: Operações | D29: =IF(COUNT('Cálculos (apoio)'!$BA$4:$BA$502)=0,"",MAX('Cálculos (apoio)'!$BA$4:$BA$502)) -> 46352 | E29: =IF(N29="Finalizado",IF(COUNT('Cálculos (apoio)'!$BB$4:$BB$502)=0,"",MAX('Cálculos (apoio)'!$BB$4:$BB$502)),"") | F29: =COUNTIFS('Atividades Micro'!$B$2:$B$554,$B29,'Atividades Micro'!$G$2:$G$554,"Macro") -> 2 | G29: =COUNTIFS('Atividades Micro'!$B$2:$B$554,$B29,'Atividades Micro'!$G$2:$G$554,"Micro",'Atividades Micro'!$J$2:$J$554,"<>Cancelado") -> 2 | H29: =COUNTIFS('Atividades Micro'!$B$2:$B$554,$B29,'Atividades Micro'!$J$2:$J$554,H$1) -> 1 | I29: =COUNTIFS('Atividades Micro'!$B$2:$B$554,$B29,'Atividades Micro'!$J$2:$J$554,I$1) -> 2 | J29: =COUNTIFS('Atividades Micro'!$B$2:$B$554,$B29,'Atividades Micro'!$J$2:$J$554,J$1) -> 0 | K29: =COUNTIFS('Atividades Micro'!$B$2:$B$554,$B29,'Atividades Micro'!$J$2:$J$554,K$1) -> 0 | L29: =COUNTIFS('Atividades Micro'!$B$2:$B$554,$B29,'Atividades Micro'!$J$2:$J$554,L$1) -> 2 | M29: =COUNTIFS('Atividades Micro'!$B$2:$B$554,$B29,'Atividades Micro'!$J$2:$J$554,M$1) -> 0 | N29: =IF(H29+I29+J29+K29+M29=0,IF(L29>0,"Cancelado","Não iniciado"),IF(M29=H29+I29+J29+K29+M29,"Finalizado",IF(K29>0,"Bloqueado",IF(J29>0,"Testes QA",IF(OR(I29>0,M29>0),"Em andamento","Não iniciado"))))) -> Em andamento | O29: =IF(H29+I29+J29+K29+M29<=0,0,M29/(H29+I29+J29+K29+M29)) -> 0

Sheet Atividades Micro
A1: Frente consolidada | B1: Linha macro | C1: Ticket Epic | D1: Ticket atividade | E1: Atividade | F1: Pai | G1: Tipo de registro | H1: Hierarquia | I1: Categoria | J1: Status | K1: Data Planejada | L1: Data fim real | M1: Linha na matriz
A2: (Migração ERP) Infraestrutura | B2: Infraestrutura - Fusão - Grupo PetzCobasi | C2: MERP-7406 | E2: Mapeamento da infraestrutura | G2: Macro | H2: História | I2: Infraestrutura | J2: Finalizado | K2: 46196 | M2: 3
A3: (Migração ERP) Infraestrutura | B3: Infraestrutura - Fusão - Grupo PetzCobasi | C3: MERP-7406 | E3: Desenho do Sizing da topologia de Servidores (Produção) | G3: Macro | H3: História | I3: Infraestrutura | J3: Finalizado | K3: 46199 | M3: 4
A4: (Migração ERP) Infraestrutura | B4: Infraestrutura - Fusão - Grupo PetzCobasi | C4: MERP-7406 | E4: Criação Ambiente Zanthus (Laboratório Fusão) | G4: Macro | H4: História | I4: Infraestrutura | J4: Finalizado | K4: 46210 | L4: 46231 | M4: 5
A5: (Migração ERP) Infraestrutura | B5: Infraestrutura - Fusão - Grupo PetzCobasi | C5: MERP-7406 | E5: Criação Ambiente Protheus (Laboratório Fusão) | G5: Macro | H5: História | I5: Infraestrutura | J5: Finalizado | K5: 46210 | M5: 6
A6: (Migração ERP) Infraestrutura | B6: Infraestrutura - Fusão - Grupo PetzCobasi | C6: MERP-7406 | E6: Criação Ambiente Zanthus (Homologação) | G6: Macro | H6: História | I6: Infraestrutura | J6: Não iniciado | K6: 46398 | M6: 7
A7: (Migração ERP) Infraestrutura | B7: Infraestrutura - Fusão - Grupo PetzCobasi | C7: MERP-7406 | E7: Criação Ambiente Protheus (Homologação) - (Subir Serviços a parte para Cobasi - Lojas, Coletor, CD, E-com-Vetx) | G7: Macro | H7: História | I7: Infraestrutura | J7: Não iniciado | K7: 46398 | M7: 8
A8: (Migração ERP) Infraestrutura | B8: Infraestrutura - Fusão - Grupo PetzCobasi | C8: MERP-7406 | E8: Upgrade Ambiente Zanthus (atualiação do ambiente de Produção) | G8: Macro | H8: História | I8: Infraestrutura | J8: Não iniciado | K8: 46568 | M8: 9
A9: (Migração ERP) Infraestrutura | B9: Infraestrutura - Fusão - Grupo PetzCobasi | C9: MERP-7406 | E9: Upgrade Ambiente Protheus (atualiação do ambiente de Produção) | G9: Macro | H9: História | I9: Infraestrutura | J9: Não iniciado | K9: 46568 | M9: 10
A10: (Migração ERP) Infraestrutura | B10: Infraestrutura - Fusão - Grupo PetzCobasi | C10: MERP-7406 | E10: Construção do Teste de Capacity (Digital e Protheus) | G10: Macro | H10: História | I10: Infraestrutura | J10: Não iniciado | K10: 46356 | M10: 11
A11: (Migração ERP) Infraestrutura | B11: Infraestrutura - Fusão - Grupo PetzCobasi | C11: MERP-7406 | E11: Teste de Capacity (Digital e Protheus) - Pré BigBang | G11: Macro | H11: História | I11: Infraestrutura | J11: Não iniciado | K11: 46476 | M11: 12
B12: Infraestrutura - Fusão - Grupo PetzCobasi | C12: MERP-7406 | E12: Criação de usuários (Zanthus | Protheus | RM) | G12: Macro | H12: História | I12: Infraestrutura | J12: Em andamento | K12: 46418
A13: (Migração ERP) Infraestrutura | B13: Infraestrutura - Fusão - Grupo PetzCobasi | C13: MERP-7406 | E13: Definição da Infra para RM-RH (Totvs ou Skyone) e Sizing | G13: Macro | H13: História | I13: Infraestrutura | J13: Não iniciado | K13: 46295 | M13: 13
A14: (Migração ERP) Infraestrutura | B14: Infraestrutura - Fusão - Grupo PetzCobasi | C14: MERP-7406 | E14: Quais serviços subir DEV (Subir Serviços a parte para Cobasi - Lojas, Coletor, CD, E-com-Vetx) | G14: Macro | H14: História | I14: Infraestrutura | J14: Finalizado | K14: 46210 | M14: 14
A15: Financeiro | B15: (Financeiro) Aderência | C15: SPR-626 | D15: SPR-1149 | E15: [0426-002521] Desenvolver CNAB a pagar Itau | G15: Macro | H15: História | I15: Aderência | J15: Finalizado | K15: 46225 | M15: 16
A16: Financeiro | B16: (Financeiro) Aderência | C16: SPR-626 | E16: Documentação do layout com Banco | G16: Micro | H16: Atividade | I16: Aderência | J16: Finalizado | K16: 46216 | L16: 46216 | M16: 17
A17: Financeiro | B17: (Financeiro) Aderência | C17: SPR-626 | E17: Desenvolvimento | G17: Micro | H17: Atividade | I17: Aderência | J17: Finalizado | K17: 46223 | L17: 46223 | M17: 18
A18: Financeiro | B18: (Financeiro) Aderência | C18: SPR-626 | E18: Testes QA | G18: Micro | H18: Atividade | I18: Aderência | J18: Finalizado | K18: 46225 | L18: 46225 | M18: 19
A19: Financeiro | B19: (Financeiro) Aderência | C19: SPR-626 | D19: SPR-1140 | E19: [0426-002609] Desenvolver CNAB a pagar Banco do Brasil | G19: Macro | H19: História | I19: Aderência | J19: Cancelado | K19: 46226 | M19: 20
A20: Financeiro | B20: (Financeiro) Aderência | C20: SPR-626 | E20: Desenvolvimento | G20: Micro | H20: Atividade | I20: Aderência | J20: Cancelado | K20: 46233 | M20: 21
A21: Financeiro | B21: (Financeiro) Aderência | C21: SPR-626 | E21: Testes QA | G21: Micro | H21: Atividade | I21: Aderência | J21: Cancelado | K21: 46238 | M21: 22
A22: Financeiro | B22: (Financeiro) Aderência | C22: SPR-626 | D22: SPR-1092 | E22: Desenvolver melhoria nos Pagamentos de Tributos | G22: Macro | H22: História | I22: Aderência | J22: Finalizado | K22: 46234 | M22: 23
A23: Financeiro | B23: (Financeiro) Aderência | C23: SPR-626 | E23: Desenvolvimento | G23: Micro | H23: Atividade | I23: Aderência | J23: Finalizado | K23: 46232 | L23: 46227 | M23: 24
A24: Financeiro | B24: (Financeiro) Aderência | C24: SPR-626 | E24: Testes QA | G24: Micro | H24: Atividade | I24: Aderência | J24: Finalizado | K24: 46234 | L24: 46234 | M24: 25
A25: Financeiro | B25: (Financeiro) Aderência | C25: SPR-626 | E25: CR - Melhorias a serem definidas | G25: Micro | H25: Atividade | I25: Aderência | J25: Não iniciado
A26: Financeiro | B26: (Financeiro) Satélites | C26: SPR-626 | D26: ??? | E26: Integração Portal Gedi | G26: Macro | H26: História | I26: Satélites | J26: Em andamento | K26: 46335 | M26: 26
A27: Financeiro | B27: (Financeiro) Satélites | C27: SPR-626 | E27: Proposta Gedi | G27: Micro | H27: Atividade | I27: Satélites | J27: Finalizado | K27: 46276 | L27: 46317 | M27: 27
A28: Financeiro | B28: (Financeiro) Satélites | C28: SPR-626 | E28: Implantação Portal - Empresa 04 e 14 | G28: Micro | H28: Atividade | I28: Satélites | J28: Finalizado | K28: 46286 | L28: 46290 | M28: 28
A29: Financeiro | B29: (Financeiro) Satélites | C29: SPR-626 | E29: Integração Portal Gedi c/ Sistemas Satélites | G29: Macro | H29: Atividade | I29: Satélites | J29: Em andamento | K29: 46363 | M29: 29
A30: Financeiro | B30: (Financeiro) Satélites | C30: SPR-626 | E30: Integração GEDI x Protheus | G30: Micro | H30: Atividade | I30: Satélites | J30: Em andamento | K30: 46308 | M30: 30
A31: Financeiro | B31: (Financeiro) Satélites | C31: SPR-626 | E31: Testes QA | G31: Micro | H31: Atividade | I31: Satélites | J31: Não iniciado | K31: 46315 | M31: 31
A32: Financeiro | B32: (Financeiro) Satélites | C32: SPR-626 | E32: Integração GEDI x Turin | G32: Micro | H32: Atividade | I32: Satélites | J32: Finalizado | K32: 46318 | L32: 46290 | M32: 32
A33: Financeiro | B33: (Financeiro) Satélites | C33: SPR-626 | E33: Testes QA | G33: Micro | H33: Atividade | I33: Satélites | J33: Não iniciado | K33: 46325 | M33: 33
A34: Financeiro | B34: (Financeiro) Satélites | C34: SPR-626 | E34: Integração GEDI x Tecsus | G34: Micro | H34: Atividade | I34: Satélites | J34: Finalizado | K34: 46331 | L34: 46288 | M34: 34
A35: Financeiro | B35: (Financeiro) Satélites | C35: SPR-626 | E35: Testes QA | G35: Micro | H35: Atividade | I35: Satélites | J35: Não iniciado | K35: 46338 | M35: 35
A36: Financeiro | B36: (Financeiro) Satélites | C36: SPR-626 | E36: Integração GEDI x RM | G36: Micro | H36: Atividade | I36: Satélites | J36: Não iniciado | K36: 46344 | M36: 36
A37: Financeiro | B37: (Financeiro) Satélites | C37: SPR-626 | E37: Testes QA | G37: Micro | H37: Atividade | I37: Satélites | J37: Não iniciado | K37: 46352 | M37: 37
A38: Financeiro | B38: (Financeiro) Satélites | C38: SPR-626 | E38: Desenvolvimento: Gedi (API p/ consumir) | G38: Micro | H38: Atividade | I38: Satélites | J38: Não iniciado | K38: 46356 | M38: 38
A39: Financeiro | B39: (Financeiro) Satélites | C39: SPR-626 | E39: Testes QA | G39: Micro | H39: Atividade | I39: Satélites | J39: Não iniciado | K39: 46363 | M39: 39
A40: Financeiro | B40: (Financeiro) Satélites | C40: SPR-626 | D40: SPR-1476 | E40: [FUSÃO] GEDI - Capturar documento fiscal ou financeiro capturado por aplicação externa | G40: Micro | H40: Atividade | I40: Satélites | J40: Finalizado | K40: 46244 | L40: 46246 | M40: 40
A41: Financeiro | B41: (Financeiro) Satélites | C41: SPR-626 | E41: Testes QA | G41: Micro | H41: Atividade | I41: Satélites | J41: Finalizado | K41: 46247 | L41: 46246 | M41: 41
A42: Financeiro | B42: (Financeiro) Satélites | C42: SPR-626 | D42: SPR-1477 | E42: [FUSÃO] GEDI - Processar os documentos capturados gerando SP genérica aprovada (NFS e Financeiro) | G42: Micro | H42: Atividade | I42: Satélites | J42: Finalizado | K42: 46258 | L42: 46258 | M42: 42
A43: Financeiro | B43: (Financeiro) Satélites | C43: SPR-626 | E43: Testes QA | G43: Micro | H43: Atividade | I43: Satélites | J43: Finalizado | K43: 46265 | L43: 46265 | M43: 43
A44: Financeiro | B44: (Financeiro) Satélites | C44: SPR-626 | D44: SPR-1478 | E44: [FUSÃO] GEDI - Atualizar fila de integração com status da pré-nota XML | G44: Micro | H44: Atividade | I44: Satélites | J44: Finalizado | K44: 46267 | L44: 46267 | M44: 44
A45: Financeiro | B45: (Financeiro) Satélites | C45: SPR-626 | E45: Testes QA | G45: Micro | H45: Atividade | I45: Satélites | J45: Finalizado | K45: 46269 | L45: 46269 | M45: 45
A46: Financeiro | B46: (Financeiro) Satélites | C46: SPR-626 | D46: SPR-1479 | E46: [FUSÃO] GEDI - Atualizar fila de integração com status da classificação do documento | G46: Micro | H46: Atividade | I46: Satélites | J46: Finalizado | K46: 46274 | L46: 46274 | M46: 46
A47: Financeiro | B47: (Financeiro) Satélites | C47: SPR-626 | E47: Testes QA | G47: Micro | H47: Atividade | I47: Satélites | J47: Finalizado | K47: 46276 | L47: 46280 | M47: 47
A48: Financeiro | B48: (Financeiro) Satélites | C48: SPR-626 | D48: SPR-1480 | E48: [FUSÃO] GEDI - Atualizar fila de integração com exclusão da classificação do documento | G48: Micro | H48: Atividade | I48: Satélites | J48: Finalizado | K48: 46280 | L48: 46261 | M48: 48
A49: Financeiro | B49: (Financeiro) Satélites | C49: SPR-626 | E49: Testes QA | G49: Micro | H49: Atividade | I49: Satélites | J49: Finalizado | K49: 46281 | L49: 46262 | M49: 49
A50: Financeiro | B50: (Financeiro) Satélites | C50: SPR-626 | D50: SPR-1481 | E50: [FUSÃO] GEDI - Atualizar fila de integração com estorno da classificação do documento | G50: Micro | H50: Atividade | I50: Satélites | J50: Finalizado | K50: 46283 | L50: 46261 | M50: 50
A51: Financeiro | B51: (Financeiro) Satélites | C51: SPR-626 | E51: Testes QA | G51: Micro | H51: Atividade | I51: Satélites | J51: Finalizado | K51: 46286 | L51: 46262 | M51: 51
A52: Financeiro | B52: (Financeiro) Satélites | C52: SPR-626 | D52: SPR-1482 | E52: [FUSÃO] GEDI - Atualizar fila de integração com inclusão do título financeiro | G52: Micro | H52: Atividade | I52: Satélites | J52: Finalizado | K52: 46288 | L52: 46266 | M52: 52
A53: Financeiro | B53: (Financeiro) Satélites | C53: SPR-626 | E53: Testes QA | G53: Micro | H53: Atividade | I53: Satélites | J53: Finalizado | K53: 46289 | L53: 46266 | M53: 53
A54: Financeiro | B54: (Financeiro) Satélites | C54: SPR-626 | D54: SPR-1483 | E54: [FUSÃO] GEDI - Atualizar fila de integração com exclusão do título financeiro | G54: Micro | H54: Atividade | I54: Satélites | J54: Finalizado | K54: 46293 | L54: 46266 | M54: 54
A55: Financeiro | B55: (Financeiro) Satélites | C55: SPR-626 | E55: Testes QA | G55: Micro | H55: Atividade | I55: Satélites | J55: Finalizado | K55: 46294 | L55: 46266 | M55: 55
A56: Financeiro | B56: (Financeiro) Satélites | C56: SPR-626 | D56: SPR-1484 | E56: [FUSÃO] GEDI - Processar os documentos capturados gerando SP genérica aprovada (CTe e NFe) | G56: Micro | H56: Atividade | I56: Satélites | J56: Finalizado | K56: 46303 | L56: 46258 | M56: 56
A57: Financeiro | B57: (Financeiro) Satélites | C57: SPR-626 | E57: Testes QA | G57: Micro | H57: Atividade | I57: Satélites | J57: Finalizado | K57: 46311 | L57: 46301 | M57: 57
A58: Financeiro | B58: (Financeiro) Satélites | C58: SPR-626 | D58: SPR-1485 | E58: [FUSÃO] GEDI - Disponibilizar consulta para fila de registros integrados | G58: Micro | H58: Atividade | I58: Satélites | J58: Finalizado | K58: 46316 | L58: 46308 | M58: 58
A59: Financeiro | B59: (Financeiro) Satélites | C59: SPR-626 | E59: Testes QA | G59: Micro | H59: Atividade | I59: Satélites | J59: Finalizado | K59: 46317 | L59: 46308 | M59: 59
A60: Financeiro | B60: (Financeiro) Satélites | C60: SPR-626 | D60: SPR-1486 | E60: [FUSÃO] GEDI - Disponibilizar fila de registros integrados para alteração de status | G60: Micro | H60: Atividade | I60: Satélites | J60: Finalizado | K60: 46322 | L60: 46309 | M60: 60
A61: Financeiro | B61: (Financeiro) Satélites | C61: SPR-626 | E61: Testes QA | G61: Micro | H61: Atividade | I61: Satélites | J61: Finalizado | K61: 46323 | L61: 46309 | M61: 61
A62: Financeiro | B62: (Financeiro) Satélites | C62: SPR-626 | D62: SPR-1487 | E62: [FUSÃO] GEDI - Gerar títulos financeiros bloqueados para pagamento | G62: Micro | H62: Atividade | I62: Satélites | J62: Não iniciado | K62: 46330 | M62: 62
A63: Financeiro | B63: (Financeiro) Satélites | C63: SPR-626 | E63: Testes QA | G63: Micro | H63: Atividade | I63: Satélites | J63: Não iniciado | K63: 46332 | M63: 63
A64: Financeiro | B64: (Financeiro) Satélites | C64: SPR-626 | D64: SPR-1488 | E64: [FUSÃO] GEDI - Possibilitar a liberação de pagamento dos títulos financeiros criados pela integração | G64: Micro | H64: Atividade | I64: Satélites | J64: Não iniciado | K64: 46337 | M64: 64
A65: Financeiro | B65: (Financeiro) Satélites | C65: SPR-626 | E65: Testes QA | G65: Micro | H65: Atividade | I65: Satélites | J65: Não iniciado | K65: 46338 | M65: 65
A66: Financeiro | B66: (Financeiro) Satélites | C66: SPR-626 | D66: SPR-1489 | E66: [FUSÃO] GEDI - Disponibilizar consulta de cadastro de fornecedores | G66: Micro | H66: Atividade | I66: Satélites | J66: Finalizado | K66: 46342 | L66: 46252 | M66: 66
A67: Financeiro | B67: (Financeiro) Satélites | C67: SPR-626 | E67: Testes QA | G67: Micro | H67: Atividade | I67: Satélites | J67: Finalizado | K67: 46343 | L67: 46255 | M67: 67
A68: Financeiro | B68: (Financeiro) Satélites | C68: SPR-626 | D68: SPR-1490 | E68: [FUSÃO] GEDI - Disponibilizar consulta de cadastro de produtos | G68: Micro | H68: Atividade | I68: Satélites | J68: Finalizado | K68: 46349 | L68: 46253 | M68: 68
A69: Financeiro | B69: (Financeiro) Satélites | C69: SPR-626 | E69: Testes QA | G69: Micro | H69: Atividade | I69: Satélites | J69: Finalizado | K69: 46350 | L69: 46255 | M69: 69
A70: Financeiro | B70: (Financeiro) Satélites | C70: SPR-626 | D70: SPR-1491 | E70: [FUSÃO] GEDI - Disponibilizar consulta de cadastro de empresa/filial | G70: Micro | H70: Atividade | I70: Satélites | J70: Finalizado | K70: 46352 | L70: 46265 | M70: 70
A71: Financeiro | B71: (Financeiro) Satélites | C71: SPR-626 | E71: Testes QA | G71: Micro | H71: Atividade | I71: Satélites | J71: Finalizado | K71: 46353 | L71: 46265 | M71: 71
A72: Financeiro | B72: (Financeiro) Satélites | C72: SPR-626 | D72: SPR-1492 | E72: [FUSÃO] GEDI - Disponibilizar consulta de cadastro de condição de pagamento | G72: Micro | H72: Atividade | I72: Satélites | J72: Finalizado | K72: 46345 | L72: 46269 | M72: 72
A73: Financeiro | B73: (Financeiro) Satélites | C73: SPR-626 | E73: Testes QA | G73: Micro | H73: Atividade | I73: Satélites | J73: Finalizado | K73: 46349 | L73: 46269 | M73: 73
A74: Financeiro | B74: (Financeiro) Satélites | C74: SPR-626 | D74: SPR-1493 | E74: [FUSÃO] GEDI - Disponibilizar consulta de cadastro de centro de custos | G74: Micro | H74: Atividade | I74: Satélites | J74: Finalizado | K74: 46351 | L74: 46281 | M74: 74
A75: Financeiro | B75: (Financeiro) Satélites | C75: SPR-626 | E75: Testes QA | G75: Micro | H75: Atividade | I75: Satélites | J75: Finalizado | K75: 46352 | L75: 46281 | M75: 75
A76: Financeiro | B76: (Financeiro) Satélites | C76: SPR-626 | D76: SPR-1494 | E76: [FUSÃO] GEDI - Disponibilizar consulta de cadastro de item contábil | G76: Micro | H76: Atividade | I76: Satélites | J76: Finalizado | K76: 46356 | L76: 46287 | M76: 76
A77: Financeiro | B77: (Financeiro) Satélites | C77: SPR-626 | E77: Testes QA | G77: Micro | H77: Atividade | I77: Satélites | J77: Finalizado | K77: 46357 | L77: 46288 | M77: 77
A78: Financeiro | B78: (Financeiro) Satélites | C78: SPR-626 | D78: SPR-1495 | E78: [FUSÃO] GEDI - Disponibilizar consulta de cadastro de finalidades | G78: Micro | H78: Atividade | I78: Satélites | J78: Cancelado | K78: 46359 | M78: 78
A79: Financeiro | B79: (Financeiro) Satélites | C79: SPR-626 | E79: Testes QA | G79: Micro | H79: Atividade | I79: Satélites | J79: Cancelado | K79: 46360 | M79: 79
A80: Financeiro | B80: (Financeiro) Satélites | C80: SPR-626 | D80: SPR-1496 | E80: [FUSÃO] GEDI - Disponibilizar consulta de cadastro de naturezas | G80: Micro | H80: Atividade | I80: Satélites | J80: Finalizado | K80: 46364 | L80: 46290 | M80: 80
A81: Financeiro | B81: (Financeiro) Satélites | C81: SPR-626 | E81: Testes QA | G81: Micro | H81: Atividade | I81: Satélites | J81: Finalizado | K81: 46365 | L81: 46293 | M81: 81
A82: Financeiro | B82: (Financeiro) Satélites | C82: SPR-626 | D82: SPR-1497 | E82: [FUSÃO] GEDI - Disponibilizar consulta de cadastro de capex/projetos | G82: Micro | H82: Atividade | I82: Satélites | J82: Finalizado | K82: 46370 | L82: 46301 | M82: 82
A83: Financeiro | B83: (Financeiro) Satélites | C83: SPR-626 | E83: Testes QA | G83: Micro | H83: Atividade | I83: Satélites | J83: Finalizado | K83: 46371 | L83: 46301 | M83: 83
A84: Financeiro | B84: (Financeiro) Satélites | C84: SPR-626 | D84: SPR-1498 | E84: [FUSÃO] GEDI - Disponibilizar consulta de cadastro de totalizadora | G84: Micro | H84: Atividade | I84: Satélites | J84: Cancelado | K84: 46373 | M84: 84
A85: Financeiro | B85: (Financeiro) Satélites | C85: SPR-626 | E85: Testes QA | G85: Micro | H85: Atividade | I85: Satélites | J85: Cancelado | K85: 46374 | M85: 85
B86: (Financeiro) Satélites | C86: SPR-626 | D86: SPR-1527 | E86: [FUSÃO] GEDI - Títulos gerados diretamente no Protheus e precisam passar por alçada de aprovação no Gedi (retidos) | G86: Micro | H86: Atividade | I86: Satélites | J86: Não iniciado
B87: (Financeiro) Satélites | C87: SPR-626 | E87: Testes QA | G87: Micro | H87: Atividade | I87: Satélites | J87: Não iniciado
A88: Financeiro | B88: (Financeiro) Satélites | C88: SPR-626 | D88: SPR-1527 | E88: [FUSÃO] GEDI - Títulos gerados diretamente no Protheus e precisam passar por alçada de aprovação no Gedi (retidos) | G88: Micro | H88: Atividade | I88: Satélites | J88: Não iniciado
A89: Financeiro | B89: (Financeiro) Satélites | C89: SPR-626 | G89: Micro | H89: Atividade | I89: Satélites | J89: Não iniciado
A90: Financeiro | B90: (Financeiro) Satélites | C90: SPR-626 | D90: SPR-1528 | E90: [FUSÃO] GEDI - Solicitar motivo de exclusão de NF/título originado do Gedi (tabela de status) | G90: Micro | H90: Atividade | I90: Satélites | J90: Finalizado | K90: 46280 | L90: 46276
A91: Financeiro | B91: (Financeiro) Satélites | C91: SPR-626 | E91: Testes QA | G91: Micro | H91: Atividade | I91: Satélites | J91: Finalizado | K91: 46282 | L91: 46280
A92: Financeiro | B92: (Financeiro) Satélites | C92: SPR-626 | D92: SPR-1460 | E92: Aptus | G92: Macro | H92: Atividade | I92: Satélites | J92: Não iniciado | M92: 87
A93: Financeiro | B93: (Financeiro) Satélites | C93: SPR-626 | E93: Proposta Comercial | G93: Micro | H93: Atividade | I93: Satélites | J93: Em andamento | K93: 46252 | L93: 46276 | M93: 88
A94: Financeiro | B94: (Financeiro) Satélites | C94: SPR-626 | E94: Parametrização Portal, Desenvolvimento API e Testes Fornecedor | G94: Micro | H94: Atividade | I94: Satélites | J94: Em andamento | K94: 46343 | M94: 89
A95: Financeiro | B95: (Financeiro) Satélites | C95: SPR-626 | E95: Adequação fontes reembolso - Atividade Protheus | G95: Micro | H95: Atividade | I95: Satélites | J95: Em andamento | K95: 46358 | M95: 90
A96: Financeiro | B96: (Financeiro) Satélites | C96: SPR-626 | E96: Testes QA Protheus | G96: Micro | H96: Atividade | I96: Satélites | J96: Não iniciado | K96: 46366 | M96: 91
A97: Financeiro | B97: (Financeiro) Satélites | C97: SPR-626 | D97: SPR-1462 | E97: Nimbi | G97: Macro | H97: Atividade | I97: Satélites | J97: Não iniciado | M97: 92
A98: Financeiro | B98: (Financeiro) Satélites | C98: SPR-626 | E98: Proposta Comercial | G98: Micro | H98: Atividade | I98: Satélites | J98: Em andamento | K98: 46252 | L98: 46276 | M98: 93
A99: Financeiro | B99: (Financeiro) Satélites | C99: SPR-626 | E99: Configuração Portal empresa Petz e Cobasi | G99: Micro | H99: Atividade | I99: Satélites | J99: Não iniciado | M99: 94
A100: Financeiro | B100: (Financeiro) Satélites | C100: SPR-626 | E100: Integração Nimbi x Gedi | G100: Micro | H100: Atividade | I100: Satélites | J100: Não iniciado | M100: 95
...

Sheet Evolução Semanal Micro
B2: EVOLUÇÃO SEMANAL DAS ATIVIDADES MICRO
B3: Aderência e Satélites • Linha do tempo • Segunda a sexta-feira
B4: ATUALIZAÇÃO AUTOMÁTICA • Histórico por datas reais, exceto 05/10–09/10: 47% informado
B6: STATUS ATUAL • PAINEL | F6: ÚLTIMA SEMANA ENCERRADA | J6: PRÓXIMO FECHAMENTO
B7: ='Painel Executivo Micro'!K8 -> 0.54418605 | F7: =G44 -> 0.53488372 | J7: =D45 -> 46325
B8: ='Painel Executivo Micro'!K7&" finalizadas / "&L46&" ativas" -> 117 finalizadas / 215 ativas | F8: =B44&"/26 • reconstruído" -> 19/10 – 23/10/26 • reconstruído | J8: =B45&"/26"&IF(TODAY()<=D45," • em curso"," • encerrado") -> 26/10 – 30/10/26 • em curso
F9: Fechamento retrospectivo pelas datas reais | J9: =IF(TODAY()<=D45,"Ponto parcial • fechamento previsto em 30/10","Fechamento reconstruído pelas datas reais") -> Ponto parcial • fechamento previsto em 30/10
B11: TRAJETÓRIA DE CONCLUSÃO | FECHAMENTOS DE SEGUNDA A SEXTA
B12: ="● Linha verde: histórico por datas reais • 05/10–09/10: 47% informado • 26/10–30/10"&IF(TODAY()<=D45,": % atual do painel (parcial)",": por datas reais") -> ● Linha verde: histórico por datas reais • 05/10–09/10: 47% informado • 26/10–30/10: % atual do painel (parcial)
M16: SEMANA | N16: EVOLUÇÃO %
M17: =B34 -> 10/08 – 14/08 | N17: =G34 -> 0.13023256
M18: =B35 -> 17/08 – 21/08 | N18: =G35 -> 0.1627907
M19: =B36 -> 24/08 – 28/08 | N19: =G36 -> 0.20930233
M20: =B37 -> 31/08 – 04/09 | N20: =G37 -> 0.26511628
M21: =B38 -> 07/09 – 11/09 | N21: =G38 -> 0.30232558
M22: =B39 -> 14/09 – 18/09 | N22: =G39 -> 0.3627907
M23: =B40 -> 21/09 – 25/09 | N23: =G40 -> 0.42325581
M24: =B41 -> 28/09 – 02/10 | N24: =G41 -> 0.44186047
M25: =B42 -> 05/10 – 09/10 | N25: =G42 -> 0.47
M26: =B43 -> 12/10 – 16/10 | N26: =G43 -> 0.50697674
M27: =B44 -> 19/10 – 23/10 | N27: =G44 -> 0.53488372
M28: =B45 -> 26/10 – 30/10 | N28: =G45 -> 0.54418605
B30: DETALHE SEMANAL | DADOS QUE FORMAM A LINHA DO TEMPO
B31: PERÍODO | C31: SEGUNDA | D31: SEXTA | E31: NOVAS¹ | F31: ACUM.² | G31: % ACUM.³ | H31: VARIAÇÃO | I31: STATUS | J31: REGISTRO
B32: =TEXT(C32,"dd/mm")&" – "&TEXT(D32,"dd/mm") -> 27/07 – 31/07 | C32: =DATE(2026,7,27) -> 46230 | D32: =C32+4 -> 46234 | E32: =COUNTIFS(TabelaAtividadesMicro6[Tipo de registro],"Micro",TabelaAtividadesMicro6[Status],"Finalizado",TabelaAtividadesMicro6[Data fim real],">="&C32,TabelaAtividadesMicro6[Data fim real],"<="&D32) -> 6 | F32: =COUNTIFS(TabelaAtividadesMicro6[Tipo de registro],"Micro",TabelaAtividadesMicro6[Status],"Finalizado",TabelaAtividadesMicro6[Data fim real],">0",TabelaAtividadesMicro6[Data fim real],"<="&D32) -> 16 | G32: =IF($L$46=0,0,F32/$L$46) -> 0.074418605 | H32: =IF($L$46=0,0,100*E32/$L$46) -> 2.7906977 | I32: Reconstruído | J32: Não gravado
B33: =TEXT(C33,"dd/mm")&" – "&TEXT(D33,"dd/mm") -> 03/08 – 07/08 | C33: =C32+7 -> 46237 | D33: =C33+4 -> 46241 | E33: =COUNTIFS(TabelaAtividadesMicro6[Tipo de registro],"Micro",TabelaAtividadesMicro6[Status],"Finalizado",TabelaAtividadesMicro6[Data fim real],">"&D32,TabelaAtividadesMicro6[Data fim real],"<="&D33) -> 3 | F33: =F32+E33 -> 19 | G33: =IF($L$46=0,0,F33/$L$46) -> 0.088372093 | H33: =IF($L$46=0,0,100*E33/$L$46) -> 1.3953488 | I33: Reconstruído | J33: Não gravado
B34: =TEXT(C34,"dd/mm")&" – "&TEXT(D34,"dd/mm") -> 10/08 – 14/08 | C34: =C33+7 -> 46244 | D34: =C34+4 -> 46248 | E34: =COUNTIFS('Atividades Micro'!$G$2:$G$554,"Micro",'Atividades Micro'!$J$2:$J$554,"Finalizado",'Atividades Micro'!$L$2:$L$554,">"&D33,'Atividades Micro'!$L$2:$L$554,"<="&D34) -> 9 | F34: =F33+E34 -> 28 | G34: =IF($L$46=0,0,F34/$L$46) -> 0.13023256 | H34: =IF($L$46=0,0,100*E34/$L$46) -> 4.1860465 | I34: Reconstruído | J34: Não gravado
B35: =TEXT(C35,"dd/mm")&" – "&TEXT(D35,"dd/mm") -> 17/08 – 21/08 | C35: =C34+7 -> 46251 | D35: =C35+4 -> 46255 | E35: =COUNTIFS('Atividades Micro'!$G$2:$G$554,"Micro",'Atividades Micro'!$J$2:$J$554,"Finalizado",'Atividades Micro'!$L$2:$L$554,">"&D34,'Atividades Micro'!$L$2:$L$554,"<="&D35) -> 7 | F35: =F34+E35 -> 35 | G35: =IF($L$46=0,0,F35/$L$46) -> 0.1627907 | H35: =IF($L$46=0,0,100*E35/$L$46) -> 3.255814 | I35: Reconstruído | J35: Não gravado
B36: =TEXT(C36,"dd/mm")&" – "&TEXT(D36,"dd/mm") -> 24/08 – 28/08 | C36: =C35+7 -> 46258 | D36: =C36+4 -> 46262 | E36: =COUNTIFS('Atividades Micro'!$G$2:$G$554,"Micro",'Atividades Micro'!$J$2:$J$554,"Finalizado",'Atividades Micro'!$L$2:$L$554,">"&D35,'Atividades Micro'!$L$2:$L$554,"<="&D36) -> 10 | F36: =F35+E36 -> 45 | G36: =IF($L$46=0,0,F36/$L$46) -> 0.20930233 | H36: =IF($L$46=0,0,100*E36/$L$46) -> 4.6511628 | I36: Reconstruído | J36: Não gravado
B37: =TEXT(C37,"dd/mm")&" – "&TEXT(D37,"dd/mm") -> 31/08 – 04/09 | C37: =C36+7 -> 46265 | D37: =C37+4 -> 46269 | E37: =COUNTIFS('Atividades Micro'!$G$2:$G$554,"Micro",'Atividades Micro'!$J$2:$J$554,"Finalizado",'Atividades Micro'!$L$2:$L$554,">"&D36,'Atividades Micro'!$L$2:$L$554,"<="&D37) -> 12 | F37: =F36+E37 -> 57 | G37: =IF($L$46=0,0,F37/$L$46) -> 0.26511628 | H37: =IF($L$46=0,0,100*E37/$L$46) -> 5.5813953 | I37: Reconstruído | J37: Não gravado
B38: =TEXT(C38,"dd/mm")&" – "&TEXT(D38,"dd/mm") -> 07/09 – 11/09 | C38: =C37+7 -> 46272 | D38: =C38+4 -> 46276 | E38: =COUNTIFS('Atividades Micro'!$G$2:$G$554,"Micro",'Atividades Micro'!$J$2:$J$554,"Finalizado",'Atividades Micro'!$L$2:$L$554,">"&D37,'Atividades Micro'!$L$2:$L$554,"<="&D38) -> 8 | F38: =F37+E38 -> 65 | G38: =IF($L$46=0,0,F38/$L$46) -> 0.30232558 | H38: =IF($L$46=0,0,100*E38/$L$46) -> 3.7209302 | I38: Reconstruído | J38: Não gravado
B39: =TEXT(C39,"dd/mm")&" – "&TEXT(D39,"dd/mm") -> 14/09 – 18/09 | C39: =C38+7 -> 46279 | D39: =C39+4 -> 46283 | E39: =COUNTIFS('Atividades Micro'!$G$2:$G$554,"Micro",'Atividades Micro'!$J$2:$J$554,"Finalizado",'Atividades Micro'!$L$2:$L$554,">"&D38,'Atividades Micro'!$L$2:$L$554,"<="&D39) -> 13 | F39: =F38+E39 -> 78 | G39: =IF($L$46=0,0,F39/$L$46) -> 0.3627907 | H39: =IF($L$46=0,0,100*E39/$L$46) -> 6.0465116 | I39: Reconstruído | J39: Não gravado
B40: =TEXT(C40,"dd/mm")&" – "&TEXT(D40,"dd/mm") -> 21/09 – 25/09 | C40: =C39+7 -> 46286 | D40: =C40+4 -> 46290 | E40: =COUNTIFS('Atividades Micro'!$G$2:$G$554,"Micro",'Atividades Micro'!$J$2:$J$554,"Finalizado",'Atividades Micro'!$L$2:$L$554,">"&D39,'Atividades Micro'!$L$2:$L$554,"<="&D40) -> 13 | F40: =F39+E40 -> 91 | G40: =IF($L$46=0,0,F40/$L$46) -> 0.42325581 | H40: =IF($L$46=0,0,100*E40/$L$46) -> 6.0465116 | I40: Reconstruído | J40: Não gravado
B41: =TEXT(C41,"dd/mm")&" – "&TEXT(D41,"dd/mm") -> 28/09 – 02/10 | C41: =C40+7 -> 46293 | D41: =C41+4 -> 46297 | E41: =COUNTIFS('Atividades Micro'!$G$2:$G$554,"Micro",'Atividades Micro'!$J$2:$J$554,"Finalizado",'Atividades Micro'!$L$2:$L$554,">"&D40,'Atividades Micro'!$L$2:$L$554,"<="&D41) -> 4 | F41: =F40+E41 -> 95 | G41: =IF($L$46=0,0,F41/$L$46) -> 0.44186047 | H41: =IF($L$46=0,0,100*E41/$L$46) -> 1.8604651 | I41: Reconstruído | J41: Não gravado
B42: =TEXT(C42,"dd/mm")&" – "&TEXT(D42,"dd/mm") -> 05/10 – 09/10 | C42: =C41+7 -> 46300 | D42: =C42+4 -> 46304 | E42: =COUNTIFS('Atividades Micro'!$G$2:$G$554,"Micro",'Atividades Micro'!$J$2:$J$554,"Finalizado",'Atividades Micro'!$L$2:$L$554,">"&D41,'Atividades Micro'!$L$2:$L$554,"<="&D42) -> 5 | F42: =F41+E42 -> 100 | G42: 0.47 | H42: =100*(G42-G41) -> 2.8139535 | I42: Informado | J42: Usuário: 47%
B43: =TEXT(C43,"dd/mm")&" – "&TEXT(D43,"dd/mm") -> 12/10 – 16/10 | C43: =C42+7 -> 46307 | D43: =C43+4 -> 46311 | E43: =COUNTIFS('Atividades Micro'!$G$2:$G$554,"Micro",'Atividades Micro'!$J$2:$J$554,"Finalizado",'Atividades Micro'!$L$2:$L$554,">"&D42,'Atividades Micro'!$L$2:$L$554,"<="&MIN(TODAY(),D43)) -> 9 | F43: =F42+E43 -> 109 | G43: =IF($L$46=0,0,F43/$L$46) -> 0.50697674 | H43: =100*(G43-G42) -> 3.6976744 | I43: Reconstruído | J43: Fechamento por datas reais; não informado
B44: =TEXT(C44,"dd/mm")&" – "&TEXT(D44,"dd/mm") -> 19/10 – 23/10 | C44: =C43+7 -> 46314 | D44: =C44+4 -> 46318 | E44: =COUNTIFS('Atividades Micro'!$G$2:$G$554,"Micro",'Atividades Micro'!$J$2:$J$554,"Finalizado",'Atividades Micro'!$L$2:$L$554,">"&D43,'Atividades Micro'!$L$2:$L$554,"<="&MIN(TODAY(),D44)) -> 6 | F44: =F43+E44 -> 115 | G44: =IF($L$46=0,0,F44/$L$46) -> 0.53488372 | H44: =100*(G44-G43) -> 2.7906977 | I44: Reconstruído | J44: Fechamento por datas reais; não informado
B45: =TEXT(C45,"dd/mm")&" – "&TEXT(D45,"dd/mm") -> 26/10 – 30/10 | C45: =C44+7 -> 46321 | D45: =C45+4 -> 46325 | E45: =COUNTIFS('Atividades Micro'!$G$2:$G$554,"Micro",'Atividades Micro'!$J$2:$J$554,"Finalizado",'Atividades Micro'!$L$2:$L$554,">"&D44,'Atividades Micro'!$L$2:$L$554,"<="&MIN(TODAY(),D45)) -> 0 | F45: =F44+E45 -> 115 | G45: =IF(TODAY()<=D45,B7,IF($L$46=0,0,F45/$L$46)) -> 0.54418605 | H45: =100*(G45-G44) -> 0.93023256 | I45: =IF(TODAY()<=D45,"Parcial • em andamento","Reconstruído") -> Parcial • em andamento | J45: =IF(TODAY()<=D45,"Status atual até "&TEXT(MIN(TODAY(),D45),"dd/mm")&"; não fechada","Fechamento por datas reais; não informado") -> Status atual até 26/10; não fechada
B46: COMO LER ESTA PRÉVIA | K46: BASE ATIVA HOJE | L46: =COUNTIFS(TabelaAtividadesMicro6[Tipo de registro],"Micro",TabelaAtividadesMicro6[Status],"<>Cancelado") -> 215
B47: ¹ Novas: finalizações com Data fim real, por fechamento de sexta; eventuais finais de semana entram no fechamento seguinte. | K47: FINALIZADAS HOJE | L47: ='Painel Executivo Micro'!K7 -> 117
B48: ² Acumulado: usa registros hoje marcados Finalizado e suas datas reais; registros sem data não entram na curva. | K48: SEM DATA FIM | L48: =COUNTIFS(TabelaAtividadesMicro6[Tipo de registro],"Micro",TabelaAtividadesMicro6[Status],"Finalizado",TabelaAtividadesMicro6[Data fim real],"") -> 2
B49: ="³ Histórico = finalizadas com data real ÷ base ativa atual; 05/10–09/10: 47% informado; 26/10–30/10: "&IF(TODAY()<=D45,"percentual atual do painel (inclui finalizadas sem data; ponto parcial).","reconstruído por datas reais.") -> ³ Histórico = finalizadas com data real ÷ base ativa atual; 05/10–09/10: 47% informado; 26/10–30/10: percentual atual do painel (inclui finalizadas sem data; ponto parcial). | K49: COM DATA FIM | L49: =L47-L48 -> 115
B50: ="A semana 19/10–23/10 foi reconstruída pelas datas reais; 26/10–30/10 "&IF(TODAY()<=D45,"mostra o percentual atual do painel como ponto parcial, não como fechamento.","mostra o fechamento reconstruído pelas datas reais.") -> A semana 19/10–23/10 foi reconstruída pelas datas reais; 26/10–30/10 mostra o percentual atual do painel como ponto parcial, não como fechamento.

Sheet CRs Atividades Micro
A1: Frente | B1: Atividade | D1: Rótulos de Linha | E1: Contagem de Atividade
A2: Financeiro | B2: CR - Melhorias a serem definidas | D2: CD | E2: 3
A3: Fiscal | B3: CR - Melhorias a serem definidas (SPR-1092) | D3: Financeiro | E3: 1
A4: CD | B4: ID-106 |Ajustes CR - pós entrega | D4: Fiscal | E4: 1
A5: CD | B5: ID-102 | Ajustes CR - pós entrega | D5: Total Geral | E5: 5
A6: CD | B6: ID-91 |Ajustes CR - pós entrega

Sheet Cálculos (apoio)
A1: CÁLCULOS DE APOIO | NÃO EDITAR
A2: (Migração ERP) Infraestrutura | B2: (Migração ERP) Infraestrutura | C2: (Migração ERP) Dados Mestres | D2: (Migração ERP) Dados Mestres | E2: (Migração ERP) Refatoração / Fontes | F2: (Migração ERP) Refatoração / Fontes | G2: (Migração ERP) Satélites | H2: (Migração ERP) Satélites | I2: Financeiro | J2: Financeiro | K2: (Financeiro) Aderência | L2: (Financeiro) Aderência | M2: (Financeiro) Satélites | N2: (Financeiro) Satélites | O2: Fiscal | P2: Fiscal | Q2: (Fiscal) Satélites | R2: (Fiscal) Satélites | S2: Contábil | T2: Contábil | U2: (Contábil) Aderência | V2: (Contábil) Aderência | W2: (Contábil) Satélites | X2: (Contábil) Satélites | Y2: Supply | Z2: Supply | AA2: (Supply) Aderência | AB2: (Supply) Aderência | AC2: (Supply) Satélites | AD2: (Supply) Satélites | AE2: CD | AF2: CD | AG2: (CD) Aderência | AH2: (CD) Aderência | AI2: (CD) Satélites | AJ2: (CD) Satélites | AK2: Comercial | AL2: Comercial | AM2: (Comercial) Aderência | AN2: (Comercial) Aderência | AO2: (Comercial) Satélites | AP2: (Comercial) Satélites | AQ2: TOTVS RM | AR2: TOTVS RM | AS2: (TOTVS RM) Aderência | AT2: (TOTVS RM) Aderência | AU2: Zanthus | AV2: Zanthus | AW2: (Zanthus) Aderência | AX2: (Zanthus) Aderência | AY2: Operações | AZ2: Operações | BA2: (Operações) Satélites | BB2: (Operações) Satélites | BC2: (Migração ERP) Infraestrutura | BD2: (Migração ERP) Dados Mestres | BE2: (Migração ERP) Refatoração / Fontes | BF2: (Migração ERP) Satélites | BG2: Financeiro | BH2: (Financeiro) Aderência | BI2: (Financeiro) Satélites | BJ2: Fiscal | BK2: (Fiscal) Satélites | BL2: Contábil | BM2: (Contábil) Aderência | BN2: (Contábil) Satélites | BO2: Supply | BP2: (Supply) Aderência | BQ2: (Supply) Satélites | BR2: CD | BS2: (CD) Aderência | BT2: (CD) Satélites | BU2: Comercial | BV2: (Comercial) Aderência | BW2: (Comercial) Satélites | BX2: TOTVS RM | BY2: (TOTVS RM) Aderência | BZ2: Zanthus | CA2: (Zanthus) Aderência | CB2: Operações | CC2: (Operações) Satélites | CD2: (Financeiro) Aderência | CE2: (Financeiro) Satélites | CF2: (Fiscal) Satélites | CG2: (Contábil) Aderência | CH2: (Contábil) Satélites | CI2: (Supply) Aderência | CJ2: (Supply) Satélites | CK2: (CD) Aderência | CL2: (CD) Satélites | CM2: (Comercial) Aderência | CN2: (Comercial) Satélites | CO2: (Operações) Satélites
A3: Data Planejada | B3: Data fim real | C3: Data Planejada | D3: Data fim real | E3: Data Planejada | F3: Data fim real | G3: Data Planejada | H3: Data fim real | I3: Data Planejada | J3: Data fim real | K3: Data Planejada | L3: Data fim real | M3: Data Planejada | N3: Data fim real | O3: Data Planejada | P3: Data fim real | Q3: Data Planejada | R3: Data fim real | S3: Data Planejada | T3: Data fim real | U3: Data Planejada | V3: Data fim real | W3: Data Planejada | X3: Data fim real | Y3: Data Planejada | Z3: Data fim real | AA3: Data Planejada | AB3: Data fim real | AC3: Data Planejada | AD3: Data fim real | AE3: Data Planejada | AF3: Data fim real | AG3: Data Planejada | AH3: Data fim real | AI3: Data Planejada | AJ3: Data fim real | AK3: Data Planejada | AL3: Data fim real | AM3: Data Planejada | AN3: Data fim real | AO3: Data Planejada | AP3: Data fim real | AQ3: Data Planejada | AR3: Data fim real | AS3: Data Planejada | AT3: Data fim real | AU3: Data Planejada | AV3: Data fim real | AW3: Data Planejada | AX3: Data fim real | AY3: Data Planejada | AZ3: Data fim real | BA3: Data Planejada | BB3: Data fim real | BC3: Data Planejada Macro | BD3: Data Planejada Macro | BE3: Data Planejada Macro | BF3: Data Planejada Macro | BG3: Data Planejada Macro | BH3: Data Planejada Macro | BI3: Data Planejada Macro | BJ3: Data Planejada Macro | BK3: Data Planejada Macro | BL3: Data Planejada Macro | BM3: Data Planejada Macro | BN3: Data Planejada Macro | BO3: Data Planejada Macro | BP3: Data Planejada Macro | BQ3: Data Planejada Macro | BR3: Data Planejada Macro | BS3: Data Planejada Macro | BT3: Data Planejada Macro | BU3: Data Planejada Macro | BV3: Data Planejada Macro | BW3: Data Planejada Macro | BX3: Data Planejada Macro | BY3: Data Planejada Macro | BZ3: Data Planejada Macro | CA3: Data Planejada Macro | CB3: Data Planejada Macro | CC3: Data Planejada Macro | CD3: Data Planejada Micro | CE3: Data Planejada Micro | CF3: Data Planejada Micro | CG3: Data Planejada Micro | CH3: Data Planejada Micro | CI3: Data Planejada Micro | CJ3: Data Planejada Micro | CK3: Data Planejada Micro | CL3: Data Planejada Micro | CM3: Data Planejada Micro | CN3: Data Planejada Micro | CO3: Data Planejada Micro
A4: =IF(AND('Atividades Micro'!$A2=A$2,'Atividades Micro'!$K2<>""),'Atividades Micro'!$K2,"") -> 46196 | B4: =IF(AND('Atividades Micro'!$A2=B$2,'Atividades Micro'!$L2<>""),'Atividades Micro'!$L2,"") | C4: =IF(AND('Atividades Micro'!$A2=C$2,'Atividades Micro'!$K2<>""),'Atividades Micro'!$K2,"") | D4: =IF(AND('Atividades Micro'!$A2=D$2,'Atividades Micro'!$L2<>""),'Atividades Micro'!$L2,"") | E4: =IF(AND('Atividades Micro'!$A2=E$2,'Atividades Micro'!$K2<>""),'Atividades Micro'!$K2,"") | F4: =IF(AND('Atividades Micro'!$A2=F$2,'Atividades Micro'!$L2<>""),'Atividades Micro'!$L2,"") | G4: =IF(AND('Atividades Micro'!$A2=G$2,'Atividades Micro'!$K2<>""),'Atividades Micro'!$K2,"") | H4: =IF(AND('Atividades Micro'!$A2=H$2,'Atividades Micro'!$L2<>""),'Atividades Micro'!$L2,"") | I4: =IF(AND('Atividades Micro'!$A2=I$2,'Atividades Micro'!$K2<>""),'Atividades Micro'!$K2,"") | J4: =IF(AND('Atividades Micro'!$A2=J$2,'Atividades Micro'!$L2<>""),'Atividades Micro'!$L2,"") | K4: =IF(AND('Atividades Micro'!$B2=K$2,'Atividades Micro'!$K2<>""),'Atividades Micro'!$K2,"") | L4: =IF(AND('Atividades Micro'!$B2=L$2,'Atividades Micro'!$L2<>""),'Atividades Micro'!$L2,"") | M4: =IF(AND('Atividades Micro'!$B2=M$2,'Atividades Micro'!$K2<>""),'Atividades Micro'!$K2,"") | N4: =IF(AND('Atividades Micro'!$B2=N$2,'Atividades Micro'!$L2<>""),'Atividades Micro'!$L2,"") | O4: =IF(AND('Atividades Micro'!$A2=O$2,'Atividades Micro'!$K2<>""),'Atividades Micro'!$K2,"") | P4: =IF(AND('Atividades Micro'!$A2=P$2,'Atividades Micro'!$L2<>""),'Atividades Micro'!$L2,"") | Q4: =IF(AND('Atividades Micro'!$B2=Q$2,'Atividades Micro'!$K2<>""),'Atividades Micro'!$K2,"") | R4: =IF(AND('Atividades Micro'!$B2=R$2,'Atividades Micro'!$L2<>""),'Atividades Micro'!$L2,"") | S4: =IF(AND('Atividades Micro'!$A2=S$2,'Atividades Micro'!$K2<>""),'Atividades Micro'!$K2,"") | T4: =IF(AND('Atividades Micro'!$A2=T$2,'Atividades Micro'!$L2<>""),'Atividades Micro'!$L2,"") | U4: =IF(AND('Atividades Micro'!$B2=U$2,'Atividades Micro'!$K2<>""),'Atividades Micro'!$K2,"") | V4: =IF(AND('Atividades Micro'!$B2=V$2,'Atividades Micro'!$L2<>""),'Atividades Micro'!$L2,"") | W4: =IF(AND('Atividades Micro'!$B2=W$2,'Atividades Micro'!$K2<>""),'Atividades Micro'!$K2,"") | X4: =IF(AND('Atividades Micro'!$B2=X$2,'Atividades Micro'!$L2<>""),'Atividades Micro'!$L2,"") | Y4: =IF(AND('Atividades Micro'!$A2=Y$2,'Atividades Micro'!$K2<>""),'Atividades Micro'!$K2,"") | Z4: =IF(AND('Atividades Micro'!$A2=Z$2,'Atividades Micro'!$L2<>""),'Atividades Micro'!$L2,"") | AA4: =IF(AND('Atividades Micro'!$B2=AA$2,'Atividades Micro'!$K2<>""),'Atividades Micro'!$K2,"") | AB4: =IF(AND('Atividades Micro'!$B2=AB$2,'Atividades Micro'!$L2<>""),'Atividades Micro'!$L2,"") | AC4: =IF(AND('Atividades Micro'!$B2=AC$2,'Atividades Micro'!$K2<>""),'Atividades Micro'!$K2,"") | AD4: =IF(AND('Atividades Micro'!$B2=AD$2,'Atividades Micro'!$L2<>""),'Atividades Micro'!$L2,"") | AE4: =IF(AND('Atividades Micro'!$A2=AE$2,'Atividades Micro'!$K2<>""),'Atividades Micro'!$K2,"") | AF4: =IF(AND('Atividades Micro'!$A2=AF$2,'Atividades Micro'!$L2<>""),'Atividades Micro'!$L2,"") | AG4: =IF(AND('Atividades Micro'!$B2=AG$2,'Atividades Micro'!$K2<>""),'Atividades Micro'!$K2,"") | AH4: =IF(AND('Atividades Micro'!$B2=AH$2,'Atividades Micro'!$L2<>""),'Atividades Micro'!$L2,"") | AI4: =IF(AND('Atividades Micro'!$B2=AI$2,'Atividades Micro'!$K2<>""),'Atividades Micro'!$K2,"") | AJ4: =IF(AND('Atividades Micro'!$B2=AJ$2,'Atividades Micro'!$L2<>""),'Atividades Micro'!$L2,"") | AK4: =IF(AND('Atividades Micro'!$A2=AK$2,'Atividades Micro'!$K2<>""),'Atividades Micro'!$K2,"") | AL4: =IF(AND('Atividades Micro'!$A2=AL$2,'Atividades Micro'!$L2<>""),'Atividades Micro'!$L2,"") | AM4: =IF(AND('Atividades Micro'!$B2=AM$2,'Atividades Micro'!$K2<>""),'Atividades Micro'!$K2,"") | AN4: =IF(AND('Atividades Micro'!$B2=AN$2,'Atividades Micro'!$L2<>""),'Atividades Micro'!$L2,"") | AO4: =IF(AND('Atividades Micro'!$B2=AO$2,'Atividades Micro'!$K2<>""),'Atividades Micro'!$K2,"") | AP4: =IF(AND('Atividades Micro'!$B2=AP$2,'Atividades Micro'!$L2<>""),'Atividades Micro'!$L2,"") | AQ4: =IF(AND('Atividades Micro'!$A2=AQ$2,'Atividades Micro'!$K2<>""),'Atividades Micro'!$K2,"") | AR4: =IF(AND('Atividades Micro'!$A2=AR$2,'Atividades Micro'!$L2<>""),'Atividades Micro'!$L2,"") | AS4: =IF(AND('Atividades Micro'!$B2=AS$2,'Atividades Micro'!$K2<>""),'Atividades Micro'!$K2,"") | AT4: =IF(AND('Atividades Micro'!$B2=AT$2,'Atividades Micro'!$L2<>""),'Atividades Micro'!$L2,"") | AU4: =IF(AND('Atividades Micro'!$A2=AU$2,'Atividades Micro'!$K2<>""),'Atividades Micro'!$K2,"") | AV4: =IF(AND('Atividades Micro'!$A2=AV$2,'Atividades Micro'!$L2<>""),'Atividades Micro'!$L2,"") | AW4: =IF(AND('Atividades Micro'!$B2=AW$2,'Atividades Micro'!$K2<>""),'Atividades Micro'!$K2,"") | AX4: =IF(AND('Atividades Micro'!$B2=AX$2,'Atividades Micro'!$L2<>""),'Atividades Micro'!$L2,"") | AY4: =IF(AND('Atividades Micro'!$A2=AY$2,'Atividades Micro'!$K2<>""),'Atividades Micro'!$K2,"") | AZ4: =IF(AND('Atividades Micro'!$A2=AZ$2,'Atividades Micro'!$L2<>""),'Atividades Micro'!$L2,"") | BA4: =IF(AND('Atividades Micro'!$B2=BA$2,'Atividades Micro'!$K2<>""),'Atividades Micro'!$K2,"") | BB4: =IF(AND('Atividades Micro'!$B2=BB$2,'Atividades Micro'!$L2<>""),'Atividades Micro'!$L2,"") | BC4: =IF(AND('Atividades Micro'!$B2=BC$2,'Atividades Micro'!$G2="Macro",'Atividades Micro'!$K2<>""),'Atividades Micro'!$K2,"") | BD4: =IF(AND('Atividades Micro'!$B2=BD$2,'Atividades Micro'!$G2="Macro",'Atividades Micro'!$K2<>""),'Atividades Micro'!$K2,"") | BE4: =IF(AND('Atividades Micro'!$B2=BE$2,'Atividades Micro'!$G2="Macro",'Atividades Micro'!$K2<>""),'Atividades Micro'!$K2,"") | BF4: =IF(AND('Atividades Micro'!$B2=BF$2,'Atividades Micro'!$G2="Macro",'Atividades Micro'!$K2<>""),'Atividades Micro'!$K2,"") | BG4: =IF(AND('Atividades Micro'!$B2=BG$2,'Atividades Micro'!$G2="Macro",'Atividades Micro'!$K2<>""),'Atividades Micro'!$K2,"") | BH4: =IF(AND('Atividades Micro'!$B2=BH$2,'Atividades Micro'!$G2="Macro",'Atividades Micro'!$K2<>""),'Atividades Micro'!$K2,"") | BI4: =IF(AND('Atividades Micro'!$B2=BI$2,'Atividades Micro'!$G2="Macro",'Atividades Micro'!$K2<>""),'Atividades Micro'!$K2,"") | BJ4: =IF(AND('Atividades Micro'!$B2=BJ$2,'Atividades Micro'!$G2="Macro",'Atividades Micro'!$K2<>""),'Atividades Micro'!$K2,"") | ... CC4: =IF(AND('Atividades Micro'!$B2=CC$2,'Atividades Micro'!$G2="Macro",'Atividades Micro'!$K2<>""),'Atividades Micro'!$K2,"") | CD4: =IF(AND('Atividades Micro'!$B2=CD$2,'Atividades Micro'!$G2="Micro",'Atividades Micro'!$K2<>""),'Atividades Micro'!$K2,"") | CE4: =IF(AND('Atividades Micro'!$B2=CE$2,'Atividades Micro'!$G2="Micro",'Atividades Micro'!$K2<>""),'Atividades Micro'!$K2,"") | CF4: =IF(AND('Atividades Micro'!$B2=CF$2,'Atividades Micro'!$G2="Micro",'Atividades Micro'!$K2<>""),'Atividades Micro'!$K2,"") | CG4: =IF(AND('Atividades Micro'!$B2=CG$2,'Atividades Micro'!$G2="Micro",'Atividades Micro'!$K2<>""),'Atividades Micro'!$K2,"") | CH4: =IF(AND('Atividades Micro'!$B2=CH$2,'Atividades Micro'!$G2="Micro",'Atividades Micro'!$K2<>""),'Atividades Micro'!$K2,"") | CI4: =IF(AND('Atividades Micro'!$B2=CI$2,'Atividades Micro'!$G2="Micro",'Atividades Micro'!$K2<>""),'Atividades Micro'!$K2,"") | CJ4: =IF(AND('Atividades Micro'!$B2=CJ$2,'Atividades Micro'!$G2="Micro",'Atividades Micro'!$K2<>""),'Atividades Micro'!$K2,"") | CK4: =IF(AND('Atividades Micro'!$B2=CK$2,'Atividades Micro'!$G2="Micro",'Atividades Micro'!$K2<>""),'Atividades Micro'!$K2,"") | ... CO4: =IF(AND('Atividades Micro'!$B2=CO$2,'Atividades Micro'!$G2="Micro",'Atividades Micro'!$K2<>""),'Atividades Micro'!$K2,"")
A5: =IF(AND('Atividades Micro'!$A3=A$2,'Atividades Micro'!$K3<>""),'Atividades Micro'!$K3,"") -> 46199 | B5: =IF(AND('Atividades Micro'!$A3=B$2,'Atividades Micro'!$L3<>""),'Atividades Micro'!$L3,"") | C5: =IF(AND('Atividades Micro'!$A3=C$2,'Atividades Micro'!$K3<>""),'Atividades Micro'!$K3,"") | D5: =IF(AND('Atividades Micro'!$A3=D$2,'Atividades Micro'!$L3<>""),'Atividades Micro'!$L3,"") | E5: =IF(AND('Atividades Micro'!$A3=E$2,'Atividades Micro'!$K3<>""),'Atividades Micro'!$K3,"") | F5: =IF(AND('Atividades Micro'!$A3=F$2,'Atividades Micro'!$L3<>""),'Atividades Micro'!$L3,"") | G5: =IF(AND('Atividades Micro'!$A3=G$2,'Atividades Micro'!$K3<>""),'Atividades Micro'!$K3,"") | H5: =IF(AND('Atividades Micro'!$A3=H$2,'Atividades Micro'!$L3<>""),'Atividades Micro'!$L3,"") | I5: =IF(AND('Atividades Micro'!$A3=I$2,'Atividades Micro'!$K3<>""),'Atividades Micro'!$K3,"") | J5: =IF(AND('Atividades Micro'!$A3=J$2,'Atividades Micro'!$L3<>""),'Atividades Micro'!$L3,"") | K5: =IF(AND('Atividades Micro'!$B3=K$2,'Atividades Micro'!$K3<>""),'Atividades Micro'!$K3,"") | L5: =IF(AND('Atividades Micro'!$B3=L$2,'Atividades Micro'!$L3<>""),'Atividades Micro'!$L3,"") | M5: =IF(AND('Atividades Micro'!$B3=M$2,'Atividades Micro'!$K3<>""),'Atividades Micro'!$K3,"") | N5: =IF(AND('Atividades Micro'!$B3=N$2,'Atividades Micro'!$L3<>""),'Atividades Micro'!$L3,"") | O5: =IF(AND('Atividades Micro'!$A3=O$2,'Atividades Micro'!$K3<>""),'Atividades Micro'!$K3,"") | P5: =IF(AND('Atividades Micro'!$A3=P$2,'Atividades Micro'!$L3<>""),'Atividades Micro'!$L3,"") | Q5: =IF(AND('Atividades Micro'!$B3=Q$2,'Atividades Micro'!$K3<>""),'Atividades Micro'!$K3,"") | R5: =IF(AND('Atividades Micro'!$B3=R$2,'Atividades Micro'!$L3<>""),'Atividades Micro'!$L3,"") | S5: =IF(AND('Atividades Micro'!$A3=S$2,'Atividades Micro'!$K3<>""),'Atividades Micro'!$K3,"") | T5: =IF(AND('Atividades Micro'!$A3=T$2,'Atividades Micro'!$L3<>""),'Atividades Micro'!$L3,"") | U5: =IF(AND('Atividades Micro'!$B3=U$2,'Atividades Micro'!$K3<>""),'Atividades Micro'!$K3,"") | V5: =IF(AND('Atividades Micro'!$B3=V$2,'Atividades Micro'!$L3<>""),'Atividades Micro'!$L3,"") | W5: =IF(AND('Atividades Micro'!$B3=W$2,'Atividades Micro'!$K3<>""),'Atividades Micro'!$K3,"") | X5: =IF(AND('Atividades Micro'!$B3=X$2,'Atividades Micro'!$L3<>""),'Atividades Micro'!$L3,"") | Y5: =IF(AND('Atividades Micro'!$A3=Y$2,'Atividades Micro'!$K3<>""),'Atividades Micro'!$K3,"") | Z5: =IF(AND('Atividades Micro'!$A3=Z$2,'Atividades Micro'!$L3<>""),'Atividades Micro'!$L3,"") | AA5: =IF(AND('Atividades Micro'!$B3=AA$2,'Atividades Micro'!$K3<>""),'Atividades Micro'!$K3,"") | AB5: =IF(AND('Atividades Micro'!$B3=AB$2,'Atividades Micro'!$L3<>""),'Atividades Micro'!$L3,"") | AC5: =IF(AND('Atividades Micro'!$B3=AC$2,'Atividades Micro'!$K3<>""),'Atividades Micro'!$K3,"") | AD5: =IF(AND('Atividades Micro'!$B3=AD$2,'Atividades Micro'!$L3<>""),'Atividades Micro'!$L3,"") | AE5: =IF(AND('Atividades Micro'!$A3=AE$2,'Atividades Micro'!$K3<>""),'Atividades Micro'!$K3,"") | AF5: =IF(AND('Atividades Micro'!$A3=AF$2,'Atividades Micro'!$L3<>""),'Atividades Micro'!$L3,"") | AG5: =IF(AND('Atividades Micro'!$B3=AG$2,'Atividades Micro'!$K3<>""),'Atividades Micro'!$K3,"") | AH5: =IF(AND('Atividades Micro'!$B3=AH$2,'Atividades Micro'!$L3<>""),'Atividades Micro'!$L3,"") | AI5: =IF(AND('Atividades Micro'!$B3=AI$2,'Atividades Micro'!$K3<>""),'Atividades Micro'!$K3,"") | AJ5: =IF(AND('Atividades Micro'!$B3=AJ$2,'Atividades Micro'!$L3<>""),'Atividades Micro'!$L3,"") | AK5: =IF(AND('Atividades Micro'!$A3=AK$2,'Atividades Micro'!$K3<>""),'Atividades Micro'!$K3,"") | AL5: =IF(AND('Atividades Micro'!$A3=AL$2,'Atividades Micro'!$L3<>""),'Atividades Micro'!$L3,"") | AM5: =IF(AND('Atividades Micro'!$B3=AM$2,'Atividades Micro'!$K3<>""),'Atividades Micro'!$K3,"") | AN5: =IF(AND('Atividades Micro'!$B3=AN$2,'Atividades Micro'!$L3<>""),'Atividades Micro'!$L3,"") | AO5: =IF(AND('Atividades Micro'!$B3=AO$2,'Atividades Micro'!$K3<>""),'Atividades Micro'!$K3,"") | AP5: =IF(AND('Atividades Micro'!$B3=AP$2,'Atividades Micro'!$L3<>""),'Atividades Micro'!$L3,"") | AQ5: =IF(AND('Atividades Micro'!$A3=AQ$2,'Atividades Micro'!$K3<>""),'Atividades Micro'!$K3,"") | AR5: =IF(AND('Atividades Micro'!$A3=AR$2,'Atividades Micro'!$L3<>""),'Atividades Micro'!$L3,"") | AS5: =IF(AND('Atividades Micro'!$B3=AS$2,'Atividades Micro'!$K3<>""),'Atividades Micro'!$K3,"") | AT5: =IF(AND('Atividades Micro'!$B3=AT$2,'Atividades Micro'!$L3<>""),'Atividades Micro'!$L3,"") | AU5: =IF(AND('Atividades Micro'!$A3=AU$2,'Atividades Micro'!$K3<>""),'Atividades Micro'!$K3,"") | AV5: =IF(AND('Atividades Micro'!$A3=AV$2,'Atividades Micro'!$L3<>""),'Atividades Micro'!$L3,"") | AW5: =IF(AND('Atividades Micro'!$B3=AW$2,'Atividades Micro'!$K3<>""),'Atividades Micro'!$K3,"") | AX5: =IF(AND('Atividades Micro'!$B3=AX$2,'Atividades Micro'!$L3<>""),'Atividades Micro'!$L3,"") | AY5: =IF(AND('Atividades Micro'!$A3=AY$2,'Atividades Micro'!$K3<>""),'Atividades Micro'!$K3,"") | AZ5: =IF(AND('Atividades Micro'!$A3=AZ$2,'Atividades Micro'!$L3<>""),'Atividades Micro'!$L3,"") | BA5: =IF(AND('Atividades Micro'!$B3=BA$2,'Atividades Micro'!$K3<>""),'Atividades Micro'!$K3,"") | BB5: =IF(AND('Atividades Micro'!$B3=BB$2,'Atividades Micro'!$L3<>""),'Atividades Micro'!$L3,"") | BC5: =IF(AND('Atividades Micro'!$B3=BC$2,'Atividades Micro'!$G3="Macro",'Atividades Micro'!$K3<>""),'Atividades Micro'!$K3,"") | BD5: =IF(AND('Atividades Micro'!$B3=BD$2,'Atividades Micro'!$G3="Macro",'Atividades Micro'!$K3<>""),'Atividades Micro'!$K3,"") | BE5: =IF(AND('Atividades Micro'!$B3=BE$2,'Atividades Micro'!$G3="Macro",'Atividades Micro'!$K3<>""),'Atividades Micro'!$K3,"") | BF5: =IF(AND('Atividades Micro'!$B3=BF$2,'Atividades Micro'!$G3="Macro",'Atividades Micro'!$K3<>""),'Atividades Micro'!$K3,"") | BG5: =IF(AND('Atividades Micro'!$B3=BG$2,'Atividades Micro'!$G3="Macro",'Atividades Micro'!$K3<>""),'Atividades Micro'!$K3,"") | BH5: =IF(AND('Atividades Micro'!$B3=BH$2,'Atividades Micro'!$G3="Macro",'Atividades Micro'!$K3<>""),'Atividades Micro'!$K3,"") | BI5: =IF(AND('Atividades Micro'!$B3=BI$2,'Atividades Micro'!$G3="Macro",'Atividades Micro'!$K3<>""),'Atividades Micro'!$K3,"") | BJ5: =IF(AND('Atividades Micro'!$B3=BJ$2,'Atividades Micro'!$G3="Macro",'Atividades Micro'!$K3<>""),'Atividades Micro'!$K3,"") | ... CC5: =IF(AND('Atividades Micro'!$B3=CC$2,'Atividades Micro'!$G3="Macro",'Atividades Micro'!$K3<>""),'Atividades Micro'!$K3,"") | CD5: =IF(AND('Atividades Micro'!$B3=CD$2,'Atividades Micro'!$G3="Micro",'Atividades Micro'!$K3<>""),'Atividades Micro'!$K3,"") | CE5: =IF(AND('Atividades Micro'!$B3=CE$2,'Atividades Micro'!$G3="Micro",'Atividades Micro'!$K3<>""),'Atividades Micro'!$K3,"") | CF5: =IF(AND('Atividades Micro'!$B3=CF$2,'Atividades Micro'!$G3="Micro",'Atividades Micro'!$K3<>""),'Atividades Micro'!$K3,"") | CG5: =IF(AND('Atividades Micro'!$B3=CG$2,'Atividades Micro'!$G3="Micro",'Atividades Micro'!$K3<>""),'Atividades Micro'!$K3,"") | CH5: =IF(AND('Atividades Micro'!$B3=CH$2,'Atividades Micro'!$G3="Micro",'Atividades Micro'!$K3<>""),'Atividades Micro'!$K3,"") | CI5: =IF(AND('Atividades Micro'!$B3=CI$2,'Atividades Micro'!$G3="Micro",'Atividades Micro'!$K3<>""),'Atividades Micro'!$K3,"") | CJ5: =IF(AND('Atividades Micro'!$B3=CJ$2,'Atividades Micro'!$G3="Micro",'Atividades Micro'!$K3<>""),'Atividades Micro'!$K3,"") | CK5: =IF(AND('Atividades Micro'!$B3=CK$2,'Atividades Micro'!$G3="Micro",'Atividades Micro'!$K3<>""),'Atividades Micro'!$K3,"") | ... CO5: =IF(AND('Atividades Micro'!$B3=CO$2,'Atividades Micro'!$G3="Micro",'Atividades Micro'!$K3<>""),'Atividades Micro'!$K3,"")
A6: =IF(AND('Atividades Micro'!$A4=A$2,'Atividades Micro'!$K4<>""),'Atividades Micro'!$K4,"") -> 46210 | B6: =IF(AND('Atividades Micro'!$A4=B$2,'Atividades Micro'!$L4<>""),'Atividades Micro'!$L4,"") -> 46231 | C6: =IF(AND('Atividades Micro'!$A4=C$2,'Atividades Micro'!$K4<>""),'Atividades Micro'!$K4,"") | D6: =IF(AND('Atividades Micro'!$A4=D$2,'Atividades Micro'!$L4<>""),'Atividades Micro'!$L4,"") | E6: =IF(AND('Atividades Micro'!$A4=E$2,'Atividades Micro'!$K4<>""),'Atividades Micro'!$K4,"") | F6: =IF(AND('Atividades Micro'!$A4=F$2,'Atividades Micro'!$L4<>""),'Atividades Micro'!$L4,"") | G6: =IF(AND('Atividades Micro'!$A4=G$2,'Atividades Micro'!$K4<>""),'Atividades Micro'!$K4,"") | H6: =IF(AND('Atividades Micro'!$A4=H$2,'Atividades Micro'!$L4<>""),'Atividades Micro'!$L4,"") | I6: =IF(AND('Atividades Micro'!$A4=I$2,'Atividades Micro'!$K4<>""),'Atividades Micro'!$K4,"") | J6: =IF(AND('Atividades Micro'!$A4=J$2,'Atividades Micro'!$L4<>""),'Atividades Micro'!$L4,"") | K6: =IF(AND('Atividades Micro'!$B4=K$2,'Atividades Micro'!$K4<>""),'Atividades Micro'!$K4,"") | L6: =IF(AND('Atividades Micro'!$B4=L$2,'Atividades Micro'!$L4<>""),'Atividades Micro'!$L4,"") | M6: =IF(AND('Atividades Micro'!$B4=M$2,'Atividades Micro'!$K4<>""),'Atividades Micro'!$K4,"") | N6: =IF(AND('Atividades Micro'!$B4=N$2,'Atividades Micro'!$L4<>""),'Atividades Micro'!$L4,"") | O6: =IF(AND('Atividades Micro'!$A4=O$2,'Atividades Micro'!$K4<>""),'Atividades Micro'!$K4,"") | P6: =IF(AND('Atividades Micro'!$A4=P$2,'Atividades Micro'!$L4<>""),'Atividades Micro'!$L4,"") | Q6: =IF(AND('Atividades Micro'!$B4=Q$2,'Atividades Micro'!$K4<>""),'Atividades Micro'!$K4,"") | R6: =IF(AND('Atividades Micro'!$B4=R$2,'Atividades Micro'!$L4<>""),'Atividades Micro'!$L4,"") | S6: =IF(AND('Atividades Micro'!$A4=S$2,'Atividades Micro'!$K4<>""),'Atividades Micro'!$K4,"") | T6: =IF(AND('Atividades Micro'!$A4=T$2,'Atividades Micro'!$L4<>""),'Atividades Micro'!$L4,"") | U6: =IF(AND('Atividades Micro'!$B4=U$2,'Atividades Micro'!$K4<>""),'Atividades Micro'!$K4,"") | V6: =IF(AND('Atividades Micro'!$B4=V$2,'Atividades Micro'!$L4<>""),'Atividades Micro'!$L4,"") | W6: =IF(AND('Atividades Micro'!$B4=W$2,'Atividades Micro'!$K4<>""),'Atividades Micro'!$K4,"") | X6: =IF(AND('Atividades Micro'!$B4=X$2,'Atividades Micro'!$L4<>""),'Atividades Micro'!$L4,"") | Y6: =IF(AND('Atividades Micro'!$A4=Y$2,'Atividades Micro'!$K4<>""),'Atividades Micro'!$K4,"") | Z6: =IF(AND('Atividades Micro'!$A4=Z$2,'Atividades Micro'!$L4<>""),'Atividades Micro'!$L4,"") | AA6: =IF(AND('Atividades Micro'!$B4=AA$2,'Atividades Micro'!$K4<>""),'Atividades Micro'!$K4,"") | AB6: =IF(AND('Atividades Micro'!$B4=AB$2,'Atividades Micro'!$L4<>""),'Atividades Micro'!$L4,"") | AC6: =IF(AND('Atividades Micro'!$B4=AC$2,'Atividades Micro'!$K4<>""),'Atividades Micro'!$K4,"") | AD6: =IF(AND('Atividades Micro'!$B4=AD$2,'Atividades Micro'!$L4<>""),'Atividades Micro'!$L4,"") | AE6: =IF(AND('Atividades Micro'!$A4=AE$2,'Atividades Micro'!$K4<>""),'Atividades Micro'!$K4,"") | AF6: =IF(AND('Atividades Micro'!$A4=AF$2,'Atividades Micro'!$L4<>""),'Atividades Micro'!$L4,"") | AG6: =IF(AND('Atividades Micro'!$B4=AG$2,'Atividades Micro'!$K4<>""),'Atividades Micro'!$K4,"") | AH6: =IF(AND('Atividades Micro'!$B4=AH$2,'Atividades Micro'!$L4<>""),'Atividades Micro'!$L4,"") | AI6: =IF(AND('Atividades Micro'!$B4=AI$2,'Atividades Micro'!$K4<>""),'Atividades Micro'!$K4,"") | AJ6: =IF(AND('Atividades Micro'!$B4=AJ$2,'Atividades Micro'!$L4<>""),'Atividades Micro'!$L4,"") | AK6: =IF(AND('Atividades Micro'!$A4=AK$2,'Atividades Micro'!$K4<>""),'Atividades Micro'!$K4,"") | AL6: =IF(AND('Atividades Micro'!$A4=AL$2,'Atividades Micro'!$L4<>""),'Atividades Micro'!$L4,"") | AM6: =IF(AND('Atividades Micro'!$B4=AM$2,'Atividades Micro'!$K4<>""),'Atividades Micro'!$K4,"") | AN6: =IF(AND('Atividades Micro'!$B4=AN$2,'Atividades Micro'!$L4<>""),'Atividades Micro'!$L4,"") | AO6: =IF(AND('Atividades Micro'!$B4=AO$2,'Atividades Micro'!$K4<>""),'Atividades Micro'!$K4,"") | AP6: =IF(AND('Atividades Micro'!$B4=AP$2,'Atividades Micro'!$L4<>""),'Atividades Micro'!$L4,"") | AQ6: =IF(AND('Atividades Micro'!$A4=AQ$2,'Atividades Micro'!$K4<>""),'Atividades Micro'!$K4,"") | AR6: =IF(AND('Atividades Micro'!$A4=AR$2,'Atividades Micro'!$L4<>""),'Atividades Micro'!$L4,"") | AS6: =IF(AND('Atividades Micro'!$B4=AS$2,'Atividades Micro'!$K4<>""),'Atividades Micro'!$K4,"") | AT6: =IF(AND('Atividades Micro'!$B4=AT$2,'Atividades Micro'!$L4<>""),'Atividades Micro'!$L4,"") | AU6: =IF(AND('Atividades Micro'!$A4=AU$2,'Atividades Micro'!$K4<>""),'Atividades Micro'!$K4,"") | AV6: =IF(AND('Atividades Micro'!$A4=AV$2,'Atividades Micro'!$L4<>""),'Atividades Micro'!$L4,"") | AW6: =IF(AND('Atividades Micro'!$B4=AW$2,'Atividades Micro'!$K4<>""),'Atividades Micro'!$K4,"") | AX6: =IF(AND('Atividades Micro'!$B4=AX$2,'Atividades Micro'!$L4<>""),'Atividades Micro'!$L4,"") | AY6: =IF(AND('Atividades Micro'!$A4=AY$2,'Atividades Micro'!$K4<>""),'Atividades Micro'!$K4,"") | AZ6: =IF(AND('Atividades Micro'!$A4=AZ$2,'Atividades Micro'!$L4<>""),'Atividades Micro'!$L4,"") | BA6: =IF(AND('Atividades Micro'!$B4=BA$2,'Atividades Micro'!$K4<>""),'Atividades Micro'!$K4,"") | BB6: =IF(AND('Atividades Micro'!$B4=BB$2,'Atividades Micro'!$L4<>""),'Atividades Micro'!$L4,"") | BC6: =IF(AND('Atividades Micro'!$B4=BC$2,'Atividades Micro'!$G4="Macro",'Atividades Micro'!$K4<>""),'Atividades Micro'!$K4,"") | BD6: =IF(AND('Atividades Micro'!$B4=BD$2,'Atividades Micro'!$G4="Macro",'Atividades Micro'!$K4<>""),'Atividades Micro'!$K4,"") | BE6: =IF(AND('Atividades Micro'!$B4=BE$2,'Atividades Micro'!$G4="Macro",'Atividades Micro'!$K4<>""),'Atividades Micro'!$K4,"") | BF6: =IF(AND('Atividades Micro'!$B4=BF$2,'Atividades Micro'!$G4="Macro",'Atividades Micro'!$K4<>""),'Atividades Micro'!$K4,"") | BG6: =IF(AND('Atividades Micro'!$B4=BG$2,'Atividades Micro'!$G4="Macro",'Atividades Micro'!$K4<>""),'Atividades Micro'!$K4,"") | BH6: =IF(AND('Atividades Micro'!$B4=BH$2,'Atividades Micro'!$G4="Macro",'Atividades Micro'!$K4<>""),'Atividades Micro'!$K4,"") | BI6: =IF(AND('Atividades Micro'!$B4=BI$2,'Atividades Micro'!$G4="Macro",'Atividades Micro'!$K4<>""),'Atividades Micro'!$K4,"") | BJ6: =IF(AND('Atividades Micro'!$B4=BJ$2,'Atividades Micro'!$G4="Macro",'Atividades Micro'!$K4<>""),'Atividades Micro'!$K4,"") | ... CC6: =IF(AND('Atividades Micro'!$B4=CC$2,'Atividades Micro'!$G4="Macro",'Atividades Micro'!$K4<>""),'Atividades Micro'!$K4,"") | CD6: =IF(AND('Atividades Micro'!$B4=CD$2,'Atividades Micro'!$G4="Micro",'Atividades Micro'!$K4<>""),'Atividades Micro'!$K4,"") | CE6: =IF(AND('Atividades Micro'!$B4=CE$2,'Atividades Micro'!$G4="Micro",'Atividades Micro'!$K4<>""),'Atividades Micro'!$K4,"") | CF6: =IF(AND('Atividades Micro'!$B4=CF$2,'Atividades Micro'!$G4="Micro",'Atividades Micro'!$K4<>""),'Atividades Micro'!$K4,"") | CG6: =IF(AND('Atividades Micro'!$B4=CG$2,'Atividades Micro'!$G4="Micro",'Atividades Micro'!$K4<>""),'Atividades Micro'!$K4,"") | CH6: =IF(AND('Atividades Micro'!$B4=CH$2,'Atividades Micro'!$G4="Micro",'Atividades Micro'!$K4<>""),'Atividades Micro'!$K4,"") | CI6: =IF(AND('Atividades Micro'!$B4=CI$2,'Atividades Micro'!$G4="Micro",'Atividades Micro'!$K4<>""),'Atividades Micro'!$K4,"") | CJ6: =IF(AND('Atividades Micro'!$B4=CJ$2,'Atividades Micro'!$G4="Micro",'Atividades Micro'!$K4<>""),'Atividades Micro'!$K4,"") | CK6: =IF(AND('Atividades Micro'!$B4=CK$2,'Atividades Micro'!$G4="Micro",'Atividades Micro'!$K4<>""),'Atividades Micro'!$K4,"") | ... CO6: =IF(AND('Atividades Micro'!$B4=CO$2,'Atividades Micro'!$G4="Micro",'Atividades Micro'!$K4<>""),'Atividades Micro'!$K4,"")
A7: =IF(AND('Atividades Micro'!$A5=A$2,'Atividades Micro'!$K5<>""),'Atividades Micro'!$K5,"") -> 46210 | B7: =IF(AND('Atividades Micro'!$A5=B$2,'Atividades Micro'!$L5<>""),'Atividades Micro'!$L5,"") | C7: =IF(AND('Atividades Micro'!$A5=C$2,'Atividades Micro'!$K5<>""),'Atividades Micro'!$K5,"") | D7: =IF(AND('Atividades Micro'!$A5=D$2,'Atividades Micro'!$L5<>""),'Atividades Micro'!$L5,"") | E7: =IF(AND('Atividades Micro'!$A5=E$2,'Atividades Micro'!$K5<>""),'Atividades Micro'!$K5,"") | F7: =IF(AND('Atividades Micro'!$A5=F$2,'Atividades Micro'!$L5<>""),'Atividades Micro'!$L5,"") | G7: =IF(AND('Atividades Micro'!$A5=G$2,'Atividades Micro'!$K5<>""),'Atividades Micro'!$K5,"") | H7: =IF(AND('Atividades Micro'!$A5=H$2,'Atividades Micro'!$L5<>""),'Atividades Micro'!$L5,"") | I7: =IF(AND('Atividades Micro'!$A5=I$2,'Atividades Micro'!$K5<>""),'Atividades Micro'!$K5,"") | J7: =IF(AND('Atividades Micro'!$A5=J$2,'Atividades Micro'!$L5<>""),'Atividades Micro'!$L5,"") | K7: =IF(AND('Atividades Micro'!$B5=K$2,'Atividades Micro'!$K5<>""),'Atividades Micro'!$K5,"") | L7: =IF(AND('Atividades Micro'!$B5=L$2,'Atividades Micro'!$L5<>""),'Atividades Micro'!$L5,"") | M7: =IF(AND('Atividades Micro'!$B5=M$2,'Atividades Micro'!$K5<>""),'Atividades Micro'!$K5,"") | N7: =IF(AND('Atividades Micro'!$B5=N$2,'Atividades Micro'!$L5<>""),'Atividades Micro'!$L5,"") | O7: =IF(AND('Atividades Micro'!$A5=O$2,'Atividades Micro'!$K5<>""),'Atividades Micro'!$K5,"") | P7: =IF(AND('Atividades Micro'!$A5=P$2,'Atividades Micro'!$L5<>""),'Atividades Micro'!$L5,"") | Q7: =IF(AND('Atividades Micro'!$B5=Q$2,'Atividades Micro'!$K5<>""),'Atividades Micro'!$K5,"") | R7: =IF(AND('Atividades Micro'!$B5=R$2,'Atividades Micro'!$L5<>""),'Atividades Micro'!$L5,"") | S7: =IF(AND('Atividades Micro'!$A5=S$2,'Atividades Micro'!$K5<>""),'Atividades Micro'!$K5,"") | T7: =IF(AND('Atividades Micro'!$A5=T$2,'Atividades Micro'!$L5<>""),'Atividades Micro'!$L5,"") | U7: =IF(AND('Atividades Micro'!$B5=U$2,'Atividades Micro'!$K5<>""),'Atividades Micro'!$K5,"") | V7: =IF(AND('Atividades Micro'!$B5=V$2,'Atividades Micro'!$L5<>""),'Atividades Micro'!$L5,"") | W7: =IF(AND('Atividades Micro'!$B5=W$2,'Atividades Micro'!$K5<>""),'Atividades Micro'!$K5,"") | X7: =IF(AND('Atividades Micro'!$B5=X$2,'Atividades Micro'!$L5<>""),'Atividades Micro'!$L5,"") | Y7: =IF(AND('Atividades Micro'!$A5=Y$2,'Atividades Micro'!$K5<>""),'Atividades Micro'!$K5,"") | Z7: =IF(AND('Atividades Micro'!$A5=Z$2,'Atividades Micro'!$L5<>""),'Atividades Micro'!$L5,"") | AA7: =IF(AND('Atividades Micro'!$B5=AA$2,'Atividades Micro'!$K5<>""),'Atividades Micro'!$K5,"") | AB7: =IF(AND('Atividades Micro'!$B5=AB$2,'Atividades Micro'!$L5<>""),'Atividades Micro'!$L5,"") | AC7: =IF(AND('Atividades Micro'!$B5=AC$2,'Atividades Micro'!$K5<>""),'Atividades Micro'!$K5,"") | AD7: =IF(AND('Atividades Micro'!$B5=AD$2,'Atividades Micro'!$L5<>""),'Atividades Micro'!$L5,"") | AE7: =IF(AND('Atividades Micro'!$A5=AE$2,'Atividades Micro'!$K5<>""),'Atividades Micro'!$K5,"") | AF7: =IF(AND('Atividades Micro'!$A5=AF$2,'Atividades Micro'!$L5<>""),'Atividades Micro'!$L5,"") | AG7: =IF(AND('Atividades Micro'!$B5=AG$2,'Atividades Micro'!$K5<>""),'Atividades Micro'!$K5,"") | AH7: =IF(AND('Atividades Micro'!$B5=AH$2,'Atividades Micro'!$L5<>""),'Atividades Micro'!$L5,"") | AI7: =IF(AND('Atividades Micro'!$B5=AI$2,'Atividades Micro'!$K5<>""),'Atividades Micro'!$K5,"") | AJ7: =IF(AND('Atividades Micro'!$B5=AJ$2,'Atividades Micro'!$L5<>""),'Atividades Micro'!$L5,"") | AK7: =IF(AND('Atividades Micro'!$A5=AK$2,'Atividades Micro'!$K5<>""),'Atividades Micro'!$K5,"") | AL7: =IF(AND('Atividades Micro'!$A5=AL$2,'Atividades Micro'!$L5<>""),'Atividades Micro'!$L5,"") | AM7: =IF(AND('Atividades Micro'!$B5=AM$2,'Atividades Micro'!$K5<>""),'Atividades Micro'!$K5,"") | AN7: =IF(AND('Atividades Micro'!$B5=AN$2,'Atividades Micro'!$L5<>""),'Atividades Micro'!$L5,"") | AO7: =IF(AND('Atividades Micro'!$B5=AO$2,'Atividades Micro'!$K5<>""),'Atividades Micro'!$K5,"") | AP7: =IF(AND('Atividades Micro'!$B5=AP$2,'Atividades Micro'!$L5<>""),'Atividades Micro'!$L5,"") | AQ7: =IF(AND('Atividades Micro'!$A5=AQ$2,'Atividades Micro'!$K5<>""),'Atividades Micro'!$K5,"") | AR7: =IF(AND('Atividades Micro'!$A5=AR$2,'Atividades Micro'!$L5<>""),'Atividades Micro'!$L5,"") | AS7: =IF(AND('Atividades Micro'!$B5=AS$2,'Atividades Micro'!$K5<>""),'Atividades Micro'!$K5,"") | AT7: =IF(AND('Atividades Micro'!$B5=AT$2,'Atividades Micro'!$L5<>""),'Atividades Micro'!$L5,"") | AU7: =IF(AND('Atividades Micro'!$A5=AU$2,'Atividades Micro'!$K5<>""),'Atividades Micro'!$K5,"") | AV7: =IF(AND('Atividades Micro'!$A5=AV$2,'Atividades Micro'!$L5<>""),'Atividades Micro'!$L5,"") | AW7: =IF(AND('Atividades Micro'!$B5=AW$2,'Atividades Micro'!$K5<>""),'Atividades Micro'!$K5,"") | AX7: =IF(AND('Atividades Micro'!$B5=AX$2,'Atividades Micro'!$L5<>""),'Atividades Micro'!$L5,"") | AY7: =IF(AND('Atividades Micro'!$A5=AY$2,'Atividades Micro'!$K5<>""),'Atividades Micro'!$K5,"") | AZ7: =IF(AND('Atividades Micro'!$A5=AZ$2,'Atividades Micro'!$L5<>""),'Atividades Micro'!$L5,"") | BA7: =IF(AND('Atividades Micro'!$B5=BA$2,'Atividades Micro'!$K5<>""),'Atividades Micro'!$K5,"") | BB7: =IF(AND('Atividades Micro'!$B5=BB$2,'Atividades Micro'!$L5<>""),'Atividades Micro'!$L5,"") | BC7: =IF(AND('Atividades Micro'!$B5=BC$2,'Atividades Micro'!$G5="Macro",'Atividades Micro'!$K5<>""),'Atividades Micro'!$K5,"") | BD7: =IF(AND('Atividades Micro'!$B5=BD$2,'Atividades Micro'!$G5="Macro",'Atividades Micro'!$K5<>""),'Atividades Micro'!$K5,"") | BE7: =IF(AND('Atividades Micro'!$B5=BE$2,'Atividades Micro'!$G5="Macro",'Atividades Micro'!$K5<>""),'Atividades Micro'!$K5,"") | BF7: =IF(AND('Atividades Micro'!$B5=BF$2,'Atividades Micro'!$G5="Macro",'Atividades Micro'!$K5<>""),'Atividades Micro'!$K5,"") | BG7: =IF(AND('Atividades Micro'!$B5=BG$2,'Atividades Micro'!$G5="Macro",'Atividades Micro'!$K5<>""),'Atividades Micro'!$K5,"") | BH7: =IF(AND('Atividades Micro'!$B5=BH$2,'Atividades Micro'!$G5="Macro",'Atividades Micro'!$K5<>""),'Atividades Micro'!$K5,"") | BI7: =IF(AND('Atividades Micro'!$B5=BI$2,'Atividades Micro'!$G5="Macro",'Atividades Micro'!$K5<>""),'Atividades Micro'!$K5,"") | BJ7: =IF(AND('Atividades Micro'!$B5=BJ$2,'Atividades Micro'!$G5="Macro",'Atividades Micro'!$K5<>""),'Atividades Micro'!$K5,"") | ... CC7: =IF(AND('Atividades Micro'!$B5=CC$2,'Atividades Micro'!$G5="Macro",'Atividades Micro'!$K5<>""),'Atividades Micro'!$K5,"") | CD7: =IF(AND('Atividades Micro'!$B5=CD$2,'Atividades Micro'!$G5="Micro",'Atividades Micro'!$K5<>""),'Atividades Micro'!$K5,"") | CE7: =IF(AND('Atividades Micro'!$B5=CE$2,'Atividades Micro'!$G5="Micro",'Atividades Micro'!$K5<>""),'Atividades Micro'!$K5,"") | CF7: =IF(AND('Atividades Micro'!$B5=CF$2,'Atividades Micro'!$G5="Micro",'Atividades Micro'!$K5<>""),'Atividades Micro'!$K5,"") | CG7: =IF(AND('Atividades Micro'!$B5=CG$2,'Atividades Micro'!$G5="Micro",'Atividades Micro'!$K5<>""),'Atividades Micro'!$K5,"") | CH7: =IF(AND('Atividades Micro'!$B5=CH$2,'Atividades Micro'!$G5="Micro",'Atividades Micro'!$K5<>""),'Atividades Micro'!$K5,"") | CI7: =IF(AND('Atividades Micro'!$B5=CI$2,'Atividades Micro'!$G5="Micro",'Atividades Micro'!$K5<>""),'Atividades Micro'!$K5,"") | CJ7: =IF(AND('Atividades Micro'!$B5=CJ$2,'Atividades Micro'!$G5="Micro",'Atividades Micro'!$K5<>""),'Atividades Micro'!$K5,"") | CK7: =IF(AND('Atividades Micro'!$B5=CK$2,'Atividades Micro'!$G5="Micro",'Atividades Micro'!$K5<>""),'Atividades Micro'!$K5,"") | ... CO7: =IF(AND('Atividades Micro'!$B5=CO$2,'Atividades Micro'!$G5="Micro",'Atividades Micro'!$K5<>""),'Atividades Micro'!$K5,"")
A8: =IF(AND('Atividades Micro'!$A6=A$2,'Atividades Micro'!$K6<>""),'Atividades Micro'!$K6,"") -> 46398 | B8: =IF(AND('Atividades Micro'!$A6=B$2,'Atividades Micro'!$L6<>""),'Atividades Micro'!$L6,"") | C8: =IF(AND('Atividades Micro'!$A6=C$2,'Atividades Micro'!$K6<>""),'Atividades Micro'!$K6,"") | D8: =IF(AND('Atividades Micro'!$A6=D$2,'Atividades Micro'!$L6<>""),'Atividades Micro'!$L6,"") | E8: =IF(AND('Atividades Micro'!$A6=E$2,'Atividades Micro'!$K6<>""),'Atividades Micro'!$K6,"") | F8: =IF(AND('Atividades Micro'!$A6=F$2,'Atividades Micro'!$L6<>""),'Atividades Micro'!$L6,"") | G8: =IF(AND('Atividades Micro'!$A6=G$2,'Atividades Micro'!$K6<>""),'Atividades Micro'!$K6,"") | H8: =IF(AND('Atividades Micro'!$A6=H$2,'Atividades Micro'!$L6<>""),'Atividades Micro'!$L6,"") | I8: =IF(AND('Atividades Micro'!$A6=I$2,'Atividades Micro'!$K6<>""),'Atividades Micro'!$K6,"") | J8: =IF(AND('Atividades Micro'!$A6=J$2,'Atividades Micro'!$L6<>""),'Atividades Micro'!$L6,"") | K8: =IF(AND('Atividades Micro'!$B6=K$2,'Atividades Micro'!$K6<>""),'Atividades Micro'!$K6,"") | L8: =IF(AND('Atividades Micro'!$B6=L$2,'Atividades Micro'!$L6<>""),'Atividades Micro'!$L6,"") | M8: =IF(AND('Atividades Micro'!$B6=M$2,'Atividades Micro'!$K6<>""),'Atividades Micro'!$K6,"") | N8: =IF(AND('Atividades Micro'!$B6=N$2,'Atividades Micro'!$L6<>""),'Atividades Micro'!$L6,"") | O8: =IF(AND('Atividades Micro'!$A6=O$2,'Atividades Micro'!$K6<>""),'Atividades Micro'!$K6,"") | P8: =IF(AND('Atividades Micro'!$A6=P$2,'Atividades Micro'!$L6<>""),'Atividades Micro'!$L6,"") | Q8: =IF(AND('Atividades Micro'!$B6=Q$2,'Atividades Micro'!$K6<>""),'Atividades Micro'!$K6,"") | R8: =IF(AND('Atividades Micro'!$B6=R$2,'Atividades Micro'!$L6<>""),'Atividades Micro'!$L6,"") | S8: =IF(AND('Atividades Micro'!$A6=S$2,'Atividades Micro'!$K6<>""),'Atividades Micro'!$K6,"") | T8: =IF(AND('Atividades Micro'!$A6=T$2,'Atividades Micro'!$L6<>""),'Atividades Micro'!$L6,"") | U8: =IF(AND('Atividades Micro'!$B6=U$2,'Atividades Micro'!$K6<>""),'Atividades Micro'!$K6,"") | V8: =IF(AND('Atividades Micro'!$B6=V$2,'Atividades Micro'!$L6<>""),'Atividades Micro'!$L6,"") | W8: =IF(AND('Atividades Micro'!$B6=W$2,'Atividades Micro'!$K6<>""),'Atividades Micro'!$K6,"") | X8: =IF(AND('Atividades Micro'!$B6=X$2,'Atividades Micro'!$L6<>""),'Atividades Micro'!$L6,"") | Y8: =IF(AND('Atividades Micro'!$A6=Y$2,'Atividades Micro'!$K6<>""),'Atividades Micro'!$K6,"") | Z8: =IF(AND('Atividades Micro'!$A6=Z$2,'Atividades Micro'!$L6<>""),'Atividades Micro'!$L6,"") | AA8: =IF(AND('Atividades Micro'!$B6=AA$2,'Atividades Micro'!$K6<>""),'Atividades Micro'!$K6,"") | AB8: =IF(AND('Atividades Micro'!$B6=AB$2,'Atividades Micro'!$L6<>""),'Atividades Micro'!$L6,"") | AC8: =IF(AND('Atividades Micro'!$B6=AC$2,'Atividades Micro'!$K6<>""),'Atividades Micro'!$K6,"") | AD8: =IF(AND('Atividades Micro'!$B6=AD$2,'Atividades Micro'!$L6<>""),'Atividades Micro'!$L6,"") | AE8: =IF(AND('Atividades Micro'!$A6=AE$2,'Atividades Micro'!$K6<>""),'Atividades Micro'!$K6,"") | AF8: =IF(AND('Atividades Micro'!$A6=AF$2,'Atividades Micro'!$L6<>""),'Atividades Micro'!$L6,"") | AG8: =IF(AND('Atividades Micro'!$B6=AG$2,'Atividades Micro'!$K6<>""),'Atividades Micro'!$K6,"") | AH8: =IF(AND('Atividades Micro'!$B6=AH$2,'Atividades Micro'!$L6<>""),'Atividades Micro'!$L6,"") | AI8: =IF(AND('Atividades Micro'!$B6=AI$2,'Atividades Micro'!$K6<>""),'Atividades Micro'!$K6,"") | AJ8: =IF(AND('Atividades Micro'!$B6=AJ$2,'Atividades Micro'!$L6<>""),'Atividades Micro'!$L6,"") | AK8: =IF(AND('Atividades Micro'!$A6=AK$2,'Atividades Micro'!$K6<>""),'Atividades Micro'!$K6,"") | AL8: =IF(AND('Atividades Micro'!$A6=AL$2,'Atividades Micro'!$L6<>""),'Atividades Micro'!$L6,"") | AM8: =IF(AND('Atividades Micro'!$B6=AM$2,'Atividades Micro'!$K6<>""),'Atividades Micro'!$K6,"") | AN8: =IF(AND('Atividades Micro'!$B6=AN$2,'Atividades Micro'!$L6<>""),'Atividades Micro'!$L6,"") | AO8: =IF(AND('Atividades Micro'!$B6=AO$2,'Atividades Micro'!$K6<>""),'Atividades Micro'!$K6,"") | AP8: =IF(AND('Atividades Micro'!$B6=AP$2,'Atividades Micro'!$L6<>""),'Atividades Micro'!$L6,"") | AQ8: =IF(AND('Atividades Micro'!$A6=AQ$2,'Atividades Micro'!$K6<>""),'Atividades Micro'!$K6,"") | AR8: =IF(AND('Atividades Micro'!$A6=AR$2,'Atividades Micro'!$L6<>""),'Atividades Micro'!$L6,"") | AS8: =IF(AND('Atividades Micro'!$B6=AS$2,'Atividades Micro'!$K6<>""),'Atividades Micro'!$K6,"") | AT8: =IF(AND('Atividades Micro'!$B6=AT$2,'Atividades Micro'!$L6<>""),'Atividades Micro'!$L6,"") | AU8: =IF(AND('Atividades Micro'!$A6=AU$2,'Atividades Micro'!$K6<>""),'Atividades Micro'!$K6,"") | AV8: =IF(AND('Atividades Micro'!$A6=AV$2,'Atividades Micro'!$L6<>""),'Atividades Micro'!$L6,"") | AW8: =IF(AND('Atividades Micro'!$B6=AW$2,'Atividades Micro'!$K6<>""),'Atividades Micro'!$K6,"") | AX8: =IF(AND('Atividades Micro'!$B6=AX$2,'Atividades Micro'!$L6<>""),'Atividades Micro'!$L6,"") | AY8: =IF(AND('Atividades Micro'!$A6=AY$2,'Atividades Micro'!$K6<>""),'Atividades Micro'!$K6,"") | AZ8: =IF(AND('Atividades Micro'!$A6=AZ$2,'Atividades Micro'!$L6<>""),'Atividades Micro'!$L6,"") | BA8: =IF(AND('Atividades Micro'!$B6=BA$2,'Atividades Micro'!$K6<>""),'Atividades Micro'!$K6,"") | BB8: =IF(AND('Atividades Micro'!$B6=BB$2,'Atividades Micro'!$L6<>""),'Atividades Micro'!$L6,"") | BC8: =IF(AND('Atividades Micro'!$B6=BC$2,'Atividades Micro'!$G6="Macro",'Atividades Micro'!$K6<>""),'Atividades Micro'!$K6,"") | BD8: =IF(AND('Atividades Micro'!$B6=BD$2,'Atividades Micro'!$G6="Macro",'Atividades Micro'!$K6<>""),'Atividades Micro'!$K6,"") | BE8: =IF(AND('Atividades Micro'!$B6=BE$2,'Atividades Micro'!$G6="Macro",'Atividades Micro'!$K6<>""),'Atividades Micro'!$K6,"") | BF8: =IF(AND('Atividades Micro'!$B6=BF$2,'Atividades Micro'!$G6="Macro",'Atividades Micro'!$K6<>""),'Atividades Micro'!$K6,"") | BG8: =IF(AND('Atividades Micro'!$B6=BG$2,'Atividades Micro'!$G6="Macro",'Atividades Micro'!$K6<>""),'Atividades Micro'!$K6,"") | BH8: =IF(AND('Atividades Micro'!$B6=BH$2,'Atividades Micro'!$G6="Macro",'Atividades Micro'!$K6<>""),'Atividades Micro'!$K6,"") | BI8: =IF(AND('Atividades Micro'!$B6=BI$2,'Atividades Micro'!$G6="Macro",'Atividades Micro'!$K6<>""),'Atividades Micro'!$K6,"") | BJ8: =IF(AND('Atividades Micro'!$B6=BJ$2,'Atividades Micro'!$G6="Macro",'Atividades Micro'!$K6<>""),'Atividades Micro'!$K6,"") | ... CC8: =IF(AND('Atividades Micro'!$B6=CC$2,'Atividades Micro'!$G6="Macro",'Atividades Micro'!$K6<>""),'Atividades Micro'!$K6,"") | CD8: =IF(AND('Atividades Micro'!$B6=CD$2,'Atividades Micro'!$G6="Micro",'Atividades Micro'!$K6<>""),'Atividades Micro'!$K6,"") | CE8: =IF(AND('Atividades Micro'!$B6=CE$2,'Atividades Micro'!$G6="Micro",'Atividades Micro'!$K6<>""),'Atividades Micro'!$K6,"") | CF8: =IF(AND('Atividades Micro'!$B6=CF$2,'Atividades Micro'!$G6="Micro",'Atividades Micro'!$K6<>""),'Atividades Micro'!$K6,"") | CG8: =IF(AND('Atividades Micro'!$B6=CG$2,'Atividades Micro'!$G6="Micro",'Atividades Micro'!$K6<>""),'Atividades Micro'!$K6,"") | CH8: =IF(AND('Atividades Micro'!$B6=CH$2,'Atividades Micro'!$G6="Micro",'Atividades Micro'!$K6<>""),'Atividades Micro'!$K6,"") | CI8: =IF(AND('Atividades Micro'!$B6=CI$2,'Atividades Micro'!$G6="Micro",'Atividades Micro'!$K6<>""),'Atividades Micro'!$K6,"") | CJ8: =IF(AND('Atividades Micro'!$B6=CJ$2,'Atividades Micro'!$G6="Micro",'Atividades Micro'!$K6<>""),'Atividades Micro'!$K6,"") | CK8: =IF(AND('Atividades Micro'!$B6=CK$2,'Atividades Micro'!$G6="Micro",'Atividades Micro'!$K6<>""),'Atividades Micro'!$K6,"") | ... CO8: =IF(AND('Atividades Micro'!$B6=CO$2,'Atividades Micro'!$G6="Micro",'Atividades Micro'!$K6<>""),'Atividades Micro'!$K6,"")
A9: =IF(AND('Atividades Micro'!$A7=A$2,'Atividades Micro'!$K7<>""),'Atividades Micro'!$K7,"") -> 46398 | B9: =IF(AND('Atividades Micro'!$A7=B$2,'Atividades Micro'!$L7<>""),'Atividades Micro'!$L7,"") | C9: =IF(AND('Atividades Micro'!$A7=C$2,'Atividades Micro'!$K7<>""),'Atividades Micro'!$K7,"") | D9: =IF(AND('Atividades Micro'!$A7=D$2,'Atividades Micro'!$L7<>""),'Atividades Micro'!$L7,"") | E9: =IF(AND('Atividades Micro'!$A7=E$2,'Atividades Micro'!$K7<>""),'Atividades Micro'!$K7,"") | F9: =IF(AND('Atividades Micro'!$A7=F$2,'Atividades Micro'!$L7<>""),'Atividades Micro'!$L7,"") | G9: =IF(AND('Atividades Micro'!$A7=G$2,'Atividades Micro'!$K7<>""),'Atividades Micro'!$K7,"") | H9: =IF(AND('Atividades Micro'!$A7=H$2,'Atividades Micro'!$L7<>""),'Atividades Micro'!$L7,"") | I9: =IF(AND('Atividades Micro'!$A7=I$2,'Atividades Micro'!$K7<>""),'Atividades Micro'!$K7,"") | J9: =IF(AND('Atividades Micro'!$A7=J$2,'Atividades Micro'!$L7<>""),'Atividades Micro'!$L7,"") | K9: =IF(AND('Atividades Micro'!$B7=K$2,'Atividades Micro'!$K7<>""),'Atividades Micro'!$K7,"") | L9: =IF(AND('Atividades Micro'!$B7=L$2,'Atividades Micro'!$L7<>""),'Atividades Micro'!$L7,"") | M9: =IF(AND('Atividades Micro'!$B7=M$2,'Atividades Micro'!$K7<>""),'Atividades Micro'!$K7,"") | N9: =IF(AND('Atividades Micro'!$B7=N$2,'Atividades Micro'!$L7<>""),'Atividades Micro'!$L7,"") | O9: =IF(AND('Atividades Micro'!$A7=O$2,'Atividades Micro'!$K7<>""),'Atividades Micro'!$K7,"") | P9: =IF(AND('Atividades Micro'!$A7=P$2,'Atividades Micro'!$L7<>""),'Atividades Micro'!$L7,"") | Q9: =IF(AND('Atividades Micro'!$B7=Q$2,'Atividades Micro'!$K7<>""),'Atividades Micro'!$K7,"") | R9: =IF(AND('Atividades Micro'!$B7=R$2,'Atividades Micro'!$L7<>""),'Atividades Micro'!$L7,"") | S9: =IF(AND('Atividades Micro'!$A7=S$2,'Atividades Micro'!$K7<>""),'Atividades Micro'!$K7,"") | T9: =IF(AND('Atividades Micro'!$A7=T$2,'Atividades Micro'!$L7<>""),'Atividades Micro'!$L7,"") | U9: =IF(AND('Atividades Micro'!$B7=U$2,'Atividades Micro'!$K7<>""),'Atividades Micro'!$K7,"") | V9: =IF(AND('Atividades Micro'!$B7=V$2,'Atividades Micro'!$L7<>""),'Atividades Micro'!$L7,"") | W9: =IF(AND('Atividades Micro'!$B7=W$2,'Atividades Micro'!$K7<>""),'Atividades Micro'!$K7,"") | X9: =IF(AND('Atividades Micro'!$B7=X$2,'Atividades Micro'!$L7<>""),'Atividades Micro'!$L7,"") | Y9: =IF(AND('Atividades Micro'!$A7=Y$2,'Atividades Micro'!$K7<>""),'Atividades Micro'!$K7,"") | Z9: =IF(AND('Atividades Micro'!$A7=Z$2,'Atividades Micro'!$L7<>""),'Atividades Micro'!$L7,"") | AA9: =IF(AND('Atividades Micro'!$B7=AA$2,'Atividades Micro'!$K7<>""),'Atividades Micro'!$K7,"") | AB9: =IF(AND('Atividades Micro'!$B7=AB$2,'Atividades Micro'!$L7<>""),'Atividades Micro'!$L7,"") | AC9: =IF(AND('Atividades Micro'!$B7=AC$2,'Atividades Micro'!$K7<>""),'Atividades Micro'!$K7,"") | AD9: =IF(AND('Atividades Micro'!$B7=AD$2,'Atividades Micro'!$L7<>""),'Atividades Micro'!$L7,"") | AE9: =IF(AND('Atividades Micro'!$A7=AE$2,'Atividades Micro'!$K7<>""),'Atividades Micro'!$K7,"") | AF9: =IF(AND('Atividades Micro'!$A7=AF$2,'Atividades Micro'!$L7<>""),'Atividades Micro'!$L7,"") | AG9: =IF(AND('Atividades Micro'!$B7=AG$2,'Atividades Micro'!$K7<>""),'Atividades Micro'!$K7,"") | AH9: =IF(AND('Atividades Micro'!$B7=AH$2,'Atividades Micro'!$L7<>""),'Atividades Micro'!$L7,"") | AI9: =IF(AND('Atividades Micro'!$B7=AI$2,'Atividades Micro'!$K7<>""),'Atividades Micro'!$K7,"") | AJ9: =IF(AND('Atividades Micro'!$B7=AJ$2,'Atividades Micro'!$L7<>""),'Atividades Micro'!$L7,"") | AK9: =IF(AND('Atividades Micro'!$A7=AK$2,'Atividades Micro'!$K7<>""),'Atividades Micro'!$K7,"") | AL9: =IF(AND('Atividades Micro'!$A7=AL$2,'Atividades Micro'!$L7<>""),'Atividades Micro'!$L7,"") | AM9: =IF(AND('Atividades Micro'!$B7=AM$2,'Atividades Micro'!$K7<>""),'Atividades Micro'!$K7,"") | AN9: =IF(AND('Atividades Micro'!$B7=AN$2,'Atividades Micro'!$L7<>""),'Atividades Micro'!$L7,"") | AO9: =IF(AND('Atividades Micro'!$B7=AO$2,'Atividades Micro'!$K7<>""),'Atividades Micro'!$K7,"") | AP9: =IF(AND('Atividades Micro'!$B7=AP$2,'Atividades Micro'!$L7<>""),'Atividades Micro'!$L7,"") | AQ9: =IF(AND('Atividades Micro'!$A7=AQ$2,'Atividades Micro'!$K7<>""),'Atividades Micro'!$K7,"") | AR9: =IF(AND('Atividades Micro'!$A7=AR$2,'Atividades Micro'!$L7<>""),'Atividades Micro'!$L7,"") | AS9: =IF(AND('Atividades Micro'!$B7=AS$2,'Atividades Micro'!$K7<>""),'Atividades Micro'!$K7,"") | AT9: =IF(AND('Atividades Micro'!$B7=AT$2,'Atividades Micro'!$L7<>""),'Atividades Micro'!$L7,"") | AU9: =IF(AND('Atividades Micro'!$A7=AU$2,'Atividades Micro'!$K7<>""),'Atividades Micro'!$K7,"") | AV9: =IF(AND('Atividades Micro'!$A7=AV$2,'Atividades Micro'!$L7<>""),'Atividades Micro'!$L7,"") | AW9: =IF(AND('Atividades Micro'!$B7=AW$2,'Atividades Micro'!$K7<>""),'Atividades Micro'!$K7,"") | AX9: =IF(AND('Atividades Micro'!$B7=AX$2,'Atividades Micro'!$L7<>""),'Atividades Micro'!$L7,"") | AY9: =IF(AND('Atividades Micro'!$A7=AY$2,'Atividades Micro'!$K7<>""),'Atividades Micro'!$K7,"") | AZ9: =IF(AND('Atividades Micro'!$A7=AZ$2,'Atividades Micro'!$L7<>""),'Atividades Micro'!$L7,"") | BA9: =IF(AND('Atividades Micro'!$B7=BA$2,'Atividades Micro'!$K7<>""),'Atividades Micro'!$K7,"") | BB9: =IF(AND('Atividades Micro'!$B7=BB$2,'Atividades Micro'!$L7<>""),'Atividades Micro'!$L7,"") | BC9: =IF(AND('Atividades Micro'!$B7=BC$2,'Atividades Micro'!$G7="Macro",'Atividades Micro'!$K7<>""),'Atividades Micro'!$K7,"") | BD9: =IF(AND('Atividades Micro'!$B7=BD$2,'Atividades Micro'!$G7="Macro",'Atividades Micro'!$K7<>""),'Atividades Micro'!$K7,"") | BE9: =IF(AND('Atividades Micro'!$B7=BE$2,'Atividades Micro'!$G7="Macro",'Atividades Micro'!$K7<>""),'Atividades Micro'!$K7,"") | BF9: =IF(AND('Atividades Micro'!$B7=BF$2,'Atividades Micro'!$G7="Macro",'Atividades Micro'!$K7<>""),'Atividades Micro'!$K7,"") | BG9: =IF(AND('Atividades Micro'!$B7=BG$2,'Atividades Micro'!$G7="Macro",'Atividades Micro'!$K7<>""),'Atividades Micro'!$K7,"") | BH9: =IF(AND('Atividades Micro'!$B7=BH$2,'Atividades Micro'!$G7="Macro",'Atividades Micro'!$K7<>""),'Atividades Micro'!$K7,"") | BI9: =IF(AND('Atividades Micro'!$B7=BI$2,'Atividades Micro'!$G7="Macro",'Atividades Micro'!$K7<>""),'Atividades Micro'!$K7,"") | BJ9: =IF(AND('Atividades Micro'!$B7=BJ$2,'Atividades Micro'!$G7="Macro",'Atividades Micro'!$K7<>""),'Atividades Micro'!$K7,"") | ... CC9: =IF(AND('Atividades Micro'!$B7=CC$2,'Atividades Micro'!$G7="Macro",'Atividades Micro'!$K7<>""),'Atividades Micro'!$K7,"") | CD9: =IF(AND('Atividades Micro'!$B7=CD$2,'Atividades Micro'!$G7="Micro",'Atividades Micro'!$K7<>""),'Atividades Micro'!$K7,"") | CE9: =IF(AND('Atividades Micro'!$B7=CE$2,'Atividades Micro'!$G7="Micro",'Atividades Micro'!$K7<>""),'Atividades Micro'!$K7,"") | CF9: =IF(AND('Atividades Micro'!$B7=CF$2,'Atividades Micro'!$G7="Micro",'Atividades Micro'!$K7<>""),'Atividades Micro'!$K7,"") | CG9: =IF(AND('Atividades Micro'!$B7=CG$2,'Atividades Micro'!$G7="Micro",'Atividades Micro'!$K7<>""),'Atividades Micro'!$K7,"") | CH9: =IF(AND('Atividades Micro'!$B7=CH$2,'Atividades Micro'!$G7="Micro",'Atividades Micro'!$K7<>""),'Atividades Micro'!$K7,"") | CI9: =IF(AND('Atividades Micro'!$B7=CI$2,'Atividades Micro'!$G7="Micro",'Atividades Micro'!$K7<>""),'Atividades Micro'!$K7,"") | CJ9: =IF(AND('Atividades Micro'!$B7=CJ$2,'Atividades Micro'!$G7="Micro",'Atividades Micro'!$K7<>""),'Atividades Micro'!$K7,"") | CK9: =IF(AND('Atividades Micro'!$B7=CK$2,'Atividades Micro'!$G7="Micro",'Atividades Micro'!$K7<>""),'Atividades Micro'!$K7,"") | ... CO9: =IF(AND('Atividades Micro'!$B7=CO$2,'Atividades Micro'!$G7="Micro",'Atividades Micro'!$K7<>""),'Atividades Micro'!$K7,"")
A10: =IF(AND('Atividades Micro'!$A8=A$2,'Atividades Micro'!$K8<>""),'Atividades Micro'!$K8,"") -> 46568 | B10: =IF(AND('Atividades Micro'!$A8=B$2,'Atividades Micro'!$L8<>""),'Atividades Micro'!$L8,"") | C10: =IF(AND('Atividades Micro'!$A8=C$2,'Atividades Micro'!$K8<>""),'Atividades Micro'!$K8,"") | D10: =IF(AND('Atividades Micro'!$A8=D$2,'Atividades Micro'!$L8<>""),'Atividades Micro'!$L8,"") | E10: =IF(AND('Atividades Micro'!$A8=E$2,'Atividades Micro'!$K8<>""),'Atividades Micro'!$K8,"") | F10: =IF(AND('Atividades Micro'!$A8=F$2,'Atividades Micro'!$L8<>""),'Atividades Micro'!$L8,"") | G10: =IF(AND('Atividades Micro'!$A8=G$2,'Atividades Micro'!$K8<>""),'Atividades Micro'!$K8,"") | H10: =IF(AND('Atividades Micro'!$A8=H$2,'Atividades Micro'!$L8<>""),'Atividades Micro'!$L8,"") | I10: =IF(AND('Atividades Micro'!$A8=I$2,'Atividades Micro'!$K8<>""),'Atividades Micro'!$K8,"") | J10: =IF(AND('Atividades Micro'!$A8=J$2,'Atividades Micro'!$L8<>""),'Atividades Micro'!$L8,"") | K10: =IF(AND('Atividades Micro'!$B8=K$2,'Atividades Micro'!$K8<>""),'Atividades Micro'!$K8,"") | L10: =IF(AND('Atividades Micro'!$B8=L$2,'Atividades Micro'!$L8<>""),'Atividades Micro'!$L8,"") | M10: =IF(AND('Atividades Micro'!$B8=M$2,'Atividades Micro'!$K8<>""),'Atividades Micro'!$K8,"") | N10: =IF(AND('Atividades Micro'!$B8=N$2,'Atividades Micro'!$L8<>""),'Atividades Micro'!$L8,"") | O10: =IF(AND('Atividades Micro'!$A8=O$2,'Atividades Micro'!$K8<>""),'Atividades Micro'!$K8,"") | P10: =IF(AND('Atividades Micro'!$A8=P$2,'Atividades Micro'!$L8<>""),'Atividades Micro'!$L8,"") | Q10: =IF(AND('Atividades Micro'!$B8=Q$2,'Atividades Micro'!$K8<>""),'Atividades Micro'!$K8,"") | R10: =IF(AND('Atividades Micro'!$B8=R$2,'Atividades Micro'!$L8<>""),'Atividades Micro'!$L8,"") | S10: =IF(AND('Atividades Micro'!$A8=S$2,'Atividades Micro'!$K8<>""),'Atividades Micro'!$K8,"") | T10: =IF(AND('Atividades Micro'!$A8=T$2,'Atividades Micro'!$L8<>""),'Atividades Micro'!$L8,"") | U10: =IF(AND('Atividades Micro'!$B8=U$2,'Atividades Micro'!$K8<>""),'Atividades Micro'!$K8,"") | V10: =IF(AND('Atividades Micro'!$B8=V$2,'Atividades Micro'!$L8<>""),'Atividades Micro'!$L8,"") | W10: =IF(AND('Atividades Micro'!$B8=W$2,'Atividades Micro'!$K8<>""),'Atividades Micro'!$K8,"") | X10: =IF(AND('Atividades Micro'!$B8=X$2,'Atividades Micro'!$L8<>""),'Atividades Micro'!$L8,"") | Y10: =IF(AND('Atividades Micro'!$A8=Y$2,'Atividades Micro'!$K8<>""),'Atividades Micro'!$K8,"") | Z10: =IF(AND('Atividades Micro'!$A8=Z$2,'Atividades Micro'!$L8<>""),'Atividades Micro'!$L8,"") | AA10: =IF(AND('Atividades Micro'!$B8=AA$2,'Atividades Micro'!$K8<>""),'Atividades Micro'!$K8,"") | AB10: =IF(AND('Atividades Micro'!$B8=AB$2,'Atividades Micro'!$L8<>""),'Atividades Micro'!$L8,"") | AC10: =IF(AND('Atividades Micro'!$B8=AC$2,'Atividades Micro'!$K8<>""),'Atividades Micro'!$K8,"") | AD10: =IF(AND('Atividades Micro'!$B8=AD$2,'Atividades Micro'!$L8<>""),'Atividades Micro'!$L8,"") | AE10: =IF(AND('Atividades Micro'!$A8=AE$2,'Atividades Micro'!$K8<>""),'Atividades Micro'!$K8,"") | AF10: =IF(AND('Atividades Micro'!$A8=AF$2,'Atividades Micro'!$L8<>""),'Atividades Micro'!$L8,"") | AG10: =IF(AND('Atividades Micro'!$B8=AG$2,'Atividades Micro'!$K8<>""),'Atividades Micro'!$K8,"") | AH10: =IF(AND('Atividades Micro'!$B8=AH$2,'Atividades Micro'!$L8<>""),'Atividades Micro'!$L8,"") | AI10: =IF(AND('Atividades Micro'!$B8=AI$2,'Atividades Micro'!$K8<>""),'Atividades Micro'!$K8,"") | AJ10: =IF(AND('Atividades Micro'!$B8=AJ$2,'Atividades Micro'!$L8<>""),'Atividades Micro'!$L8,"") | AK10: =IF(AND('Atividades Micro'!$A8=AK$2,'Atividades Micro'!$K8<>""),'Atividades Micro'!$K8,"") | AL10: =IF(AND('Atividades Micro'!$A8=AL$2,'Atividades Micro'!$L8<>""),'Atividades Micro'!$L8,"") | AM10: =IF(AND('Atividades Micro'!$B8=AM$2,'Atividades Micro'!$K8<>""),'Atividades Micro'!$K8,"") | AN10: =IF(AND('Atividades Micro'!$B8=AN$2,'Atividades Micro'!$L8<>""),'Atividades Micro'!$L8,"") | AO10: =IF(AND('Atividades Micro'!$B8=AO$2,'Atividades Micro'!$K8<>""),'Atividades Micro'!$K8,"") | AP10: =IF(AND('Atividades Micro'!$B8=AP$2,'Atividades Micro'!$L8<>""),'Atividades Micro'!$L8,"") | AQ10: =IF(AND('Atividades Micro'!$A8=AQ$2,'Atividades Micro'!$K8<>""),'Atividades Micro'!$K8,"") | AR10: =IF(AND('Atividades Micro'!$A8=AR$2,'Atividades Micro'!$L8<>""),'Atividades Micro'!$L8,"") | AS10: =IF(AND('Atividades Micro'!$B8=AS$2,'Atividades Micro'!$K8<>""),'Atividades Micro'!$K8,"") | AT10: =IF(AND('Atividades Micro'!$B8=AT$2,'Atividades Micro'!$L8<>""),'Atividades Micro'!$L8,"") | AU10: =IF(AND('Atividades Micro'!$A8=AU$2,'Atividades Micro'!$K8<>""),'Atividades Micro'!$K8,"") | AV10: =IF(AND('Atividades Micro'!$A8=AV$2,'Atividades Micro'!$L8<>""),'Atividades Micro'!$L8,"") | AW10: =IF(AND('Atividades Micro'!$B8=AW$2,'Atividades Micro'!$K8<>""),'Atividades Micro'!$K8,"") | AX10: =IF(AND('Atividades Micro'!$B8=AX$2,'Atividades Micro'!$L8<>""),'Atividades Micro'!$L8,"") | AY10: =IF(AND('Atividades Micro'!$A8=AY$2,'Atividades Micro'!$K8<>""),'Atividades Micro'!$K8,"") | AZ10: =IF(AND('Atividades Micro'!$A8=AZ$2,'Atividades Micro'!$L8<>""),'Atividades Micro'!$L8,"") | BA10: =IF(AND('Atividades Micro'!$B8=BA$2,'Atividades Micro'!$K8<>""),'Atividades Micro'!$K8,"") | BB10: =IF(AND('Atividades Micro'!$B8=BB$2,'Atividades Micro'!$L8<>""),'Atividades Micro'!$L8,"") | BC10: =IF(AND('Atividades Micro'!$B8=BC$2,'Atividades Micro'!$G8="Macro",'Atividades Micro'!$K8<>""),'Atividades Micro'!$K8,"") | BD10: =IF(AND('Atividades Micro'!$B8=BD$2,'Atividades Micro'!$G8="Macro",'Atividades Micro'!$K8<>""),'Atividades Micro'!$K8,"") | BE10: =IF(AND('Atividades Micro'!$B8=BE$2,'Atividades Micro'!$G8="Macro",'Atividades Micro'!$K8<>""),'Atividades Micro'!$K8,"") | BF10: =IF(AND('Atividades Micro'!$B8=BF$2,'Atividades Micro'!$G8="Macro",'Atividades Micro'!$K8<>""),'Atividades Micro'!$K8,"") | BG10: =IF(AND('Atividades Micro'!$B8=BG$2,'Atividades Micro'!$G8="Macro",'Atividades Micro'!$K8<>""),'Atividades Micro'!$K8,"") | BH10: =IF(AND('Atividades Micro'!$B8=BH$2,'Atividades Micro'!$G8="Macro",'Atividades Micro'!$K8<>""),'Atividades Micro'!$K8,"") | BI10: =IF(AND('Atividades Micro'!$B8=BI$2,'Atividades Micro'!$G8="Macro",'Atividades Micro'!$K8<>""),'Atividades Micro'!$K8,"") | BJ10: =IF(AND('Atividades Micro'!$B8=BJ$2,'Atividades Micro'!$G8="Macro",'Atividades Micro'!$K8<>""),'Atividades Micro'!$K8,"") | ... CC10: =IF(AND('Atividades Micro'!$B8=CC$2,'Atividades Micro'!$G8="Macro",'Atividades Micro'!$K8<>""),'Atividades Micro'!$K8,"") | CD10: =IF(AND('Atividades Micro'!$B8=CD$2,'Atividades Micro'!$G8="Micro",'Atividades Micro'!$K8<>""),'Atividades Micro'!$K8,"") | CE10: =IF(AND('Atividades Micro'!$B8=CE$2,'Atividades Micro'!$G8="Micro",'Atividades Micro'!$K8<>""),'Atividades Micro'!$K8,"") | CF10: =IF(AND('Atividades Micro'!$B8=CF$2,'Atividades Micro'!$G8="Micro",'Atividades Micro'!$K8<>""),'Atividades Micro'!$K8,"") | CG10: =IF(AND('Atividades Micro'!$B8=CG$2,'Atividades Micro'!$G8="Micro",'Atividades Micro'!$K8<>""),'Atividades Micro'!$K8,"") | CH10: =IF(AND('Atividades Micro'!$B8=CH$2,'Atividades Micro'!$G8="Micro",'Atividades Micro'!$K8<>""),'Atividades Micro'!$K8,"") | CI10: =IF(AND('Atividades Micro'!$B8=CI$2,'Atividades Micro'!$G8="Micro",'Atividades Micro'!$K8<>""),'Atividades Micro'!$K8,"") | CJ10: =IF(AND('Atividades Micro'!$B8=CJ$2,'Atividades Micro'!$G8="Micro",'Atividades Micro'!$K8<>""),'Atividades Micro'!$K8,"") | CK10: =IF(AND('Atividades Micro'!$B8=CK$2,'Atividades Micro'!$G8="Micro",'Atividades Micro'!$K8<>""),'Atividades Micro'!$K8,"") | ... CO10: =IF(AND('Atividades Micro'!$B8=CO$2,'Atividades Micro'!$G8="Micro",'Atividades Micro'!$K8<>""),'Atividades Micro'!$K8,"")
